Workbook

Sheet CRUSCOTTO
B2: Genere | C2: Sottogenere | D2: # TOT schede | F2: # Ordinarie | G2: # Varianti | H2: Avanzamento | I2: # Mancanti | J2: Valore G25 | L2: Ordinarie | P2: Varianti | T2: Genere | U2: Sottogenere | V2: # TOT schede | X2: # In collezione | Y2: Varianti | Z2: Avanzamento | AA2: # Mancanti | AB2: Valore G26
L3: Nuove | M3: Usate | N3: 2a Scelta | O3: Mancanti | P3: Nuove | Q3: Usate | R3: 2a Scelta | S3: Mancanti
B4: Precursorie | C4: 1. Sida | D4: =SUM(E4:E7) -> 287 | E4: =IF(COUNTIF('1. Precursorie'!B:B,CRUSCOTTO!C4)=(CRUSCOTTO!F4+CRUSCOTTO!G4),CRUSCOTTO!F4+CRUSCOTTO!G4,"Errore") -> 99 | F4: =COUNTIFS('1. Precursorie'!B:B,CRUSCOTTO!C4,'1. Precursorie'!J:J,"-") -> 60 | G4: =COUNTIFS('1. Precursorie'!B:B,CRUSCOTTO!C4,'1. Precursorie'!J:J,"Variante") -> 39 | H4: =(E4-I4)/E4 -> 0.74747475 | I4: =IF(G4=0,O4,O4+S4) -> 25 | J4: =SUMIF('1. Precursorie'!B:B,CRUSCOTTO!C4,'1. Precursorie'!S:S) -> 3630 | L4: =COUNTIFS('1. Precursorie'!B:B,CRUSCOTTO!C4,'1. Precursorie'!J:J,"-",'1. Precursorie'!P:P,"Nuova") -> 26 | M4: =COUNTIFS('1. Precursorie'!B:B,CRUSCOTTO!C4,'1. Precursorie'!J:J,"-",'1. Precursorie'!P:P,"Usata") -> 24 | N4: =COUNTIFS('1. Precursorie'!B:B,CRUSCOTTO!C4,'1. Precursorie'!J:J,"-",'1. Precursorie'!P:P,"2a scelta") -> 1 | O4: =COUNTIFS('1. Precursorie'!B:B,CRUSCOTTO!C4,'1. Precursorie'!J:J,"-",'1. Precursorie'!P:P,"Manca") -> 9 | P4: =IF(G4=0,"-",COUNTIFS('1. Precursorie'!B:B,CRUSCOTTO!C4,'1. Precursorie'!J:J,"Variante",'1. Precursorie'!P:P,"Nuova")) -> 8 | Q4: =IF(G4=0,"-",COUNTIFS('1. Precursorie'!B:B,CRUSCOTTO!C4,'1. Precursorie'!J:J,"Variante",'1. Precursorie'!P:P,"Usata")) -> 13 | R4: =IF(G4=0,"-",COUNTIFS('1. Precursorie'!B:B,CRUSCOTTO!C4,'1. Precursorie'!J:J,"Variante",'1. Precursorie'!P:P,"2a scelta")) -> 2 | S4: =IF(G4=0,"-",COUNTIFS('1. Precursorie'!B:B,CRUSCOTTO!C4,'1. Precursorie'!J:J,"Variante",'1. Precursorie'!P:P,"Manca")) -> 16 | T4: Internazionali | U4: 1. Ordinarie | V4: =SUM(W4:W7) -> 767 | W4: =COUNTIF('13. Internazionali'!B:B,"13. Internazionali")-COUNTIF('13. Internazionali'!P:P,"n/a") -> 332 | X4: =COUNTIF('13. Internazionali'!P:P,"Nuova")+COUNTIF('13. Internazionali'!P:P,"Usata")+COUNTIF('13. Internazionali'!P:P,"2a Scelta") -> 190 | Y4: - | Z4: =(X4)/W4 -> 0.57228916 | AA4: =COUNTIF('13. Internazionali'!P:P,"Manca") -> 138 | AB4: =SUMIF('13. Internazionali'!P:P,"Usata",'13. Internazionali'!M:M)+1.5*SUMIF('13. Internazionali'!P:P,"Nuova",'13. Internazionali'!M:M) -> 1216.5
C5: 2. Urmet | E5: =IF(COUNTIF('1. Precursorie'!B:B,CRUSCOTTO!C5)=(CRUSCOTTO!F5+CRUSCOTTO!G5),CRUSCOTTO!F5+CRUSCOTTO!G5,"Errore") -> 23 | F5: =COUNTIFS('1. Precursorie'!B:B,CRUSCOTTO!C5,'1. Precursorie'!J:J,"-") -> 13 | G5: =COUNTIFS('1. Precursorie'!B:B,CRUSCOTTO!C5,'1. Precursorie'!J:J,"Variante") -> 10 | H5: =(E5-I5)/E5 -> 0.95652174 | I5: =IF(G5=0,O5,O5+S5) -> 1 | J5: =SUMIF('1. Precursorie'!B:B,CRUSCOTTO!C5,'1. Precursorie'!S:S) -> 2342 | L5: =COUNTIFS('1. Precursorie'!B:B,CRUSCOTTO!C5,'1. Precursorie'!J:J,"-",'1. Precursorie'!P:P,"Nuova") -> 10 | M5: =COUNTIFS('1. Precursorie'!B:B,CRUSCOTTO!C5,'1. Precursorie'!J:J,"-",'1. Precursorie'!P:P,"Usata") -> 3 | N5: =COUNTIFS('1. Precursorie'!B:B,CRUSCOTTO!C5,'1. Precursorie'!J:J,"-",'1. Precursorie'!P:P,"2a scelta") -> 0 | O5: =COUNTIFS('1. Precursorie'!B:B,CRUSCOTTO!C5,'1. Precursorie'!J:J,"-",'1. Precursorie'!P:P,"Manca") -> 0 | P5: =IF(G5=0,"-",COUNTIFS('1. Precursorie'!B:B,CRUSCOTTO!C5,'1. Precursorie'!J:J,"Variante",'1. Precursorie'!P:P,"Nuova")) -> 4 | Q5: =IF(G5=0,"-",COUNTIFS('1. Precursorie'!B:B,CRUSCOTTO!C5,'1. Precursorie'!J:J,"Variante",'1. Precursorie'!P:P,"Usata")) -> 5 | R5: =IF(G5=0,"-",COUNTIFS('1. Precursorie'!B:B,CRUSCOTTO!C5,'1. Precursorie'!J:J,"Variante",'1. Precursorie'!P:P,"2a scelta")) -> 0 | S5: =IF(G5=0,"-",COUNTIFS('1. Precursorie'!B:B,CRUSCOTTO!C5,'1. Precursorie'!J:J,"Variante",'1. Precursorie'!P:P,"Manca")) -> 1 | U5: 2. Test | W5: =COUNTIF('13. Internazionali'!B:B,"13. Internazionali")-COUNTIF('13. Internazionali'!R:R,"n/a") -> 111 | X5: =COUNTIF('13. Internazionali'!R:R,"Nuova")+COUNTIF('13. Internazionali'!R:R,"Usata")+COUNTIF('13. Internazionali'!R:R,"2a Scelta") -> 34 | Y5: - | Z5: =(X5)/W5 -> 0.30630631 | AA5: =COUNTIF('13. Internazionali'!R:R,"Manca") -> 77 | AB5: =SUMIF('13. Internazionali'!R:R,"Usata",'13. Internazionali'!N:N)+1.5*SUMIF('13. Internazionali'!R:R,"Nuova",'13. Internazionali'!N:N) -> 208
C6: 3. Studi e prove | E6: =IF(COUNTIF('1. Precursorie'!B:B,CRUSCOTTO!C6)=(CRUSCOTTO!F6+CRUSCOTTO!G6),CRUSCOTTO!F6+CRUSCOTTO!G6,"Errore") -> 11 | F6: =COUNTIFS('1. Precursorie'!B:B,CRUSCOTTO!C6,'1. Precursorie'!J:J,"-") -> 11 | G6: =COUNTIFS('1. Precursorie'!B:B,CRUSCOTTO!C6,'1. Precursorie'!J:J,"Variante") -> 0 | H6: =(E6-I6)/E6 -> 0.72727273 | I6: =IF(G6=0,O6,O6+S6) -> 3 | J6: =SUMIF('1. Precursorie'!B:B,CRUSCOTTO!C6,'1. Precursorie'!S:S) -> 400 | L6: =COUNTIFS('1. Precursorie'!B:B,CRUSCOTTO!C6,'1. Precursorie'!J:J,"-",'1. Precursorie'!P:P,"Nuova") -> 6 | M6: =COUNTIFS('1. Precursorie'!B:B,CRUSCOTTO!C6,'1. Precursorie'!J:J,"-",'1. Precursorie'!P:P,"Usata") -> 2 | N6: =COUNTIFS('1. Precursorie'!B:B,CRUSCOTTO!C6,'1. Precursorie'!J:J,"-",'1. Precursorie'!P:P,"2a scelta") -> 0 | O6: =COUNTIFS('1. Precursorie'!B:B,CRUSCOTTO!C6,'1. Precursorie'!J:J,"-",'1. Precursorie'!P:P,"Manca") -> 3 | P6: =IF(G6=0,"-",COUNTIFS('1. Precursorie'!B:B,CRUSCOTTO!C6,'1. Precursorie'!J:J,"Variante",'1. Precursorie'!P:P,"Nuova")) -> - | Q6: =IF(G6=0,"-",COUNTIFS('1. Precursorie'!B:B,CRUSCOTTO!C6,'1. Precursorie'!J:J,"Variante",'1. Precursorie'!P:P,"Usata")) -> - | R6: =IF(G6=0,"-",COUNTIFS('1. Precursorie'!B:B,CRUSCOTTO!C6,'1. Precursorie'!J:J,"Variante",'1. Precursorie'!P:P,"2a scelta")) -> - | S6: =IF(G6=0,"-",COUNTIFS('1. Precursorie'!B:B,CRUSCOTTO!C6,'1. Precursorie'!J:J,"Variante",'1. Precursorie'!P:P,"Manca")) -> - | U6: 3. Arch | W6: - | X6: =COUNTIF('13. Internazionali'!S:S,"Nuova")+COUNTIF('13. Internazionali'!S:S,"Usata")+COUNTIF('13. Internazionali'!S:S,"2a Scelta") -> 6 | Y6: - | Z6: - | AA6: - | AB6: 0
C7: 4. Turistiche | E7: =IF(COUNTIF('1. Precursorie'!B:B,CRUSCOTTO!C7)=(CRUSCOTTO!F7+CRUSCOTTO!G7),CRUSCOTTO!F7+CRUSCOTTO!G7,"Errore") -> 154 | F7: =COUNTIFS('1. Precursorie'!B:B,CRUSCOTTO!C7,'1. Precursorie'!J:J,"-") -> 125 | G7: =COUNTIFS('1. Precursorie'!B:B,CRUSCOTTO!C7,'1. Precursorie'!J:J,"Variante") -> 29 | H7: =(E7-I7)/E7 -> 0.97402597 | I7: =IF(G7=0,O7,O7+S7) -> 4 | J7: =SUMIF('1. Precursorie'!B:B,CRUSCOTTO!C7,'1. Precursorie'!S:S) -> 4764.5 | L7: =COUNTIFS('1. Precursorie'!B:B,CRUSCOTTO!C7,'1. Precursorie'!J:J,"-",'1. Precursorie'!P:P,"Nuova") -> 78 | M7: =COUNTIFS('1. Precursorie'!B:B,CRUSCOTTO!C7,'1. Precursorie'!J:J,"-",'1. Precursorie'!P:P,"Usata") -> 45 | N7: =COUNTIFS('1. Precursorie'!B:B,CRUSCOTTO!C7,'1. Precursorie'!J:J,"-",'1. Precursorie'!P:P,"2a scelta") -> 2 | O7: =COUNTIFS('1. Precursorie'!B:B,CRUSCOTTO!C7,'1. Precursorie'!J:J,"-",'1. Precursorie'!P:P,"Manca") -> 0 | P7: =IF(G7=0,"-",COUNTIFS('1. Precursorie'!B:B,CRUSCOTTO!C7,'1. Precursorie'!J:J,"Variante",'1. Precursorie'!P:P,"Nuova")) -> 15 | Q7: =IF(G7=0,"-",COUNTIFS('1. Precursorie'!B:B,CRUSCOTTO!C7,'1. Precursorie'!J:J,"Variante",'1. Precursorie'!P:P,"Usata")) -> 10 | R7: =IF(G7=0,"-",COUNTIFS('1. Precursorie'!B:B,CRUSCOTTO!C7,'1. Precursorie'!J:J,"Variante",'1. Precursorie'!P:P,"2a scelta")) -> 0 | S7: =IF(G7=0,"-",COUNTIFS('1. Precursorie'!B:B,CRUSCOTTO!C7,'1. Precursorie'!J:J,"Variante",'1. Precursorie'!P:P,"Manca")) -> 4 | U7: 4. Base | W7: =COUNTIF('13. Internazionali'!B:B,"13. Internazionali")-COUNTIF('13. Internazionali'!Q:Q,"n/a") -> 324 | X7: =COUNTIF('13. Internazionali'!Q:Q,"Nuova")+COUNTIF('13. Internazionali'!Q:Q,"Usata")+COUNTIF('13. Internazionali'!Q:Q,"2a Scelta") -> 27 | Y7: - | Z7: - | AA7: - | AB7: 0
B8: Private | C8: 1. Precursorie omaggio | D8: =SUM(E8:E10) -> 479 | E8: =IF(COUNTIF('2. Private'!B:B,CRUSCOTTO!C8)=(CRUSCOTTO!F8+CRUSCOTTO!G8),CRUSCOTTO!F8+CRUSCOTTO!G8,"Errore") -> 91 | F8: =COUNTIFS('2. Private'!B:B,CRUSCOTTO!C8,'2. Private'!K:K,"-") -> 91 | G8: =COUNTIFS('2. Private'!B:B,CRUSCOTTO!C8,'2. Private'!K:K,"Variante") -> 0 | H8: =(E8-I8)/E8 -> 0.76923077 | I8: =IF(G8=0,O8,O8+S8) -> 21 | J8: =SUMIF('2. Private'!B:B,CRUSCOTTO!C8,'2. Private'!T:T) -> 4625 | L8: =COUNTIFS('2. Private'!B:B,CRUSCOTTO!C8,'2. Private'!K:K,"-",'2. Private'!P:P,"Nuova") -> 58 | M8: =COUNTIFS('2. Private'!B:B,CRUSCOTTO!C8,'2. Private'!K:K,"-",'2. Private'!P:P,"Usata") -> 11 | N8: =COUNTIFS('2. Private'!B:B,CRUSCOTTO!C8,'2. Private'!K:K,"-",'2. Private'!P:P,"2a scelta") -> 1 | O8: =COUNTIFS('2. Private'!B:B,CRUSCOTTO!C8,'2. Private'!K:K,"-",'2. Private'!P:P,"Manca") -> 21 | P8: =IF(G8=0,"-",COUNTIFS('2. Private'!B:B,CRUSCOTTO!C8,'2. Private'!K:K,"Variante",'2. Private'!P:P,"Nuova")) -> - | Q8: =IF(G8=0,"-",COUNTIFS('2. Private'!B:B,CRUSCOTTO!C8,'2. Private'!K:K,"Variante",'2. Private'!P:P,"Usata")) -> - | R8: =IF(G8=0,"-",COUNTIFS('2. Private'!B:B,CRUSCOTTO!C8,'2. Private'!K:K,"Variante",'2. Private'!P:P,"2a scelta")) -> - | S8: =IF(G8=0,"-",COUNTIFS('2. Private'!B:B,CRUSCOTTO!C8,'2. Private'!K:K,"Variante",'2. Private'!P:P,"Manca")) -> - | T8: San Marino e Vaticano | U8: 1. San Marino | V8: =W8+W9 -> 533 | W8: =COUNTIF('14. San Marino'!A:A,"14. San Marino") -> 199 | X8: =COUNTIF('14. San Marino'!Q:Q,"Nuova")+COUNTIF('14. San Marino'!Q:Q,"Usata")+COUNTIF('14. San Marino'!Q:Q,"2a Scelta") -> 190 | Y8: =COUNTIF('14. San Marino'!I:I,"Variante") -> 4 | Z8: =X8/W8 -> 0.95477387 | AA8: =COUNTIF('14. San Marino'!Q:Q,"Manca") -> 9 | AB8: =SUM('14. San Marino'!T:T) -> 428
C9: 2. Omaggio private | E9: =IF(COUNTIF('2. Private'!B:B,CRUSCOTTO!C9)=(CRUSCOTTO!F9+CRUSCOTTO!G9),CRUSCOTTO!F9+CRUSCOTTO!G9,"Errore") -> 179 | F9: =COUNTIFS('2. Private'!B:B,CRUSCOTTO!C9,'2. Private'!K:K,"-") -> 153 | G9: =COUNTIFS('2. Private'!B:B,CRUSCOTTO!C9,'2. Private'!K:K,"Variante") -> 26 | H9: =(E9-I9)/E9 -> 0.90502793 | I9: =IF(G9=0,O9,O9+S9) -> 17 | J9: =SUMIF('2. Private'!B:B,CRUSCOTTO!C9,'2. Private'!T:T) -> 5632 | L9: =COUNTIFS('2. Private'!B:B,CRUSCOTTO!C9,'2. Private'!K:K,"-",'2. Private'!P:P,"Nuova") -> 141 | M9: =COUNTIFS('2. Private'!B:B,CRUSCOTTO!C9,'2. Private'!K:K,"-",'2. Private'!P:P,"Usata") -> 0 | N9: =COUNTIFS('2. Private'!B:B,CRUSCOTTO!C9,'2. Private'!K:K,"-",'2. Private'!P:P,"2a scelta") -> 0 | O9: =COUNTIFS('2. Private'!B:B,CRUSCOTTO!C9,'2. Private'!K:K,"-",'2. Private'!P:P,"Manca") -> 12 | P9: =IF(G9=0,"-",COUNTIFS('2. Private'!B:B,CRUSCOTTO!C9,'2. Private'!K:K,"Variante",'2. Private'!P:P,"Nuova")) -> 20 | Q9: =IF(G9=0,"-",COUNTIFS('2. Private'!B:B,CRUSCOTTO!C9,'2. Private'!K:K,"Variante",'2. Private'!P:P,"Usata")) -> 1 | R9: =IF(G9=0,"-",COUNTIFS('2. Private'!B:B,CRUSCOTTO!C9,'2. Private'!K:K,"Variante",'2. Private'!P:P,"2a scelta")) -> 0 | S9: =IF(G9=0,"-",COUNTIFS('2. Private'!B:B,CRUSCOTTO!C9,'2. Private'!K:K,"Variante",'2. Private'!P:P,"Manca")) -> 5 | U9: 2. Vaticano | W9: =COUNTIF('15. Vaticano'!A:A,"15. Vaticano") -> 334 | X9: =COUNTIF('15. Vaticano'!Q:Q,"Nuova")+COUNTIF('15. Vaticano'!Q:Q,"Usata")+COUNTIF('15. Vaticano'!Q:Q,"2a Scelta") -> 0 | Y9: =COUNTIF('15. Vaticano'!I:I,"Variante") -> 26 | Z9: =X9/W9 -> 0 | AA9: =COUNTIF('15. Vaticano'!Q:Q,"Manca") -> 334 | AB9: =SUM('15. Vaticano'!T:T) -> 0
C10: 3. Private Rese Pubbliche | E10: =IF(COUNTIF('2. Private'!B:B,CRUSCOTTO!C10)=(CRUSCOTTO!F10+CRUSCOTTO!G10),CRUSCOTTO!F10+CRUSCOTTO!G10,"Errore") -> 209 | F10: =COUNTIFS('2. Private'!B:B,CRUSCOTTO!C10,'2. Private'!K:K,"-") -> 198 | G10: =COUNTIFS('2. Private'!B:B,CRUSCOTTO!C10,'2. Private'!K:K,"Variante") -> 11 | H10: =(E10-I10)/E10 -> 0.99521531 | I10: =IF(G10=0,O10,O10+S10) -> 1 | J10: =SUMIF('2. Private'!B:B,CRUSCOTTO!C10,'2. Private'!T:T) -> 1203 | L10: =COUNTIFS('2. Private'!B:B,CRUSCOTTO!C10,'2. Private'!K:K,"-",'2. Private'!P:P,"Nuova") -> 198 | M10: =COUNTIFS('2. Private'!B:B,CRUSCOTTO!C10,'2. Private'!K:K,"-",'2. Private'!P:P,"Usata") -> 0 | N10: =COUNTIFS('2. Private'!B:B,CRUSCOTTO!C10,'2. Private'!K:K,"-",'2. Private'!P:P,"2a scelta") -> 0 | O10: =COUNTIFS('2. Private'!B:B,CRUSCOTTO!C10,'2. Private'!K:K,"-",'2. Private'!P:P,"Manca") -> 0 | P10: =IF(G10=0,"-",COUNTIFS('2. Private'!B:B,CRUSCOTTO!C10,'2. Private'!K:K,"Variante",'2. Private'!P:P,"Nuova")) -> 10 | Q10: =IF(G10=0,"-",COUNTIFS('2. Private'!B:B,CRUSCOTTO!C10,'2. Private'!K:K,"Variante",'2. Private'!P:P,"Usata")) -> 0 | R10: =IF(G10=0,"-",COUNTIFS('2. Private'!B:B,CRUSCOTTO!C10,'2. Private'!K:K,"Variante",'2. Private'!P:P,"2a scelta")) -> 0 | S10: =IF(G10=0,"-",COUNTIFS('2. Private'!B:B,CRUSCOTTO!C10,'2. Private'!K:K,"Variante",'2. Private'!P:P,"Manca")) -> 1 | T10: Infostrada | U10: 1. Ordinarie | V10: =W10+W11 -> 297 | W10: =COUNTIF('16. Infostrada'!B:B,U10) -> 48 | X10: =COUNTIFS('16. Infostrada'!B:B,U10,'16. Infostrada'!Q:Q,"Nuova")+COUNTIFS('16. Infostrada'!B:B,U10,'16. Infostrada'!Q:Q,"Usata")+COUNTIFS('16. Infostrada'!B:B,U10,'16. Infostrada'!Q:Q,"2a Scelta") -> 45 | Y10: =COUNTIFS('16. Infostrada'!B:B,U10,'16. Infostrada'!I:I,"Variante") -> 0 | Z10: =X10/W10 -> 0.9375 | AA10: =COUNTIFS('16. Infostrada'!B:B,U10,'16. Infostrada'!Q:Q,"Manca") -> 3 | AB10: =SUMIF('16. Infostrada'!B:B,CRUSCOTTO!U10,'16. Infostrada'!T:T) -> 42
B11: Ordinarie & Pubbliche Figurate | C11: 1. Fasce Orarie | D11: =SUM(E11:E16) -> 2922 | E11: =IF(COUNTIF('3. SIP'!B:B,CRUSCOTTO!C11)=(CRUSCOTTO!F11+CRUSCOTTO!G11),CRUSCOTTO!F11+CRUSCOTTO!G11,"Errore") -> 86 | F11: =COUNTIFS('3. SIP'!B:B,CRUSCOTTO!C11,'3. SIP'!K:K,"-") -> 65 | G11: =COUNTIFS('3. SIP'!B:B,CRUSCOTTO!C11,'3. SIP'!K:K,"Variante") -> 21 | H11: =(E11-I11)/E11 -> 0.96511628 | I11: =IF(G11=0,O11,O11+S11) -> 3 | J11: =SUMIF('3. SIP'!B:B,CRUSCOTTO!C11,'3. SIP'!T:T) -> 2206.8 | L11: =COUNTIFS('3. SIP'!B:B,CRUSCOTTO!C11,'3. SIP'!K:K,"-",'3. SIP'!P:P,"Nuova") -> 59 | M11: =COUNTIFS('3. SIP'!B:B,CRUSCOTTO!C11,'3. SIP'!K:K,"-",'3. SIP'!P:P,"Usata") -> 5 | N11: =COUNTIFS('3. SIP'!B:B,CRUSCOTTO!C11,'3. SIP'!K:K,"-",'3. SIP'!P:P,"2a scelta") -> 0 | O11: =COUNTIFS('3. SIP'!B:B,CRUSCOTTO!C11,'3. SIP'!K:K,"-",'3. SIP'!P:P,"Manca") -> 1 | P11: =COUNTIFS('3. SIP'!B:B,CRUSCOTTO!C11,'3. SIP'!K:K,"Variante",'3. SIP'!P:P,"Nuova") -> 18 | Q11: =COUNTIFS('3. SIP'!B:B,CRUSCOTTO!C11,'3. SIP'!K:K,"Variante",'3. SIP'!P:P,"Usata") -> 1 | R11: =COUNTIFS('3. SIP'!B:B,CRUSCOTTO!C11,'3. SIP'!K:K,"Variante",'3. SIP'!P:P,"2a scelta") -> 0 | S11: =COUNTIFS('3. SIP'!B:B,CRUSCOTTO!C11,'3. SIP'!K:K,"Variante",'3. SIP'!P:P,"Manca") -> 2 | U11: 2. Remote memory | W11: =COUNTIF('16. Infostrada'!B:B,U11) -> 249 | X11: =COUNTIFS('16. Infostrada'!B:B,U11,'16. Infostrada'!Q:Q,"Nuova")+COUNTIFS('16. Infostrada'!B:B,U11,'16. Infostrada'!Q:Q,"Usata")+COUNTIFS('16. Infostrada'!B:B,U11,'16. Infostrada'!Q:Q,"2a Scelta") -> 67 | Y11: =COUNTIFS('16. Infostrada'!B:B,U11,'16. Infostrada'!I:I,"Variante") -> 3 | Z11: =X11/W11 -> 0.26907631 | AA11: =COUNTIFS('16. Infostrada'!B:B,U11,'16. Infostrada'!Q:Q,"Manca") -> 182 | AB11: =SUMIF('16. Infostrada'!B:B,CRUSCOTTO!U11,'16. Infostrada'!T:T) -> 0
C12: 2. SIP | E12: =IF(COUNTIF('3. SIP'!B:B,CRUSCOTTO!C12)=(CRUSCOTTO!F12+CRUSCOTTO!G12),CRUSCOTTO!F12+CRUSCOTTO!G12,"Errore") -> 356 | F12: =COUNTIFS('3. SIP'!B:B,CRUSCOTTO!C12,'3. SIP'!K:K,"-") -> 335 | G12: =COUNTIFS('3. SIP'!B:B,CRUSCOTTO!C12,'3. SIP'!K:K,"Variante") -> 21 | H12: =(E12-I12)/E12 -> 0.99438202 | I12: =IF(G12=0,O12,O12+S12) -> 2 | J12: =SUMIF('3. SIP'!B:B,CRUSCOTTO!C12,'3. SIP'!T:T) -> 6639.65 | L12: =COUNTIFS('3. SIP'!B:B,CRUSCOTTO!C12,'3. SIP'!K:K,"-",'3. SIP'!P:P,"Nuova") -> 329 | M12: =COUNTIFS('3. SIP'!B:B,CRUSCOTTO!C12,'3. SIP'!K:K,"-",'3. SIP'!P:P,"Usata") -> 3 | N12: =COUNTIFS('3. SIP'!B:B,CRUSCOTTO!C12,'3. SIP'!K:K,"-",'3. SIP'!P:P,"2a scelta") -> 3 | O12: =COUNTIFS('3. SIP'!B:B,CRUSCOTTO!C12,'3. SIP'!K:K,"-",'3. SIP'!P:P,"Manca") -> 0 | P12: =COUNTIFS('3. SIP'!B:B,CRUSCOTTO!C12,'3. SIP'!K:K,"Variante",'3. SIP'!P:P,"Nuova") -> 17 | Q12: =COUNTIFS('3. SIP'!B:B,CRUSCOTTO!C12,'3. SIP'!K:K,"Variante",'3. SIP'!P:P,"Usata") -> 2 | R12: =COUNTIFS('3. SIP'!B:B,CRUSCOTTO!C12,'3. SIP'!K:K,"Variante",'3. SIP'!P:P,"2a scelta") -> 0 | S12: =COUNTIFS('3. SIP'!B:B,CRUSCOTTO!C12,'3. SIP'!K:K,"Variante",'3. SIP'!P:P,"Manca") -> 2 | T12: Albacom | U12: 1. Ordinarie | V12: =W12+W13 -> 214 | W12: =COUNTIF('17. Albacom'!B:B,U12) -> 13 | X12: =COUNTIFS('17. Albacom'!B:B,U12,'17. Albacom'!Q:Q,"Nuova")+COUNTIFS('17. Albacom'!B:B,U12,'17. Albacom'!Q:Q,"Usata")+COUNTIFS('17. Albacom'!B:B,U12,'17. Albacom'!Q:Q,"2a Scelta") -> 12 | Y12: =COUNTIFS('17. Albacom'!B:B,U12,'17. Albacom'!I:I,"Variante") -> 0 | Z12: =X12/W12 -> 0.92307692 | AA12: =COUNTIFS('17. Albacom'!B:B,U12,'17. Albacom'!Q:Q,"Manca") -> 1 | AB12: =SUMIF('17. Albacom'!B:B,CRUSCOTTO!U12,'17. Albacom'!T:T) -> 24
C13: 3. Telecom Lire | E13: =IF(COUNTIF('4. Telecom lire'!B:B,CRUSCOTTO!C13)=(CRUSCOTTO!F13+CRUSCOTTO!G13),CRUSCOTTO!F13+CRUSCOTTO!G13,"Errore") -> 1145 | F13: =COUNTIFS('4. Telecom lire'!B:B,CRUSCOTTO!C13,'4. Telecom lire'!K:K,"-") -> 1115 | G13: =COUNTIFS('4. Telecom lire'!B:B,CRUSCOTTO!C13,'4. Telecom lire'!K:K,"Variante") -> 30 | H13: =(E13-I13)/E13 -> 0.98340611 | I13: =IF(G13=0,O13,O13+S13) -> 19 | J13: =SUMIF('4. Telecom lire'!B:B,CRUSCOTTO!C13,'4. Telecom lire'!S:S) -> 2302.2 | L13: =COUNTIFS('4. Telecom lire'!B:B,CRUSCOTTO!C13,'4. Telecom lire'!K:K,"-",'4. Telecom lire'!P:P,"Nuova") -> 1112 | M13: =COUNTIFS('4. Telecom lire'!B:B,CRUSCOTTO!C13,'4. Telecom lire'!K:K,"-",'4. Telecom lire'!P:P,"Usata") -> 1 | N13: =COUNTIFS('4. Telecom lire'!B:B,CRUSCOTTO!C13,'4. Telecom lire'!K:K,"-",'4. Telecom lire'!P:P,"2a scelta") -> 0 | O13: =COUNTIFS('4. Telecom lire'!B:B,CRUSCOTTO!C13,'4. Telecom lire'!K:K,"-",'4. Telecom lire'!P:P,"Manca") -> 2 | P13: =COUNTIFS('4. Telecom lire'!B:B,CRUSCOTTO!C13,'4. Telecom lire'!K:K,"Variante",'4. Telecom lire'!P:P,"Nuova") -> 11 | Q13: =COUNTIFS('4. Telecom lire'!B:B,CRUSCOTTO!C13,'4. Telecom lire'!K:K,"Variante",'4. Telecom lire'!P:P,"Usata") -> 2 | R13: =COUNTIFS('4. Telecom lire'!B:B,CRUSCOTTO!C13,'4. Telecom lire'!K:K,"Variante",'4. Telecom lire'!P:P,"2a scelta") -> 0 | S13: =COUNTIFS('4. Telecom lire'!B:B,CRUSCOTTO!C13,'4. Telecom lire'!K:K,"Variante",'4. Telecom lire'!P:P,"Manca") -> 17 | U13: 2. Test, dimostrative, powered | W13: =COUNTIF('17. Albacom'!B:B,U13) -> 201 | X13: =COUNTIFS('17. Albacom'!B:B,U13,'17. Albacom'!Q:Q,"Nuova")+COUNTIFS('17. Albacom'!B:B,U13,'17. Albacom'!Q:Q,"Usata")+COUNTIFS('17. Albacom'!B:B,U13,'17. Albacom'!Q:Q,"2a Scelta") -> 15 | Y13: =COUNTIFS('17. Albacom'!B:B,U13,'17. Albacom'!I:I,"Variante") -> 0 | Z13: =X13/W13 -> 0.074626866 | AA13: =COUNTIFS('17. Albacom'!B:B,U13,'17. Albacom'!Q:Q,"Manca") -> 186 | AB13: =SUMIF('17. Albacom'!B:B,CRUSCOTTO!U13,'17. Albacom'!T:T) -> 0
C14: 4. Telecom Euro | E14: =IF(COUNTIF('5. Telecom euro'!B:B,CRUSCOTTO!C14)=(CRUSCOTTO!F14+CRUSCOTTO!G14),CRUSCOTTO!F14+CRUSCOTTO!G14,"Errore") -> 1131 | F14: =COUNTIFS('5. Telecom euro'!B:B,CRUSCOTTO!C14,'5. Telecom euro'!L:L,"-") -> 1129 | G14: =COUNTIFS('5. Telecom euro'!B:B,CRUSCOTTO!C14,'5. Telecom euro'!L:L,"Variante") -> 2 | H14: =(E14-I14)/E14 -> 0.99646331 | I14: =IF(G14=0,O14,O14+S14) -> 4 | J14: =SUMIF('5. Telecom euro'!B:B,CRUSCOTTO!C14,'5. Telecom euro'!T:T) -> 4063.2 | L14: =COUNTIFS('5. Telecom euro'!B:B,CRUSCOTTO!C14,'5. Telecom euro'!L:L,"-",'5. Telecom euro'!Q:Q,"Nuova") -> 1126 | M14: =COUNTIFS('5. Telecom euro'!B:B,CRUSCOTTO!C14,'5. Telecom euro'!L:L,"-",'5. Telecom euro'!Q:Q,"Usata") -> 0 | N14: =COUNTIFS('5. Telecom euro'!B:B,CRUSCOTTO!C14,'5. Telecom euro'!L:L,"-",'5. Telecom euro'!Q:Q,"2a scelta") -> 0 | O14: =COUNTIFS('5. Telecom euro'!B:B,CRUSCOTTO!C14,'5. Telecom euro'!L:L,"-",'5. Telecom euro'!Q:Q,"Manca") -> 3 | P14: =COUNTIFS('5. Telecom euro'!B:B,CRUSCOTTO!C14,'5. Telecom euro'!L:L,"Variante",'5. Telecom euro'!Q:Q,"Nuova") -> 1 | Q14: =COUNTIFS('5. Telecom euro'!B:B,CRUSCOTTO!C14,'5. Telecom euro'!L:L,"Variante",'5. Telecom euro'!Q:Q,"Usata") -> 0 | R14: =COUNTIFS('5. Telecom euro'!B:B,CRUSCOTTO!C14,'5. Telecom euro'!L:L,"Variante",'5. Telecom euro'!Q:Q,"2a scelta") -> 0 | S14: =COUNTIFS('5. Telecom euro'!B:B,CRUSCOTTO!C14,'5. Telecom euro'!L:L,"Variante",'5. Telecom euro'!Q:Q,"Manca") -> 1 | T14: Tiscali | U14: 1. Ordinarie | V14: =W14+W15 -> 877 | W14: =COUNTIF('18. Tiscali'!B:B,U14) -> 580 | X14: =COUNTIFS('18. Tiscali'!B:B,U14,'18. Tiscali'!Q:Q,"Nuova")+COUNTIFS('18. Tiscali'!B:B,U14,'18. Tiscali'!Q:Q,"Usata")+COUNTIFS('18. Tiscali'!B:B,U14,'18. Tiscali'!Q:Q,"2a Scelta") -> 0 | Y14: =COUNTIFS('18. Tiscali'!B:B,U14,'18. Tiscali'!I:I,"Variante") -> 260 | Z14: =X14/W14 -> 0 | AA14: =COUNTIFS('18. Tiscali'!B:B,U14,'18. Tiscali'!Q:Q,"Manca") -> 580 | AB14: =SUMIF('18. Tiscali'!B:B,CRUSCOTTO!U14,'18. Tiscali'!T:T) -> 0
C15: 5. Alto Adige | E15: =IF(COUNTIF('6. Alto Adige'!B:B,CRUSCOTTO!C15)=(CRUSCOTTO!F15+CRUSCOTTO!G15),CRUSCOTTO!F15+CRUSCOTTO!G15,"Errore") -> 162 | F15: =COUNTIFS('6. Alto Adige'!B:B,CRUSCOTTO!C15,'6. Alto Adige'!K:K,"-") -> 155 | G15: =COUNTIFS('6. Alto Adige'!B:B,CRUSCOTTO!C15,'6. Alto Adige'!K:K,"Variante") -> 7 | H15: =(E15-I15)/E15 -> 0.95061728 | I15: =IF(G15=0,O15,O15+S15) -> 8 | J15: =SUMIF('6. Alto Adige'!B:B,CRUSCOTTO!C15,'6. Alto Adige'!T:T) -> 3239.2 | L15: =COUNTIFS('6. Alto Adige'!B:B,CRUSCOTTO!C15,'6. Alto Adige'!K:K,"-",'6. Alto Adige'!P:P,"Nuova") -> 145 | M15: =COUNTIFS('6. Alto Adige'!B:B,CRUSCOTTO!C15,'6. Alto Adige'!K:K,"-",'6. Alto Adige'!P:P,"Usata") -> 4 | N15: =COUNTIFS('6. Alto Adige'!B:B,CRUSCOTTO!C15,'6. Alto Adige'!K:K,"-",'6. Alto Adige'!P:P,"2a scelta") -> 0 | O15: =COUNTIFS('6. Alto Adige'!B:B,CRUSCOTTO!C15,'6. Alto Adige'!K:K,"-",'6. Alto Adige'!P:P,"Manca") -> 6 | P15: =COUNTIFS('6. Alto Adige'!B:B,CRUSCOTTO!C15,'6. Alto Adige'!K:K,"Variante",'6. Alto Adige'!P:P,"Nuova") -> 4 | Q15: =COUNTIFS('6. Alto Adige'!B:B,CRUSCOTTO!C15,'6. Alto Adige'!K:K,"Variante",'6. Alto Adige'!P:P,"Usata") -> 1 | R15: =COUNTIFS('6. Alto Adige'!B:B,CRUSCOTTO!C15,'6. Alto Adige'!K:K,"Variante",'6. Alto Adige'!P:P,"2a scelta") -> 0 | S15: =COUNTIFS('6. Alto Adige'!B:B,CRUSCOTTO!C15,'6. Alto Adige'!K:K,"Variante",'6. Alto Adige'!P:P,"Manca") -> 2 | U15: 2. Ricaricasa, Netcard | W15: =COUNTIF('18. Tiscali'!B:B,U15) -> 297 | X15: =COUNTIFS('18. Tiscali'!B:B,U15,'18. Tiscali'!Q:Q,"Nuova")+COUNTIFS('18. Tiscali'!B:B,U15,'18. Tiscali'!Q:Q,"Usata")+COUNTIFS('18. Tiscali'!B:B,U15,'18. Tiscali'!Q:Q,"2a Scelta") -> 0 | Y15: =COUNTIFS('18. Tiscali'!B:B,U15,'18. Tiscali'!I:I,"Variante") -> 133 | Z15: =X15/W15 -> 0 | AA15: =COUNTIFS('18. Tiscali'!B:B,U15,'18. Tiscali'!Q:Q,"Manca") -> 297 | AB15: =SUMIF('18. Tiscali'!B:B,CRUSCOTTO!U15,'18. Tiscali'!T:T) -> 0
C16: 6. Basi militari | E16: =IF(COUNTIF('7. Basi Militari'!B:B,CRUSCOTTO!C16)=(CRUSCOTTO!F16+CRUSCOTTO!G16),CRUSCOTTO!F16+CRUSCOTTO!G16,"Errore") -> 42 | F16: =COUNTIFS('7. Basi Militari'!B:B,CRUSCOTTO!C16,'7. Basi Militari'!L:L,"-") -> 31 | G16: =COUNTIFS('7. Basi Militari'!B:B,CRUSCOTTO!C16,'7. Basi Militari'!L:L,"Varietà") -> 11 | H16: =(E16-I16)/E16 -> 0.85714286 | I16: =IF(G16=0,O16,O16+S16) -> 6 | J16: =SUMIF('1. Precursorie'!B:B,CRUSCOTTO!C16,'1. Precursorie'!S:S) -> 0 | L16: =COUNTIFS('7. Basi Militari'!B:B,CRUSCOTTO!C16,'7. Basi Militari'!L:L,"-",'7. Basi Militari'!Q:Q,"Nuova") -> 1 | M16: =COUNTIFS('7. Basi Militari'!B:B,CRUSCOTTO!C16,'7. Basi Militari'!L:L,"-",'7. Basi Militari'!Q:Q,"Usata") -> 29 | N16: =COUNTIFS('7. Basi Militari'!B:B,CRUSCOTTO!C16,'7. Basi Militari'!L:L,"-",'7. Basi Militari'!Q:Q,"2a Scelta") -> 0 | O16: =COUNTIFS('7. Basi Militari'!B:B,CRUSCOTTO!C16,'7. Basi Militari'!L:L,"-",'7. Basi Militari'!Q:Q,"Manca") -> 1 | P16: =COUNTIFS('7. Basi Militari'!B:B,CRUSCOTTO!C16,'7. Basi Militari'!L:L,"Varietà",'7. Basi Militari'!Q:Q,"Nuova") -> 0 | Q16: =COUNTIFS('7. Basi Militari'!B:B,CRUSCOTTO!C16,'7. Basi Militari'!L:L,"Varietà",'7. Basi Militari'!Q:Q,"Usata") -> 6 | R16: =COUNTIFS('7. Basi Militari'!B:B,CRUSCOTTO!C16,'7. Basi Militari'!L:L,"Varietà",'7. Basi Militari'!Q:Q,"2a Scelta") -> 0 | S16: =COUNTIFS('7. Basi Militari'!B:B,CRUSCOTTO!C16,'7. Basi Militari'!L:L,"Varietà",'7. Basi Militari'!Q:Q,"Manca") -> 5 | T16: ATW | U16: 1. Ordinarie | V16: =W16+W17 -> 367 | W16: =COUNTIF('19. ATW'!B:B,U16) -> 356 | X16: =COUNTIFS('19. ATW'!B:B,U16,'19. ATW'!Q:Q,"Nuova")+COUNTIFS('19. ATW'!B:B,U16,'19. ATW'!Q:Q,"Usata")+COUNTIFS('19. ATW'!B:B,U16,'19. ATW'!Q:Q,"2a Scelta") -> 215 | Y16: =COUNTIFS('19. ATW'!B:B,U16,'19. ATW'!I:I,"Variante") -> 16 | Z16: =X16/W16 -> 0.60393258 | AA16: =COUNTIFS('19. ATW'!B:B,U16,'19. ATW'!Q:Q,"Manca") -> 141 | AB16: =SUMIF('19. ATW'!B:B,CRUSCOTTO!U16,'19. ATW'!T:T) -> 770
E17: =SUM(E4:E16) -> 3688 | F17: =SUM(F4:F16) -> 3481 | G17: =SUM(G4:G16) -> 207 | H17: =(E17-I17)/E17 -> 0.96908894 | I17: =SUM(I4:I16) -> 114 | J17: =SUM(J4:J16) -> 41047.55 | L17: =SUM(L4:L16)/$F$17 -> 0.94484344 | M17: =SUM(M4:M16)/$F$17 -> 0.036483769 | N17: =SUM(N4:N16)/$F$17 -> 0.0020109164 | O17: =SUM(O4:O16)/$F$17 -> 0.016661879 | P17: =SUM(P4:P16)/$G$17 -> 0.52173913 | Q17: =SUM(Q4:Q16)/$G$17 -> 0.19806763 | R17: =SUM(R4:R16)/$G$17 -> 0.0096618357 | S17: =SUM(S4:S16)/$G$17 -> 0.2705314 | U17: 2. Test, Sample, Promocard | W17: =COUNTIF('19. ATW'!B:B,U17) -> 11 | X17: =COUNTIFS('19. ATW'!B:B,U17,'19. ATW'!Q:Q,"Nuova")+COUNTIFS('19. ATW'!B:B,U17,'19. ATW'!Q:Q,"Usata")+COUNTIFS('19. ATW'!B:B,U17,'19. ATW'!Q:Q,"2a Scelta") -> 8 | Y17: =COUNTIFS('19. ATW'!B:B,U17,'19. ATW'!I:I,"Variante") -> 0 | Z17: =X17/W17 -> 0.72727273 | AA17: =COUNTIFS('19. ATW'!B:B,U17,'19. ATW'!Q:Q,"Manca") -> 3 | AB17: =SUMIF('19. ATW'!B:B,CRUSCOTTO!U17,'19. ATW'!T:T) -> 63
T18: Altre compagnie | U18: 20. Accesso web | V18: =SUM(W18:W23) -> 335 | W18: =COUNTIF('20. Accesso Web'!A:A,U18) -> 170 | X18: =COUNTIFS('20. Accesso Web'!A:A,U18,'20. Accesso Web'!Q:Q,"Nuova")+COUNTIFS('20. Accesso Web'!A:A,U18,'20. Accesso Web'!Q:Q,"Usata")+COUNTIFS('20. Accesso Web'!A:A,U18,'20. Accesso Web'!Q:Q,"2a Scelta") -> 0 | Y18: =COUNTIFS('20. Accesso Web'!A:A,U18,'20. Accesso Web'!I:I,"Variante") -> 4 | Z18: =X18/W18 -> 0 | AA18: =COUNTIFS('20. Accesso Web'!A:A,U18,'20. Accesso Web'!Q:Q,"Manca") -> 170 | AB18: =SUMIF('20. Accesso Web'!A:A,CRUSCOTTO!U18,'20. Accesso Web'!T:T) -> 0
B19: Genere | C19: Sottogenere | D19: # TOT schede | F19: # In collezione | G19: # Varianti | H19: Avanzamento | I19: # Mancanti | J19: Valore G26 | L19: Presente | M19: Mancante | N19: Presente | O19: Mancanti | U19: 21. Adriacom | W19: =COUNTIF('21. Adriacom'!B:B,U19) -> 29 | X19: =COUNTIFS('21. Adriacom'!B:B,U19,'21. Adriacom'!Q:Q,"Nuova")+COUNTIFS('21. Adriacom'!B:B,U19,'21. Adriacom'!Q:Q,"Usata")+COUNTIFS('21. Adriacom'!B:B,U19,'21. Adriacom'!Q:Q,"2a Scelta") -> 0 | Y19: =COUNTIFS('21. Adriacom'!B:B,U19,'21. Adriacom'!I:I,"Variante") -> 0 | Z19: =X19/W19 -> 0 | AA19: =COUNTIFS('21. Adriacom'!B:B,U19,'21. Adriacom'!Q:Q,"Manca") -> 29 | AB19: =SUMIF('20. Accesso Web'!A:A,CRUSCOTTO!U19,'20. Accesso Web'!T:T) -> 0
M20: =COUNTIFS('8. Folder'!B:B,CRUSCOTTO!U27,'8. Folder'!J:J,"-",'8. Folder'!M:M,"Sì") -> 12 | N20: =COUNTIFS('8. Folder'!B:B,CRUSCOTTO!U27,'8. Folder'!J:J,"-",'8. Folder'!M:M,"No") -> 10 | O20: =IF(Y27=0,"-",COUNTIFS('8. Folder'!B:B,CRUSCOTTO!U27,'8. Folder'!J:J,"Variante",'8. Folder'!M:M,"Sì")) -> - | P20: =IF(Y27=0,"-",COUNTIFS('8. Folder'!B:B,CRUSCOTTO!U27,'8. Folder'!J:J,"Variante",'8. Folder'!M:M,"No")) -> - | U20: 22. Noicom | W20: =COUNTIF('21. Adriacom'!B:B,U20) -> 17 | X20: =COUNTIFS('21. Adriacom'!B:B,U20,'21. Adriacom'!Q:Q,"Nuova")+COUNTIFS('21. Adriacom'!B:B,U20,'21. Adriacom'!Q:Q,"Usata")+COUNTIFS('21. Adriacom'!B:B,U20,'21. Adriacom'!Q:Q,"2a Scelta") -> 0 | Y20: =COUNTIFS('21. Adriacom'!B:B,U20,'21. Adriacom'!I:I,"Variante") -> 0 | Z20: =X20/W20 -> 0 | AA20: =COUNTIFS('21. Adriacom'!B:B,U20,'21. Adriacom'!Q:Q,"Manca") -> 17 | AB20: =SUMIF('20. Accesso Web'!A:A,CRUSCOTTO!U20,'20. Accesso Web'!T:T) -> 0
B21: Prototipi | C21: 1. Sida | D21: =SUM(E21:E30) -> 784 | E21: =COUNTIF('11. Prototipi'!B:B,CRUSCOTTO!C21) -> 36 | F21: =COUNTIFS('11. Prototipi'!B:B,CRUSCOTTO!C21,'11. Prototipi'!U:U,"Nuova")+COUNTIFS('11. Prototipi'!B:B,CRUSCOTTO!C21,'11. Prototipi'!U:U,"Usata")+COUNTIFS('11. Prototipi'!U:U,CRUSCOTTO!C21,'11. Prototipi'!U:U,"2a Scelta") -> 2 | G21: - | H21: =(F21)/E21 -> 0.055555556 | I21: =COUNTIFS('11. Prototipi'!B:B,C21,'11. Prototipi'!U:U,"Manca") -> 34 | J21: =SUMIF('11. Prototipi'!B:B,CRUSCOTTO!C21,'11. Prototipi'!X:X) -> 150 | M21: =COUNTIFS('8. Folder'!B:B,CRUSCOTTO!U28,'8. Folder'!J:J,"-",'8. Folder'!M:M,"Sì") -> 23 | N21: =COUNTIFS('8. Folder'!B:B,CRUSCOTTO!U28,'8. Folder'!J:J,"-",'8. Folder'!M:M,"No") -> 8 | O21: =IF(Y28=0,"-",COUNTIFS('8. Folder'!B:B,CRUSCOTTO!U28,'8. Folder'!J:J,"Variante",'8. Folder'!M:M,"Sì")) -> - | P21: =IF(Y28=0,"-",COUNTIFS('8. Folder'!B:B,CRUSCOTTO!U28,'8. Folder'!J:J,"Variante",'8. Folder'!M:M,"No")) -> - | U21: 23. Intelcom / Westel | W21: =COUNTIF('20. Accesso Web'!A:A,U21) -> 0 | X21: =COUNTIFS('20. Accesso Web'!A:A,U21,'20. Accesso Web'!Q:Q,"Nuova")+COUNTIFS('20. Accesso Web'!A:A,U21,'20. Accesso Web'!Q:Q,"Usata")+COUNTIFS('20. Accesso Web'!A:A,U21,'20. Accesso Web'!Q:Q,"2a Scelta") -> 0 | Y21: =COUNTIFS('20. Accesso Web'!A:A,U21,'20. Accesso Web'!I:I,"Variante") -> 0 | Z21: =X21/W21 -> #DIV/0! | AA21: =COUNTIFS('20. Accesso Web'!A:A,U21,'20. Accesso Web'!Q:Q,"Manca") -> 0 | AB21: =SUMIF('20. Accesso Web'!A:A,CRUSCOTTO!U21,'20. Accesso Web'!T:T) -> 0
C22: 2. Appalto | E22: =COUNTIF('11. Prototipi'!B:B,CRUSCOTTO!C22) -> 56 | F22: =COUNTIFS('11. Prototipi'!B:B,CRUSCOTTO!C22,'11. Prototipi'!U:U,"Nuova")+COUNTIFS('11. Prototipi'!B:B,CRUSCOTTO!C22,'11. Prototipi'!U:U,"Usata")+COUNTIFS('11. Prototipi'!U:U,CRUSCOTTO!C22,'11. Prototipi'!U:U,"2a Scelta") -> 4 | G22: - | H22: =(F22)/E22 -> 0.071428571 | I22: =COUNTIFS('11. Prototipi'!B:B,C22,'11. Prototipi'!U:U,"Manca") -> 52 | J22: =SUMIF('11. Prototipi'!B:B,CRUSCOTTO!C22,'11. Prototipi'!X:X) -> 190 | M22: =COUNTIFS('8. Folder'!B:B,CRUSCOTTO!U29,'8. Folder'!J:J,"-",'8. Folder'!M:M,"Sì") -> 83 | N22: =COUNTIFS('8. Folder'!B:B,CRUSCOTTO!U29,'8. Folder'!J:J,"-",'8. Folder'!M:M,"No") -> 11 | O22: =IF(Y29=0,"-",COUNTIFS('8. Folder'!B:B,CRUSCOTTO!U29,'8. Folder'!J:J,"Variante",'8. Folder'!M:M,"Sì")) -> 3 | P22: =IF(Y29=0,"-",COUNTIFS('8. Folder'!B:B,CRUSCOTTO!U29,'8. Folder'!J:J,"Variante",'8. Folder'!M:M,"No")) -> 0 | U22: 24. RSLCom | W22: =COUNTIF('20. Accesso Web'!A:A,U22) -> 0 | X22: =COUNTIFS('20. Accesso Web'!A:A,U22,'20. Accesso Web'!Q:Q,"Nuova")+COUNTIFS('20. Accesso Web'!A:A,U22,'20. Accesso Web'!Q:Q,"Usata")+COUNTIFS('20. Accesso Web'!A:A,U22,'20. Accesso Web'!Q:Q,"2a Scelta") -> 0 | Y22: =COUNTIFS('20. Accesso Web'!A:A,U22,'20. Accesso Web'!I:I,"Variante") -> 0 | Z22: =X22/W22 -> #DIV/0! | AA22: =COUNTIFS('20. Accesso Web'!A:A,U22,'20. Accesso Web'!Q:Q,"Manca") -> 0 | AB22: =SUMIF('20. Accesso Web'!A:A,CRUSCOTTO!U22,'20. Accesso Web'!T:T) -> 0
C23: 3. Urmet | E23: =COUNTIF('11. Prototipi'!B:B,CRUSCOTTO!C23) -> 55 | F23: =COUNTIFS('11. Prototipi'!B:B,CRUSCOTTO!C23,'11. Prototipi'!U:U,"Nuova")+COUNTIFS('11. Prototipi'!B:B,CRUSCOTTO!C23,'11. Prototipi'!U:U,"Usata")+COUNTIFS('11. Prototipi'!U:U,CRUSCOTTO!C23,'11. Prototipi'!U:U,"2a Scelta") -> 28 | G23: - | H23: =(F23)/E23 -> 0.50909091 | I23: =COUNTIFS('11. Prototipi'!B:B,C23,'11. Prototipi'!U:U,"Manca") -> 27 | J23: =SUMIF('11. Prototipi'!B:B,CRUSCOTTO!C23,'11. Prototipi'!X:X) -> 1371 | M23: =COUNTIFS('8. Folder'!B:B,CRUSCOTTO!U30,'8. Folder'!J:J,"-",'8. Folder'!M:M,"Sì") -> 11 | N23: =COUNTIFS('8. Folder'!B:B,CRUSCOTTO!U30,'8. Folder'!J:J,"-",'8. Folder'!M:M,"No") -> 2 | O23: =IF(Y30=0,"-",COUNTIFS('8. Folder'!B:B,CRUSCOTTO!U30,'8. Folder'!J:J,"Variante",'8. Folder'!M:M,"Sì")) -> - | P23: =IF(Y30=0,"-",COUNTIFS('8. Folder'!B:B,CRUSCOTTO!U30,'8. Folder'!J:J,"Variante",'8. Folder'!M:M,"No")) -> - | U23: 25. Arcard / TCP | W23: =COUNTIF('25. Arcard TCP'!A:A,U23) -> 119 | X23: =COUNTIF('25. Arcard TCP'!Q:Q,"Nuova")+COUNTIF('25. Arcard TCP'!Q:Q,"Usata")+COUNTIF('25. Arcard TCP'!Q:Q,"2a Scelta") -> 80 | Y23: =COUNTIFS('25. Arcard TCP'!A:A,U23,'25. Arcard TCP'!I:I,"Variante") -> 0 | Z23: =X23/W23 -> 0.67226891 | AA23: =COUNTIF('25. Arcard TCP'!Q:Q,"Manca") -> 33 | AB23: =SUMIF('20. Accesso Web'!A:A,CRUSCOTTO!U23,'20. Accesso Web'!T:T) -> 0
C24: 4. Fasce orarie | E24: =COUNTIF('11. Prototipi'!B:B,CRUSCOTTO!C24) -> 34 | F24: =COUNTIFS('11. Prototipi'!B:B,CRUSCOTTO!C24,'11. Prototipi'!U:U,"Nuova")+COUNTIFS('11. Prototipi'!B:B,CRUSCOTTO!C24,'11. Prototipi'!U:U,"Usata")+COUNTIFS('11. Prototipi'!U:U,CRUSCOTTO!C24,'11. Prototipi'!U:U,"2a Scelta") -> 10 | G24: - | H24: =(F24)/E24 -> 0.29411765 | I24: =COUNTIFS('11. Prototipi'!B:B,C24,'11. Prototipi'!U:U,"Manca") -> 24 | J24: =SUMIF('11. Prototipi'!B:B,CRUSCOTTO!C24,'11. Prototipi'!X:X) -> 713 | M24: =COUNTIFS('8. Folder'!B:B,CRUSCOTTO!U31,'8. Folder'!J:J,"-",'8. Folder'!M:M,"Sì") -> 206 | N24: =COUNTIFS('8. Folder'!B:B,CRUSCOTTO!U31,'8. Folder'!J:J,"-",'8. Folder'!M:M,"No") -> 35 | O24: =IF(Y31=0,"-",COUNTIFS('8. Folder'!B:B,CRUSCOTTO!U31,'8. Folder'!J:J,"Variante",'8. Folder'!M:M,"Sì")) -> 6 | P24: =IF(Y31=0,"-",COUNTIFS('8. Folder'!B:B,CRUSCOTTO!U31,'8. Folder'!J:J,"Variante",'8. Folder'!M:M,"No")) -> 6 | W24: =SUM(W4:W23) -> 3390 | X24: =SUM(X4:X23) -> 889 | Y24: - | Z24: =(W24-AA24)/W24 -> 0.35103245 | AA24: =SUM(AA4:AA23) -> 2200 | AB24: =SUM(AB4:AB23) -> 2751.5
C25: 5. SIP | E25: =COUNTIF('11. Prototipi'!B:B,CRUSCOTTO!C25) -> 182 | F25: =COUNTIFS('11. Prototipi'!B:B,CRUSCOTTO!C25,'11. Prototipi'!U:U,"Nuova")+COUNTIFS('11. Prototipi'!B:B,CRUSCOTTO!C25,'11. Prototipi'!U:U,"Usata")+COUNTIFS('11. Prototipi'!U:U,CRUSCOTTO!C25,'11. Prototipi'!U:U,"2a Scelta") -> 35 | G25: - | H25: =(F25)/E25 -> 0.19230769 | I25: =COUNTIFS('11. Prototipi'!B:B,C25,'11. Prototipi'!U:U,"Manca") -> 147 | J25: =SUMIF('11. Prototipi'!B:B,CRUSCOTTO!C25,'11. Prototipi'!X:X) -> 1359 | M25: =COUNTIFS('8. Folder'!B:B,CRUSCOTTO!U32,'8. Folder'!J:J,"-",'8. Folder'!M:M,"Sì") -> 99 | N25: =COUNTIFS('8. Folder'!B:B,CRUSCOTTO!U32,'8. Folder'!J:J,"-",'8. Folder'!M:M,"No") -> 2 | O25: =IF(Y32=0,"-",COUNTIFS('8. Folder'!B:B,CRUSCOTTO!U32,'8. Folder'!J:J,"Variante",'8. Folder'!M:M,"Sì")) -> 2 | P25: =IF(Y32=0,"-",COUNTIFS('8. Folder'!B:B,CRUSCOTTO!U32,'8. Folder'!J:J,"Variante",'8. Folder'!M:M,"No")) -> 3
C26: 6. Telecom | E26: =COUNTIF('11. Prototipi'!B:B,CRUSCOTTO!C26) -> 163 | F26: =COUNTIFS('11. Prototipi'!B:B,CRUSCOTTO!C26,'11. Prototipi'!U:U,"Nuova")+COUNTIFS('11. Prototipi'!B:B,CRUSCOTTO!C26,'11. Prototipi'!U:U,"Usata")+COUNTIFS('11. Prototipi'!U:U,CRUSCOTTO!C26,'11. Prototipi'!U:U,"2a Scelta") -> 72 | G26: - | H26: =(F26)/E26 -> 0.44171779 | I26: =COUNTIFS('11. Prototipi'!B:B,C26,'11. Prototipi'!U:U,"Manca") -> 91 | J26: =SUMIF('11. Prototipi'!B:B,CRUSCOTTO!C26,'11. Prototipi'!X:X) -> 937 | M26: =COUNTIFS('8. Folder'!B:B,CRUSCOTTO!U33,'8. Folder'!J:J,"-",'8. Folder'!M:M,"Sì") -> 30 | N26: =COUNTIFS('8. Folder'!B:B,CRUSCOTTO!U33,'8. Folder'!J:J,"-",'8. Folder'!M:M,"No") -> 0 | O26: =IF(Y33=0,"-",COUNTIFS('8. Folder'!B:B,CRUSCOTTO!U33,'8. Folder'!J:J,"Variante",'8. Folder'!M:M,"Sì")) -> - | P26: =IF(Y33=0,"-",COUNTIFS('8. Folder'!B:B,CRUSCOTTO!U33,'8. Folder'!J:J,"Variante",'8. Folder'!M:M,"No")) -> - | T26: Genere | U26: Sottogenere | V26: # TOT Folder | X26: # Ordinari | Y26: # Varianti | Z26: Avanzamento | AA26: # Mancanti | AB26: Valore G25
C27: 7. Chip | E27: =COUNTIF('11. Prototipi'!B:B,CRUSCOTTO!C27) -> 21 | F27: =COUNTIFS('11. Prototipi'!B:B,CRUSCOTTO!C27,'11. Prototipi'!U:U,"Nuova")+COUNTIFS('11. Prototipi'!B:B,CRUSCOTTO!C27,'11. Prototipi'!U:U,"Usata")+COUNTIFS('11. Prototipi'!U:U,CRUSCOTTO!C27,'11. Prototipi'!U:U,"2a Scelta") -> 2 | G27: - | H27: =(F27)/E27 -> 0.095238095 | I27: =COUNTIFS('11. Prototipi'!B:B,C27,'11. Prototipi'!U:U,"Manca") -> 19 | J27: =SUMIF('11. Prototipi'!B:B,CRUSCOTTO!C27,'11. Prototipi'!X:X) -> 270 | M27: =COUNTIFS('8. Folder'!B:B,CRUSCOTTO!U34,'8. Folder'!J:J,"-",'8. Folder'!M:M,"Sì") -> 3 | N27: =COUNTIFS('8. Folder'!B:B,CRUSCOTTO!U34,'8. Folder'!J:J,"-",'8. Folder'!M:M,"No") -> 0 | O27: =IF(Y34=0,"-",COUNTIFS('8. Folder'!B:B,CRUSCOTTO!U34,'8. Folder'!J:J,"Variante",'8. Folder'!M:M,"Sì")) -> - | P27: =IF(Y34=0,"-",COUNTIFS('8. Folder'!B:B,CRUSCOTTO!U34,'8. Folder'!J:J,"Variante",'8. Folder'!M:M,"No")) -> - | T27: Folder | U27: 1. Precursorie omaggio | V27: =SUM(W27:W29) -> 150 | W27: =IF(COUNTIF('8. Folder'!B:B,CRUSCOTTO!U27)=(CRUSCOTTO!X27+CRUSCOTTO!Y27),CRUSCOTTO!X27+CRUSCOTTO!Y27,"Errore") -> 22 | X27: =COUNTIFS('8. Folder'!B:B,CRUSCOTTO!U27,'8. Folder'!J:J,"-") -> 22 | Y27: =COUNTIFS('8. Folder'!B:B,CRUSCOTTO!U27,'8. Folder'!J:J,"Variante") -> 0 | Z27: =(W27-AA27)/W27 -> 0.54545455 | AA27: =IF(Y27=0,N20,N20+P20) -> 10 | AB27: =SUMIF('8. Folder'!B:B,CRUSCOTTO!U27,'8. Folder'!P:P) -> 169
C28: 8. IPM-Incard | E28: =COUNTIF('11. Prototipi'!B:B,CRUSCOTTO!C28) -> 107 | F28: =COUNTIFS('11. Prototipi'!B:B,CRUSCOTTO!C28,'11. Prototipi'!U:U,"Nuova")+COUNTIFS('11. Prototipi'!B:B,CRUSCOTTO!C28,'11. Prototipi'!U:U,"Usata")+COUNTIFS('11. Prototipi'!U:U,CRUSCOTTO!C28,'11. Prototipi'!U:U,"2a Scelta") -> 28 | G28: - | H28: =(F28)/E28 -> 0.26168224 | I28: =COUNTIFS('11. Prototipi'!B:B,C28,'11. Prototipi'!U:U,"Manca") -> 79 | J28: =SUMIF('11. Prototipi'!B:B,CRUSCOTTO!C28,'11. Prototipi'!X:X) -> 1077 | M28: =COUNTIFS('8. Folder'!B:B,CRUSCOTTO!U35,'8. Folder'!J:J,"-",'8. Folder'!M:M,"Sì") -> 1 | N28: =COUNTIFS('8. Folder'!B:B,CRUSCOTTO!U35,'8. Folder'!J:J,"-",'8. Folder'!M:M,"No") -> 1 | O28: =IF(Y35=0,"-",COUNTIFS('8. Folder'!B:B,CRUSCOTTO!U35,'8. Folder'!J:J,"Variante",'8. Folder'!M:M,"Sì")) -> - | P28: =IF(Y35=0,"-",COUNTIFS('8. Folder'!B:B,CRUSCOTTO!U35,'8. Folder'!J:J,"Variante",'8. Folder'!M:M,"No")) -> - | U28: 2. Omaggio private | W28: =IF(COUNTIF('8. Folder'!B:B,CRUSCOTTO!U28)=(CRUSCOTTO!X28+CRUSCOTTO!Y28),CRUSCOTTO!X28+CRUSCOTTO!Y28,"Errore") -> 31 | X28: =COUNTIFS('8. Folder'!B:B,CRUSCOTTO!U28,'8. Folder'!J:J,"-") -> 31 | Y28: =COUNTIFS('8. Folder'!B:B,CRUSCOTTO!U28,'8. Folder'!J:J,"Variante") -> 0 | Z28: =(W28-AA28)/W28 -> 0.74193548 | AA28: =IF(Y28=0,N21,N21+P21) -> 8 | AB28: =SUMIF('8. Folder'!B:B,CRUSCOTTO!U28,'8. Folder'!P:P) -> 655
C29: 9. Urmet | E29: =COUNTIF('11. Prototipi'!B:B,CRUSCOTTO!C29) -> 110 | F29: =COUNTIFS('11. Prototipi'!B:B,CRUSCOTTO!C29,'11. Prototipi'!U:U,"Nuova")+COUNTIFS('11. Prototipi'!B:B,CRUSCOTTO!C29,'11. Prototipi'!U:U,"Usata")+COUNTIFS('11. Prototipi'!U:U,CRUSCOTTO!C29,'11. Prototipi'!U:U,"2a Scelta") -> 53 | G29: - | H29: =(F29)/E29 -> 0.48181818 | I29: =COUNTIFS('11. Prototipi'!B:B,C29,'11. Prototipi'!U:U,"Manca") -> 57 | J29: =SUMIF('11. Prototipi'!B:B,CRUSCOTTO!C29,'11. Prototipi'!X:X) -> 697 | M29: =COUNTIFS('8. Folder'!B:B,CRUSCOTTO!U36,'8. Folder'!J:J,"-",'8. Folder'!M:M,"Sì") -> 7 | N29: =COUNTIFS('8. Folder'!B:B,CRUSCOTTO!U36,'8. Folder'!J:J,"-",'8. Folder'!M:M,"No") -> 2 | O29: =IF(Y36=0,"-",COUNTIFS('8. Folder'!B:B,CRUSCOTTO!U36,'8. Folder'!J:J,"Variante",'8. Folder'!M:M,"Sì")) -> - | P29: =IF(Y36=0,"-",COUNTIFS('8. Folder'!B:B,CRUSCOTTO!U36,'8. Folder'!J:J,"Variante",'8. Folder'!M:M,"No")) -> - | U29: 3. Private Rese Pubbliche | W29: =IF(COUNTIF('8. Folder'!B:B,CRUSCOTTO!U29)=(CRUSCOTTO!X29+CRUSCOTTO!Y29),CRUSCOTTO!X29+CRUSCOTTO!Y29,"Errore") -> 97 | X29: =COUNTIFS('8. Folder'!B:B,CRUSCOTTO!U29,'8. Folder'!J:J,"-") -> 94 | Y29: =COUNTIFS('8. Folder'!B:B,CRUSCOTTO!U29,'8. Folder'!J:J,"Variante") -> 3 | Z29: =(W29-AA29)/W29 -> 0.88659794 | AA29: =IF(Y29=0,N22,N22+P22) -> 11 | AB29: =SUMIF('8. Folder'!B:B,CRUSCOTTO!U29,'8. Folder'!P:P) -> 1104
C30: 10. Prove materiale | E30: =COUNTIF('11. Prototipi'!B:B,CRUSCOTTO!C30) -> 20 | F30: =COUNTIFS('11. Prototipi'!B:B,CRUSCOTTO!C30,'11. Prototipi'!U:U,"Nuova")+COUNTIFS('11. Prototipi'!B:B,CRUSCOTTO!C30,'11. Prototipi'!U:U,"Usata")+COUNTIFS('11. Prototipi'!U:U,CRUSCOTTO!C30,'11. Prototipi'!U:U,"2a Scelta") -> 8 | G30: - | H30: =(F30)/E30 -> 0.4 | I30: =COUNTIFS('11. Prototipi'!B:B,C30,'11. Prototipi'!U:U,"Manca") -> 12 | J30: =SUMIF('11. Prototipi'!B:B,CRUSCOTTO!C30,'11. Prototipi'!X:X) -> 115 | M30: =COUNTIFS('8. Folder'!B:B,CRUSCOTTO!U37,'8. Folder'!J:J,"-",'8. Folder'!M:M,"Sì") -> 36 | N30: =COUNTIFS('8. Folder'!B:B,CRUSCOTTO!U37,'8. Folder'!J:J,"-",'8. Folder'!M:M,"No") -> 18 | O30: =IF(Y37=0,"-",COUNTIFS('8. Folder'!B:B,CRUSCOTTO!U37,'8. Folder'!J:J,"Variante",'8. Folder'!M:M,"Sì")) -> - | P30: =IF(Y37=0,"-",COUNTIFS('8. Folder'!B:B,CRUSCOTTO!U37,'8. Folder'!J:J,"Variante",'8. Folder'!M:M,"No")) -> - | U30: 4. Figurate SIP | V30: =SUM(W30:W33) -> 405 | W30: =IF(COUNTIF('8. Folder'!B:B,CRUSCOTTO!U30)=(CRUSCOTTO!X30+CRUSCOTTO!Y30),CRUSCOTTO!X30+CRUSCOTTO!Y30,"Errore") -> 13 | X30: =COUNTIFS('8. Folder'!B:B,CRUSCOTTO!U30,'8. Folder'!J:J,"-") -> 13 | Y30: =COUNTIFS('8. Folder'!B:B,CRUSCOTTO!U30,'8. Folder'!J:J,"Variante") -> 0 | Z30: =(W30-AA30)/W30 -> 0.84615385 | AA30: =IF(Y30=0,N23,N23+P23) -> 2 | AB30: =SUMIF('8. Folder'!B:B,CRUSCOTTO!U30,'8. Folder'!P:P) -> 430
B31: Usi Speciali | C31: 1. Parlamento | D31: =SUM(E31:E39) -> 660 | E31: =COUNTIF('12. Usi speciali'!B:B,C31) -> 14 | F31: =COUNTIFS('12. Usi speciali'!B:B,CRUSCOTTO!C31,'12. Usi speciali'!P:P,"Nuova")+COUNTIFS('12. Usi speciali'!B:B,CRUSCOTTO!C31,'12. Usi speciali'!P:P,"Usata")+COUNTIFS('12. Usi speciali'!B:B,CRUSCOTTO!C31,'12. Usi speciali'!P:P,"2a Scelta") -> 5 | G31: - | H31: =(F31)/E31 -> 0.35714286 | I31: =COUNTIFS('12. Usi speciali'!B:B,CRUSCOTTO!C31,'12. Usi speciali'!P:P,"Manca") -> 9 | J31: =SUMIF('12. Usi speciali'!B:B,CRUSCOTTO!C31,'12. Usi speciali'!S:S) -> 118 | M31: =SUM(M20:M30) -> 511 | N31: =SUM(N20:N30) -> 89 | O31: =SUM(O20:O30) -> 11 | P31: =SUM(P20:P30) -> 9 | U31: 5. Figurate Telecom lire | W31: =IF(COUNTIF('8. Folder'!B:B,CRUSCOTTO!U31)=(CRUSCOTTO!X31+CRUSCOTTO!Y31),CRUSCOTTO!X31+CRUSCOTTO!Y31,"Errore") -> 256 | X31: =COUNTIFS('8. Folder'!B:B,CRUSCOTTO!U31,'8. Folder'!J:J,"-") -> 242 | Y31: =COUNTIFS('8. Folder'!B:B,CRUSCOTTO!U31,'8. Folder'!J:J,"Variante") -> 14 | Z31: =(W31-AA31)/W31 -> 0.83984375 | AA31: =IF(Y31=0,N24,N24+P24) -> 41 | AB31: =SUMIF('8. Folder'!B:B,CRUSCOTTO!U31,'8. Folder'!P:P) -> 4509
C32: 2. Basi Nato | E32: =COUNTIF('12. Usi speciali'!B:B,C32) -> 6 | F32: =COUNTIFS('12. Usi speciali'!B:B,CRUSCOTTO!C32,'12. Usi speciali'!P:P,"Nuova")+COUNTIFS('12. Usi speciali'!B:B,CRUSCOTTO!C32,'12. Usi speciali'!P:P,"Usata")+COUNTIFS('12. Usi speciali'!B:B,CRUSCOTTO!C32,'12. Usi speciali'!P:P,"2a Scelta") -> 3 | G32: - | H32: =(F32)/E32 -> 0.5 | I32: =COUNTIFS('12. Usi speciali'!B:B,CRUSCOTTO!C32,'12. Usi speciali'!P:P,"Manca") -> 3 | J32: =SUMIF('12. Usi speciali'!B:B,CRUSCOTTO!C32,'12. Usi speciali'!S:S) -> 150 | U32: 6. Figurate Telecom euro | W32: =IF(COUNTIF('8. Folder'!B:B,CRUSCOTTO!U32)=(CRUSCOTTO!X32+CRUSCOTTO!Y32),CRUSCOTTO!X32+CRUSCOTTO!Y32,"Errore") -> 106 | X32: =COUNTIFS('8. Folder'!B:B,CRUSCOTTO!U32,'8. Folder'!J:J,"-") -> 101 | Y32: =COUNTIFS('8. Folder'!B:B,CRUSCOTTO!U32,'8. Folder'!J:J,"Variante") -> 5 | Z32: =(W32-AA32)/W32 -> 0.95283019 | AA32: =IF(Y32=0,N25,N25+P25) -> 5 | AB32: =SUMIF('8. Folder'!B:B,CRUSCOTTO!U32,'8. Folder'!P:P) -> 1655.5
C33: 3. Ospedali / Easytel | E33: =COUNTIF('12. Usi speciali'!B:B,C33) -> 33 | F33: =COUNTIFS('12. Usi speciali'!B:B,CRUSCOTTO!C33,'12. Usi speciali'!P:P,"Nuova")+COUNTIFS('12. Usi speciali'!B:B,CRUSCOTTO!C33,'12. Usi speciali'!P:P,"Usata")+COUNTIFS('12. Usi speciali'!B:B,CRUSCOTTO!C33,'12. Usi speciali'!P:P,"2a Scelta") -> 16 | G33: - | H33: =(F33)/E33 -> 0.48484848 | I33: =COUNTIFS('12. Usi speciali'!B:B,CRUSCOTTO!C33,'12. Usi speciali'!P:P,"Manca") -> 17 | J33: =SUMIF('12. Usi speciali'!B:B,CRUSCOTTO!C33,'12. Usi speciali'!S:S) -> 134 | U33: 7. Alto Adige | W33: =IF(COUNTIF('8. Folder'!B:B,CRUSCOTTO!U33)=(CRUSCOTTO!X33+CRUSCOTTO!Y33),CRUSCOTTO!X33+CRUSCOTTO!Y33,"Errore") -> 30 | X33: =COUNTIFS('8. Folder'!B:B,CRUSCOTTO!U33,'8. Folder'!J:J,"-") -> 30 | Y33: =COUNTIFS('8. Folder'!B:B,CRUSCOTTO!U33,'8. Folder'!J:J,"Variante") -> 0 | Z33: =(W33-AA33)/W33 -> 1 | AA33: =IF(Y33=0,N26,N26+P26) -> 0 | AB33: =SUMIF('8. Folder'!B:B,CRUSCOTTO!U33,'8. Folder'!P:P) -> 417
C34: 4. Carte di credito | E34: =COUNTIF('12. Usi speciali'!B:B,C34) -> 105 | F34: =COUNTIFS('12. Usi speciali'!B:B,CRUSCOTTO!C34,'12. Usi speciali'!P:P,"Nuova")+COUNTIFS('12. Usi speciali'!B:B,CRUSCOTTO!C34,'12. Usi speciali'!P:P,"Usata")+COUNTIFS('12. Usi speciali'!B:B,CRUSCOTTO!C34,'12. Usi speciali'!P:P,"2a Scelta") -> 22 | G34: - | H34: =(F34)/E34 -> 0.20952381 | I34: =COUNTIFS('12. Usi speciali'!B:B,CRUSCOTTO!C34,'12. Usi speciali'!P:P,"Manca") -> 83 | J34: =SUMIF('12. Usi speciali'!B:B,CRUSCOTTO!C34,'12. Usi speciali'!S:S) -> 440 | U34: 8. ADAC | V34: =SUM(W34:W36) -> 16 | W34: =IF(COUNTIF('8. Folder'!B:B,CRUSCOTTO!U34)=(CRUSCOTTO!X34+CRUSCOTTO!Y34),CRUSCOTTO!X34+CRUSCOTTO!Y34,"Errore") -> 3 | X34: =COUNTIFS('8. Folder'!B:B,CRUSCOTTO!U34,'8. Folder'!J:J,"-") -> 3 | Y34: =COUNTIFS('8. Folder'!B:B,CRUSCOTTO!U34,'8. Folder'!J:J,"Variante") -> 0 | Z34: =(W34-AA34)/W34 -> 1 | AA34: =IF(Y34=0,N27,N27+P27) -> 0 | AB34: =SUMIF('8. Folder'!B:B,CRUSCOTTO!U34,'8. Folder'!P:P) -> 75
C35: 5. Call-IT | E35: =COUNTIF('12. Usi speciali'!B:B,C35) -> 88 | F35: =COUNTIFS('12. Usi speciali'!B:B,CRUSCOTTO!C35,'12. Usi speciali'!P:P,"Nuova")+COUNTIFS('12. Usi speciali'!B:B,CRUSCOTTO!C35,'12. Usi speciali'!P:P,"Usata")+COUNTIFS('12. Usi speciali'!B:B,CRUSCOTTO!C35,'12. Usi speciali'!P:P,"2a Scelta") -> 5 | G35: - | H35: =(F35)/E35 -> 0.056818182 | I35: =COUNTIFS('12. Usi speciali'!B:B,CRUSCOTTO!C35,'12. Usi speciali'!P:P,"Manca") -> 83 | J35: =SUMIF('12. Usi speciali'!B:B,CRUSCOTTO!C35,'12. Usi speciali'!S:S) -> 71 | U35: 9. Chip | W35: =IF(COUNTIF('8. Folder'!B:B,CRUSCOTTO!U35)=(CRUSCOTTO!X35+CRUSCOTTO!Y35),CRUSCOTTO!X35+CRUSCOTTO!Y35,"Errore") -> 2 | X35: =COUNTIFS('8. Folder'!B:B,CRUSCOTTO!U35,'8. Folder'!J:J,"-") -> 2 | Y35: =COUNTIFS('8. Folder'!B:B,CRUSCOTTO!U35,'8. Folder'!J:J,"Variante") -> 0 | Z35: =(W35-AA35)/W35 -> 0.5 | AA35: =IF(Y35=0,N28,N28+P28) -> 1 | AB35: =SUMIF('8. Folder'!B:B,CRUSCOTTO!U35,'8. Folder'!P:P) -> 14
C36: 6. Sala Stampa | E36: =COUNTIF('12. Usi speciali'!B:B,C36) -> 175 | F36: =COUNTIFS('12. Usi speciali'!B:B,CRUSCOTTO!C36,'12. Usi speciali'!P:P,"Nuova")+COUNTIFS('12. Usi speciali'!B:B,CRUSCOTTO!C36,'12. Usi speciali'!P:P,"Usata")+COUNTIFS('12. Usi speciali'!B:B,CRUSCOTTO!C36,'12. Usi speciali'!P:P,"2a Scelta") -> 52 | G36: - | H36: =(F36)/E36 -> 0.29714286 | I36: =COUNTIFS('12. Usi speciali'!B:B,CRUSCOTTO!C36,'12. Usi speciali'!P:P,"Manca") -> 123 | J36: =SUMIF('12. Usi speciali'!B:B,CRUSCOTTO!C36,'12. Usi speciali'!S:S) -> 1418 | U36: 10. Generici | W36: =IF(COUNTIF('8. Folder'!B:B,CRUSCOTTO!U36)=(CRUSCOTTO!X36+CRUSCOTTO!Y36),CRUSCOTTO!X36+CRUSCOTTO!Y36,"Errore") -> 11 | X36: =COUNTIFS('8. Folder'!B:B,CRUSCOTTO!U36,'8. Folder'!J:J,"-") -> 11 | Y36: =COUNTIFS('8. Folder'!B:B,CRUSCOTTO!U36,'8. Folder'!J:J,"Variante") -> 0 | Z36: =(W36-AA36)/W36 -> 0.81818182 | AA36: =IF(Y36=0,N29,N29+P29) -> 2 | AB36: =SUMIF('8. Folder'!B:B,CRUSCOTTO!U36,'8. Folder'!P:P) -> 101
C37: 7. Mediaphone | E37: =COUNTIF('12. Usi speciali'!B:B,C37) -> 104 | F37: =COUNTIFS('12. Usi speciali'!B:B,CRUSCOTTO!C37,'12. Usi speciali'!P:P,"Nuova")+COUNTIFS('12. Usi speciali'!B:B,CRUSCOTTO!C37,'12. Usi speciali'!P:P,"Usata")+COUNTIFS('12. Usi speciali'!B:B,CRUSCOTTO!C37,'12. Usi speciali'!P:P,"2a Scelta") -> 74 | G37: - | H37: =(F37)/E37 -> 0.71153846 | I37: =COUNTIFS('12. Usi speciali'!B:B,CRUSCOTTO!C37,'12. Usi speciali'!P:P,"Manca") -> 30 | J37: =SUMIF('12. Usi speciali'!B:B,CRUSCOTTO!C37,'12. Usi speciali'!S:S) -> 2571 | U37: 11. Gadget e altro | V37: =W37 -> 54 | W37: =IF(COUNTIF('8. Folder'!B:B,CRUSCOTTO!U37)=(CRUSCOTTO!X37+CRUSCOTTO!Y37),CRUSCOTTO!X37+CRUSCOTTO!Y37,"Errore") -> 54 | X37: =COUNTIFS('8. Folder'!B:B,CRUSCOTTO!U37,'8. Folder'!J:J,"-") -> 54 | Y37: =COUNTIFS('8. Folder'!B:B,CRUSCOTTO!U37,'8. Folder'!J:J,"Variante") -> 0 | Z37: =(W37-AA37)/W37 -> 0.66666667 | AA37: =IF(Y37=0,N30,N30+P30) -> 18 | AB37: =SUMIF('8. Folder'!B:B,CRUSCOTTO!U37,'8. Folder'!P:P) -> 353.5
C38: 8. Prome | E38: =COUNTIF('12. Usi speciali'!B:B,C38) -> 69 | F38: =COUNTIFS('12. Usi speciali'!B:B,CRUSCOTTO!C38,'12. Usi speciali'!P:P,"Nuova")+COUNTIFS('12. Usi speciali'!B:B,CRUSCOTTO!C38,'12. Usi speciali'!P:P,"Usata")+COUNTIFS('12. Usi speciali'!B:B,CRUSCOTTO!C38,'12. Usi speciali'!P:P,"2a Scelta") -> 2 | G38: - | H38: =(F38)/E38 -> 0.028985507 | I38: =COUNTIFS('12. Usi speciali'!B:B,CRUSCOTTO!C38,'12. Usi speciali'!P:P,"Manca") -> 67 | J38: =SUMIF('12. Usi speciali'!B:B,CRUSCOTTO!C38,'12. Usi speciali'!S:S) -> 60 | W38: =SUM(W27:W37) -> 625 | X38: =SUM(X27:X37) -> 603 | Y38: =SUM(Y27:Y37) -> 22 | Z38: =(W38-AA38)/W38 -> 0.8432 | AA38: =N31+P31 -> 98 | AB38: =SUM(AB27:AB37) -> 9483
C39: 9. Giubileo e altri USP | E39: =COUNTIF('12. Usi speciali'!B:B,C39) -> 66 | F39: =COUNTIFS('12. Usi speciali'!B:B,CRUSCOTTO!C39,'12. Usi speciali'!P:P,"Nuova")+COUNTIFS('12. Usi speciali'!B:B,CRUSCOTTO!C39,'12. Usi speciali'!P:P,"Usata")+COUNTIFS('12. Usi speciali'!B:B,CRUSCOTTO!C39,'12. Usi speciali'!P:P,"2a Scelta") -> 7 | G39: - | H39: =(F39)/E39 -> 0.10606061 | I39: =COUNTIFS('12. Usi speciali'!B:B,CRUSCOTTO!C39,'12. Usi speciali'!P:P,"Manca") -> 59 | J39: =SUMIF('12. Usi speciali'!B:B,CRUSCOTTO!C39,'12. Usi speciali'!S:S) -> 144
E40: =SUM(E21:E39) -> 1444 | F40: =SUM(F21:F39) -> 428 | G40: =SUM(G21:G39) -> 0 | H40: =F40/E40 -> 0.29639889 | I40: =SUM(I21:I39) -> 1016 | J40: =SUM(J27:J39) -> 7265

Sheet 1. Precursorie
A1: Genere | B1: Sottogenere | C1: N.Golden | D1: N. C&C | E1: N. AG | F1: Taglio | G1: Scadenza | H1: Titolo | I1: Note | J1: Var | K1: Pr. | L1: Tiratura | M1: Val 2025 Nuova | N1: Val 2025 Usata | P1: Presente | Q1: Magnetizzazione | S1: Valore collezione
A2: 1. Precursorie | B2: 1. Sida | C2: P0 | D2: 1000 | E2: - | F2: - | G2: 1976 | H2: Sida 0 | I2: - | J2: - | K2: Pik | L2: - | M2: - | N2: P.A.R. | P2: Usata | Q2: Sì | S2: =IF(P2='Menu tendina'!A$5,0,IF(P2='Menu tendina'!A$4,'1. Precursorie'!N2/2,IF(P2='Menu tendina'!A$3,'1. Precursorie'!N2,IF(P2='Menu tendina'!A$2,'1. Precursorie'!M2,0)))) -> P.A.R.
A3: 1. Precursorie | B3: 1. Sida | C3: P1 | D3: 1001 | E3: P1 | F3: 2000 | G3: 1977 | H3: 1° Gruppo SIDA | I3: Bandella Circolare | J3: - | K3: Pik | L3: - | M3: 400 | N3: 300 | P3: Nuova | Q3: No | S3: =IF(P3='Menu tendina'!A$5,0,IF(P3='Menu tendina'!A$4,'1. Precursorie'!N3/2,IF(P3='Menu tendina'!A$3,'1. Precursorie'!N3,IF(P3='Menu tendina'!A$2,'1. Precursorie'!M3,0)))) -> 400
A4: 1. Precursorie | B4: 1. Sida | C4: P2 | D4: 1002 | E4: P2 | F4: 5000 | G4: 1977 | H4: 1° Gruppo SIDA | I4: Bandella Circolare | J4: - | K4: Pik | L4: - | M4: 500 | N4: 300 | P4: Manca | S4: =IF(P4='Menu tendina'!A$5,0,IF(P4='Menu tendina'!A$4,'1. Precursorie'!N4/2,IF(P4='Menu tendina'!A$3,'1. Precursorie'!N4,IF(P4='Menu tendina'!A$2,'1. Precursorie'!M4,0)))) -> 0
A5: 1. Precursorie | B5: 1. Sida | C5: P3 | D5: 1003 | E5: P3 | F5: 9000 | G5: 1977 | H5: 1° Gruppo SIDA | I5: Bandella Circolare | J5: - | K5: Pik | L5: - | M5: 400 | N5: 350 | P5: Manca | S5: =IF(P5='Menu tendina'!A$5,0,IF(P5='Menu tendina'!A$4,'1. Precursorie'!N5/2,IF(P5='Menu tendina'!A$3,'1. Precursorie'!N5,IF(P5='Menu tendina'!A$2,'1. Precursorie'!M5,0)))) -> 0
A6: 1. Precursorie | B6: 1. Sida | C6: P4 | D6: 1004 | E6: P4 | F6: 2000 | G6: 1978 | H6: 1° Gruppo SIDA | I6: Banella Sagomata | J6: - | K6: Pik | L6: 500 | M6: 380 | N6: 280 | P6: Nuova | Q6: Sì | S6: =IF(P6='Menu tendina'!A$5,0,IF(P6='Menu tendina'!A$4,'1. Precursorie'!N6/2,IF(P6='Menu tendina'!A$3,'1. Precursorie'!N6,IF(P6='Menu tendina'!A$2,'1. Precursorie'!M6,0)))) -> 380
A7: 1. Precursorie | B7: 1. Sida | C7: P5 | D7: - | E7: P5 | F7: 5000 | G7: 1978 | H7: 1° Gruppo SIDA | I7: (N.M.) Bandella Sagomata | J7: - | K7: Pik | L7: - | M7: P.A.R. | N7: P.A.R. | P7: Manca | Q7: n/a | S7: =IF(P7='Menu tendina'!A$5,0,IF(P7='Menu tendina'!A$4,'1. Precursorie'!N7/2,IF(P7='Menu tendina'!A$3,'1. Precursorie'!N7,IF(P7='Menu tendina'!A$2,'1. Precursorie'!M7,0)))) -> 0
A8: 1. Precursorie | B8: 1. Sida | C8: P6 | D8: 1005 | E8: P6 | F8: 9000 | G8: 1978 | H8: 1° Gruppo SIDA | I8: Bandella Sagomata | J8: - | K8: Pik | L8: 500 | M8: 450 | N8: 350 | P8: Nuova | Q8: No | S8: =IF(P8='Menu tendina'!A$5,0,IF(P8='Menu tendina'!A$4,'1. Precursorie'!N8/2,IF(P8='Menu tendina'!A$3,'1. Precursorie'!N8,IF(P8='Menu tendina'!A$2,'1. Precursorie'!M8,0)))) -> 450
A9: 1. Precursorie | B9: 1. Sida | C9: P7 | D9: 1006 | E9: P7 | F9: 2000 | G9: 28915 | H9: 1° Gruppo SIDA | I9: Bandella Sagomata | J9: - | K9: Pik | L9: 200 | M9: 250 | N9: 80 | P9: Nuova | S9: =IF(P9='Menu tendina'!A$5,0,IF(P9='Menu tendina'!A$4,'1. Precursorie'!N9/2,IF(P9='Menu tendina'!A$3,'1. Precursorie'!N9,IF(P9='Menu tendina'!A$2,'1. Precursorie'!M9,0)))) -> 250
A10: 1. Precursorie | B10: 1. Sida | C10: P7A | D10: 1006A | E10: P7A | F10: 2000 | G10: 28915 | H10: 1° Gruppo SIDA | I10: Bandella Diritta | J10: Variante | K10: Pik | L10: - | M10: 220 | N10: 130 | P10: Manca | S10: =IF(P10='Menu tendina'!A$5,0,IF(P10='Menu tendina'!A$4,'1. Precursorie'!N10/2,IF(P10='Menu tendina'!A$3,'1. Precursorie'!N10,IF(P10='Menu tendina'!A$2,'1. Precursorie'!M10,0)))) -> 0
A11: 1. Precursorie | B11: 1. Sida | C11: P7B | D11: 1006B | E11: P7B | F11: 2000 | G11: 28915 | H11: 1° Gruppo SIDA | I11: Badella Ridotta | J11: Variante | K11: Pik | L11: - | M11: 220 | N11: 130 | P11: Manca | S11: =IF(P11='Menu tendina'!A$5,0,IF(P11='Menu tendina'!A$4,'1. Precursorie'!N11/2,IF(P11='Menu tendina'!A$3,'1. Precursorie'!N11,IF(P11='Menu tendina'!A$2,'1. Precursorie'!M11,0)))) -> 0
A12: 1. Precursorie | B12: 1. Sida | C12: P8 | D12: 1007 | E12: P8 | F12: 5000 | G12: 28915 | H12: 1° Gruppo SIDA | I12: Bandella Sagomata | J12: - | K12: Pik | L12: 200 | M12: 250 | N12: 130 | P12: Usata | Q12: Sì | S12: =IF(P12='Menu tendina'!A$5,0,IF(P12='Menu tendina'!A$4,'1. Precursorie'!N12/2,IF(P12='Menu tendina'!A$3,'1. Precursorie'!N12,IF(P12='Menu tendina'!A$2,'1. Precursorie'!M12,0)))) -> 130
A13: 1. Precursorie | B13: 1. Sida | C13: P8A | D13: 1007A | E13: P8A | F13: 5000 | G13: 28915 | H13: 1° Gruppo SIDA | I13: Bandella Diritta | J13: Variante | K13: Pik | L13: - | M13: 220 | N13: 130 | P13: Manca | S13: =IF(P13='Menu tendina'!A$5,0,IF(P13='Menu tendina'!A$4,'1. Precursorie'!N13/2,IF(P13='Menu tendina'!A$3,'1. Precursorie'!N13,IF(P13='Menu tendina'!A$2,'1. Precursorie'!M13,0)))) -> 0
A14: 1. Precursorie | B14: 1. Sida | C14: P8B | D14: 1007B | E14: P8B | F14: 5000 | G14: 28915 | H14: 1° Gruppo SIDA | I14: Badella Ridotta | J14: Variante | K14: Pik | L14: - | M14: 220 | N14: 130 | P14: Nuova | Q14: Sì | S14: =IF(P14='Menu tendina'!A$5,0,IF(P14='Menu tendina'!A$4,'1. Precursorie'!N14/2,IF(P14='Menu tendina'!A$3,'1. Precursorie'!N14,IF(P14='Menu tendina'!A$2,'1. Precursorie'!M14,0)))) -> 220
A15: 1. Precursorie | B15: 1. Sida | C15: P9 | D15: 1008 | E15: P9 | F15: 9000 | G15: 28915 | H15: 1° Gruppo SIDA | I15: Bandella Sagomata | J15: - | K15: Pik | L15: 200 | M15: 80 | N15: 35 | P15: Nuova | Q15: Sì | S15: =IF(P15='Menu tendina'!A$5,0,IF(P15='Menu tendina'!A$4,'1. Precursorie'!N15/2,IF(P15='Menu tendina'!A$3,'1. Precursorie'!N15,IF(P15='Menu tendina'!A$2,'1. Precursorie'!M15,0)))) -> 80
A16: 1. Precursorie | B16: 1. Sida | C16: P9A | D16: 1008A | E16: P9A | F16: 9000 | G16: 28915 | H16: 1° Gruppo SIDA | I16: Bandella Diritta | J16: Variante | K16: Pik | L16: - | M16: 100 | N16: 55 | P16: Manca | S16: =IF(P16='Menu tendina'!A$5,0,IF(P16='Menu tendina'!A$4,'1. Precursorie'!N16/2,IF(P16='Menu tendina'!A$3,'1. Precursorie'!N16,IF(P16='Menu tendina'!A$2,'1. Precursorie'!M16,0)))) -> 0
A17: 1. Precursorie | B17: 1. Sida | C17: P9B | D17: 1008B | E17: P9B | F17: 9000 | G17: 28915 | H17: 1° Gruppo SIDA | I17: Badella Ridotta | J17: Variante | K17: Pik | L17: - | M17: 120 | N17: 55 | P17: Manca | S17: =IF(P17='Menu tendina'!A$5,0,IF(P17='Menu tendina'!A$4,'1. Precursorie'!N17/2,IF(P17='Menu tendina'!A$3,'1. Precursorie'!N17,IF(P17='Menu tendina'!A$2,'1. Precursorie'!M17,0)))) -> 0
A18: 1. Precursorie | B18: 1. Sida | C18: P10 | D18: 1009 | E18: P10 | F18: 2000 | G18: 29281 | H18: 1° Gruppo SIDA | I18: Bianca / Bandella Sagomata | J18: - | K18: Pik | L18: 200 | M18: 200 | N18: 120 | P18: Nuova | Q18: No | S18: =IF(P18='Menu tendina'!A$5,0,IF(P18='Menu tendina'!A$4,'1. Precursorie'!N18/2,IF(P18='Menu tendina'!A$3,'1. Precursorie'!N18,IF(P18='Menu tendina'!A$2,'1. Precursorie'!M18,0)))) -> 200
A19: 1. Precursorie | B19: 1. Sida | C19: P10A | D19: 1009A | E19: P10A | F19: 2000 | G19: 29281 | H19: 1° Gruppo SIDA | I19: Grigia / Bandella Sagomata | J19: Variante | K19: Pik | L19: 200 | M19: 250 | N19: 100 | P19: Manca | S19: =IF(P19='Menu tendina'!A$5,0,IF(P19='Menu tendina'!A$4,'1. Precursorie'!N19/2,IF(P19='Menu tendina'!A$3,'1. Precursorie'!N19,IF(P19='Menu tendina'!A$2,'1. Precursorie'!M19,0)))) -> 0
A20: 1. Precursorie | B20: 1. Sida | C20: P11 | D20: 1010 | E20: P11 | F20: 5000 | G20: 29281 | H20: 1° Gruppo SIDA | I20: Bianca / Bandella Sagomata | J20: - | K20: Pik | L20: 200 | M20: P.A.R. | N20: P.A.R. | P20: Manca | S20: =IF(P20='Menu tendina'!A$5,0,IF(P20='Menu tendina'!A$4,'1. Precursorie'!N20/2,IF(P20='Menu tendina'!A$3,'1. Precursorie'!N20,IF(P20='Menu tendina'!A$2,'1. Precursorie'!M20,0)))) -> 0
A21: 1. Precursorie | B21: 1. Sida | C21: P11A | D21: - | E21: - | F21: 5000 | G21: 29281 | H21: 1° Gruppo SIDA | I21: Grigia / Bandella Sagomata | J21: Variante | K21: Pik | L21: 200 | M21: P.A.R. | N21: P.A.R. | P21: Manca | S21: =IF(P21='Menu tendina'!A$5,0,IF(P21='Menu tendina'!A$4,'1. Precursorie'!N21/2,IF(P21='Menu tendina'!A$3,'1. Precursorie'!N21,IF(P21='Menu tendina'!A$2,'1. Precursorie'!M21,0)))) -> 0
A22: 1. Precursorie | B22: 1. Sida | C22: P12 | D22: 1010B | E22: P12 | F22: 9000 | G22: 29281 | H22: 1° Gruppo SIDA | I22: Bianca / Bandella Sagomata | J22: - | K22: Pik | L22: - | M22: P.A.R. | N22: P.A.R. | P22: Manca | S22: =IF(P22='Menu tendina'!A$5,0,IF(P22='Menu tendina'!A$4,'1. Precursorie'!N22/2,IF(P22='Menu tendina'!A$3,'1. Precursorie'!N22,IF(P22='Menu tendina'!A$2,'1. Precursorie'!M22,0)))) -> 0
A23: 1. Precursorie | B23: 1. Sida | C23: P13 | D23: 1011 | E23: P13 | F23: 2000 | G23: 29677 | H23: 1° Gruppo SIDA | I23: Bandella Sagomata | J23: - | K23: Pik | L23: 200 | M23: 20 | N23: 10 | P23: Nuova | Q23: No | S23: =IF(P23='Menu tendina'!A$5,0,IF(P23='Menu tendina'!A$4,'1. Precursorie'!N23/2,IF(P23='Menu tendina'!A$3,'1. Precursorie'!N23,IF(P23='Menu tendina'!A$2,'1. Precursorie'!M23,0)))) -> 20
A24: 1. Precursorie | B24: 1. Sida | C24: P13A | D24: 1011A | E24: P13A | F24: 2000 | G24: 29677 | H24: 1° Gruppo SIDA | I24: Bandella Diritta | J24: Variante | K24: Pik | L24: 200 | M24: 35 | N24: 15 | P24: Nuova | Q24: No | S24: =IF(P24='Menu tendina'!A$5,0,IF(P24='Menu tendina'!A$4,'1. Precursorie'!N24/2,IF(P24='Menu tendina'!A$3,'1. Precursorie'!N24,IF(P24='Menu tendina'!A$2,'1. Precursorie'!M24,0)))) -> 35
A25: 1. Precursorie | B25: 1. Sida | C25: P14 | D25: 1012 | E25: P14 | F25: 5000 | G25: 29677 | H25: 1° Gruppo SIDA | I25: Bandella Sagomata | J25: - | K25: Pik | L25: 200 | M25: 20 | N25: 10 | P25: Nuova | Q25: Sì | S25: =IF(P25='Menu tendina'!A$5,0,IF(P25='Menu tendina'!A$4,'1. Precursorie'!N25/2,IF(P25='Menu tendina'!A$3,'1. Precursorie'!N25,IF(P25='Menu tendina'!A$2,'1. Precursorie'!M25,0)))) -> 20
A26: 1. Precursorie | B26: 1. Sida | C26: P14A | D26: 1012A | E26: #N/A | F26: 5000 | G26: 29677 | H26: 1° Gruppo SIDA | I26: Bandella Diritta | J26: Variante | K26: Pik | L26: 200 | M26: 35 | N26: 15 | P26: Nuova | Q26: No | S26: =IF(P26='Menu tendina'!A$5,0,IF(P26='Menu tendina'!A$4,'1. Precursorie'!N26/2,IF(P26='Menu tendina'!A$3,'1. Precursorie'!N26,IF(P26='Menu tendina'!A$2,'1. Precursorie'!M26,0)))) -> 35
A27: 1. Precursorie | B27: 1. Sida | C27: P15 | D27: 1013 | E27: P15 | F27: 9000 | G27: 29677 | H27: 1° Gruppo SIDA | I27: Bandella Sagomata | J27: - | K27: Pik | L27: 200 | M27: 150 | N27: 25 | P27: Manca | S27: =IF(P27='Menu tendina'!A$5,0,IF(P27='Menu tendina'!A$4,'1. Precursorie'!N27/2,IF(P27='Menu tendina'!A$3,'1. Precursorie'!N27,IF(P27='Menu tendina'!A$2,'1. Precursorie'!M27,0)))) -> 0
A28: 1. Precursorie | B28: 1. Sida | C28: P15A | D28: 1013A | E28: P15A | F28: 9000 | G28: 29677 | H28: 1° Gruppo SIDA | I28: Bandella Diritta | J28: Variante | K28: Pik | L28: 200 | M28: 80 | N28: 25 | P28: Nuova | Q28: No | S28: =IF(P28='Menu tendina'!A$5,0,IF(P28='Menu tendina'!A$4,'1. Precursorie'!N28/2,IF(P28='Menu tendina'!A$3,'1. Precursorie'!N28,IF(P28='Menu tendina'!A$2,'1. Precursorie'!M28,0)))) -> 80
A29: 1. Precursorie | B29: 1. Sida | C29: P16 | D29: 1014 | E29: P16 | F29: 3000 | G29: 29983 | H29: 2° Gruppo SIDA | I29: Zona 6 "Times" | J29: - | K29: Pik | L29: 2600 | M29: 40 | N29: 15 | P29: 2a scelta | Q29: Sì | S29: =IF(P29='Menu tendina'!A$5,0,IF(P29='Menu tendina'!A$4,'1. Precursorie'!N29/2,IF(P29='Menu tendina'!A$3,'1. Precursorie'!N29,IF(P29='Menu tendina'!A$2,'1. Precursorie'!M29,0)))) -> 7.5
A30: 1. Precursorie | B30: 1. Sida | C30: P16A | D30: 1014a | E30: P16A | F30: 3000 | G30: 29983 | H30: 2° Gruppo SIDA - Zonale | I30: Zona 1 "Helvetica" | J30: Variante | K30: Pik | L30: 100 | M30: - | N30: 50 | P30: Manca | S30: =IF(P30='Menu tendina'!A$5,0,IF(P30='Menu tendina'!A$4,'1. Precursorie'!N30/2,IF(P30='Menu tendina'!A$3,'1. Precursorie'!N30,IF(P30='Menu tendina'!A$2,'1. Precursorie'!M30,0)))) -> 0
A31: 1. Precursorie | B31: 1. Sida | C31: P16B | D31: 1014b | E31: P16B | F31: 3000 | G31: 29983 | H31: 2° Gruppo SIDA - Zonale | I31: Zona 1 "Times" | J31: Variante | K31: Pik | L31: 200 | M31: - | N31: 35 | P31: Usata | S31: =IF(P31='Menu tendina'!A$5,0,IF(P31='Menu tendina'!A$4,'1. Precursorie'!N31/2,IF(P31='Menu tendina'!A$3,'1. Precursorie'!N31,IF(P31='Menu tendina'!A$2,'1. Precursorie'!M31,0)))) -> 35
A32: 1. Precursorie | B32: 1. Sida | C32: P16C | D32: 1014c | E32: P16C | F32: 3000 | G32: 29983 | H32: 2° Gruppo SIDA - Zonale | I32: Zona 2 "Helvetica" | J32: Variante | K32: Pik | L32: 100 | M32: - | N32: 50 | P32: Manca | S32: =IF(P32='Menu tendina'!A$5,0,IF(P32='Menu tendina'!A$4,'1. Precursorie'!N32/2,IF(P32='Menu tendina'!A$3,'1. Precursorie'!N32,IF(P32='Menu tendina'!A$2,'1. Precursorie'!M32,0)))) -> 0
A33: 1. Precursorie | B33: 1. Sida | C33: P16D | D33: 1014d | E33: P16D | F33: 3000 | G33: 29983 | H33: 2° Gruppo SIDA - Zonale | I33: Zona 3 "Helvetica" | J33: Variante | K33: Pik | L33: 100 | M33: - | N33: 30 | P33: 2a scelta | S33: =IF(P33='Menu tendina'!A$5,0,IF(P33='Menu tendina'!A$4,'1. Precursorie'!N33/2,IF(P33='Menu tendina'!A$3,'1. Precursorie'!N33,IF(P33='Menu tendina'!A$2,'1. Precursorie'!M33,0)))) -> 15
A34: 1. Precursorie | B34: 1. Sida | C34: P16E | D34: 1014e | E34: P16E | F34: 3000 | G34: 29983 | H34: 2° Gruppo SIDA - Zonale | I34: Zona 4 "Helvetica" | J34: Variante | K34: Pik | L34: 100 | M34: - | N34: 25 | P34: Usata | Q34: Sì | S34: =IF(P34='Menu tendina'!A$5,0,IF(P34='Menu tendina'!A$4,'1. Precursorie'!N34/2,IF(P34='Menu tendina'!A$3,'1. Precursorie'!N34,IF(P34='Menu tendina'!A$2,'1. Precursorie'!M34,0)))) -> 25
A35: 1. Precursorie | B35: 1. Sida | C35: P16F | D35: 1014f | E35: P16F | F35: 3000 | G35: 29983 | H35: 2° Gruppo SIDA - Zonale | I35: Zona 4 "Times" | J35: Variante | K35: Pik | L35: 200 | M35: - | N35: 25 | P35: Usata | S35: =IF(P35='Menu tendina'!A$5,0,IF(P35='Menu tendina'!A$4,'1. Precursorie'!N35/2,IF(P35='Menu tendina'!A$3,'1. Precursorie'!N35,IF(P35='Menu tendina'!A$2,'1. Precursorie'!M35,0)))) -> 25
A36: 1. Precursorie | B36: 1. Sida | C36: P16G | D36: 1014g | E36: P16G | F36: 3000 | G36: 29983 | H36: 2° Gruppo SIDA - Zonale | I36: Zona 5 "Helvetica" | J36: Variante | K36: Pik | L36: 100 | M36: - | N36: 20 | P36: Nuova | Q36: No | S36: =IF(P36='Menu tendina'!A$5,0,IF(P36='Menu tendina'!A$4,'1. Precursorie'!N36/2,IF(P36='Menu tendina'!A$3,'1. Precursorie'!N36,IF(P36='Menu tendina'!A$2,'1. Precursorie'!M36,0)))) -> -
A37: 1. Precursorie | B37: 1. Sida | C37: P16H | D37: 1014h | E37: P16H | F37: 3000 | G37: 29983 | H37: 2° Gruppo SIDA - Zonale | I37: Zona 5 "Times" | J37: Variante | K37: Pik | L37: 200 | M37: - | N37: 20 | P37: Usata | S37: =IF(P37='Menu tendina'!A$5,0,IF(P37='Menu tendina'!A$4,'1. Precursorie'!N37/2,IF(P37='Menu tendina'!A$3,'1. Precursorie'!N37,IF(P37='Menu tendina'!A$2,'1. Precursorie'!M37,0)))) -> 20
A38: 1. Precursorie | B38: 1. Sida | C38: P16L | D38: - | E38: - | F38: 3000 | G38: 29983 | H38: 2° Gruppo SIDA - Zonale | I38: Zona 7 "Helvetica" | J38: Variante | K38: Pik | L38: - | M38: - | N38: 300 | P38: Manca | S38: =IF(P38='Menu tendina'!A$5,0,IF(P38='Menu tendina'!A$4,'1. Precursorie'!N38/2,IF(P38='Menu tendina'!A$3,'1. Precursorie'!N38,IF(P38='Menu tendina'!A$2,'1. Precursorie'!M38,0)))) -> 0
A39: 1. Precursorie | B39: 1. Sida | C39: P17 | D39: 1015 | E39: P17 | F39: 6000 | G39: 29983 | H39: 2° Gruppo SIDA | I39: Zona 6 "Times" | J39: - | K39: Pik | L39: 1500 | M39: 15 | N39: 10 | P39: Nuova | Q39: Sì | S39: =IF(P39='Menu tendina'!A$5,0,IF(P39='Menu tendina'!A$4,'1. Precursorie'!N39/2,IF(P39='Menu tendina'!A$3,'1. Precursorie'!N39,IF(P39='Menu tendina'!A$2,'1. Precursorie'!M39,0)))) -> 15
A40: 1. Precursorie | B40: 1. Sida | C40: P17A | D40: 1015a | E40: P17A | F40: 6000 | G40: 29983 | H40: 2° Gruppo SIDA - Zonale | I40: Zona 1 "Helvetica" | J40: Variante | K40: Pik | L40: 100 | M40: - | N40: 45 | P40: Usata | S40: =IF(P40='Menu tendina'!A$5,0,IF(P40='Menu tendina'!A$4,'1. Precursorie'!N40/2,IF(P40='Menu tendina'!A$3,'1. Precursorie'!N40,IF(P40='Menu tendina'!A$2,'1. Precursorie'!M40,0)))) -> 45
A41: 1. Precursorie | B41: 1. Sida | C41: P17B | D41: 1015b | E41: P17B | F41: 6000 | G41: 29983 | H41: 2° Gruppo SIDA - Zonale | I41: Zona 1 "Times" | J41: Variante | K41: Pik | L41: 100 | M41: - | N41: 45 | P41: Usata | Q41: Sì | S41: =IF(P41='Menu tendina'!A$5,0,IF(P41='Menu tendina'!A$4,'1. Precursorie'!N41/2,IF(P41='Menu tendina'!A$3,'1. Precursorie'!N41,IF(P41='Menu tendina'!A$2,'1. Precursorie'!M41,0)))) -> 45
A42: 1. Precursorie | B42: 1. Sida | C42: P17C | D42: 1015c | E42: P17C | F42: 6000 | G42: 29983 | H42: 2° Gruppo SIDA - Zonale | I42: Zona 2 "Helvetica" | J42: Variante | K42: Pik | L42: 100 | M42: - | N42: 45 | P42: Usata | Q42: Sì | S42: =IF(P42='Menu tendina'!A$5,0,IF(P42='Menu tendina'!A$4,'1. Precursorie'!N42/2,IF(P42='Menu tendina'!A$3,'1. Precursorie'!N42,IF(P42='Menu tendina'!A$2,'1. Precursorie'!M42,0)))) -> 45
A43: 1. Precursorie | B43: 1. Sida | C43: P17D | D43: 1015d | E43: P17D | F43: 6000 | G43: 29983 | H43: 2° Gruppo SIDA - Zonale | I43: Zona 3 "Helvetica" | J43: Variante | K43: Pik | L43: 100 | M43: - | N43: 30 | P43: Manca | S43: =IF(P43='Menu tendina'!A$5,0,IF(P43='Menu tendina'!A$4,'1. Precursorie'!N43/2,IF(P43='Menu tendina'!A$3,'1. Precursorie'!N43,IF(P43='Menu tendina'!A$2,'1. Precursorie'!M43,0)))) -> 0
A44: 1. Precursorie | B44: 1. Sida | C44: P17E | D44: 1015e | E44: P17E | F44: 6000 | G44: 29983 | H44: 2° Gruppo SIDA - Zonale | I44: Zona 4 "Helvetica" | J44: Variante | K44: Pik | L44: 100 | M44: - | N44: 65 | P44: Usata | Q44: Sì | S44: =IF(P44='Menu tendina'!A$5,0,IF(P44='Menu tendina'!A$4,'1. Precursorie'!N44/2,IF(P44='Menu tendina'!A$3,'1. Precursorie'!N44,IF(P44='Menu tendina'!A$2,'1. Precursorie'!M44,0)))) -> 65
A45: 1. Precursorie | B45: 1. Sida | C45: P17F | D45: 1015f | E45: P17F | F45: 6000 | G45: 29983 | H45: 2° Gruppo SIDA - Zonale | I45: Zona 4 "Times" | J45: Variante | K45: Pik | L45: 200 | M45: - | N45: 25 | P45: Usata | S45: =IF(P45='Menu tendina'!A$5,0,IF(P45='Menu tendina'!A$4,'1. Precursorie'!N45/2,IF(P45='Menu tendina'!A$3,'1. Precursorie'!N45,IF(P45='Menu tendina'!A$2,'1. Precursorie'!M45,0)))) -> 25
A46: 1. Precursorie | B46: 1. Sida | C46: P17G | D46: 1015g | E46: P17G | F46: 6000 | G46: 29983 | H46: 2° Gruppo SIDA - Zonale | I46: Zona 5 "Helvetica" | J46: Variante | K46: Pik | L46: 100 | M46: - | N46: 45 | P46: Manca | S46: =IF(P46='Menu tendina'!A$5,0,IF(P46='Menu tendina'!A$4,'1. Precursorie'!N46/2,IF(P46='Menu tendina'!A$3,'1. Precursorie'!N46,IF(P46='Menu tendina'!A$2,'1. Precursorie'!M46,0)))) -> 0
A47: 1. Precursorie | B47: 1. Sida | C47: P17H | D47: 1015h | E47: P17H | F47: 6000 | G47: 29983 | H47: 2° Gruppo SIDA - Zonale | I47: Zona 5 "Times" | J47: Variante | K47: Pik | L47: 100 | M47: - | N47: 45 | P47: Nuova | Q47: No | S47: =IF(P47='Menu tendina'!A$5,0,IF(P47='Menu tendina'!A$4,'1. Precursorie'!N47/2,IF(P47='Menu tendina'!A$3,'1. Precursorie'!N47,IF(P47='Menu tendina'!A$2,'1. Precursorie'!M47,0)))) -> -
A48: 1. Precursorie | B48: 1. Sida | C48: P17L | D48: - | E48: - | F48: 6000 | G48: 29983 | H48: 2° Gruppo SIDA - Zonale | I48: Zona 7 "Helvetica" | J48: Variante | K48: Pik | L48: - | M48: - | N48: 400 | P48: Manca | S48: =IF(P48='Menu tendina'!A$5,0,IF(P48='Menu tendina'!A$4,'1. Precursorie'!N48/2,IF(P48='Menu tendina'!A$3,'1. Precursorie'!N48,IF(P48='Menu tendina'!A$2,'1. Precursorie'!M48,0)))) -> 0
A49: 1. Precursorie | B49: 1. Sida | C49: P18 | D49: 1016 | E49: P18 | F49: 9000 | G49: 29983 | H49: 2° Gruppo SIDA | I49: Zona 6 "Times" | J49: - | K49: Pik | L49: 500 | M49: 100 | N49: 15 | P49: Usata | S49: =IF(P49='Menu tendina'!A$5,0,IF(P49='Menu tendina'!A$4,'1. Precursorie'!N49/2,IF(P49='Menu tendina'!A$3,'1. Precursorie'!N49,IF(P49='Menu tendina'!A$2,'1. Precursorie'!M49,0)))) -> 15
A50: 1. Precursorie | B50: 1. Sida | C50: P18A | D50: 1016a | E50: P18A | F50: 9000 | G50: 29983 | H50: 2° Gruppo SIDA - Zonale | I50: Zona 1 "Helvetica" | J50: Variante | K50: Pik | L50: 100 | M50: - | N50: 35 | P50: 2a scelta | S50: =IF(P50='Menu tendina'!A$5,0,IF(P50='Menu tendina'!A$4,'1. Precursorie'!N50/2,IF(P50='Menu tendina'!A$3,'1. Precursorie'!N50,IF(P50='Menu tendina'!A$2,'1. Precursorie'!M50,0)))) -> 17.5
A51: 1. Precursorie | B51: 1. Sida | C51: P18B | D51: 1016b | E51: P18B | F51: 9000 | G51: 29983 | H51: 2° Gruppo SIDA - Zonale | I51: Zona 1 "Times" | J51: Variante | K51: Pik | L51: 100 | M51: - | N51: 50 | P51: Usata | S51: =IF(P51='Menu tendina'!A$5,0,IF(P51='Menu tendina'!A$4,'1. Precursorie'!N51/2,IF(P51='Menu tendina'!A$3,'1. Precursorie'!N51,IF(P51='Menu tendina'!A$2,'1. Precursorie'!M51,0)))) -> 50
A52: 1. Precursorie | B52: 1. Sida | C52: P18C | D52: 1016c | E52: P18C | F52: 9000 | G52: 29983 | H52: 2° Gruppo SIDA - Zonale | I52: Zona 2 "Helvetica" | J52: Variante | K52: Pik | L52: 100 | M52: - | N52: 25 | P52: Usata | S52: =IF(P52='Menu tendina'!A$5,0,IF(P52='Menu tendina'!A$4,'1. Precursorie'!N52/2,IF(P52='Menu tendina'!A$3,'1. Precursorie'!N52,IF(P52='Menu tendina'!A$2,'1. Precursorie'!M52,0)))) -> 25
A53: 1. Precursorie | B53: 1. Sida | C53: P18D | D53: 1016d | E53: P18D | F53: 9000 | G53: 29983 | H53: 2° Gruppo SIDA - Zonale | I53: Zona 3 "Helvetica" | J53: Variante | K53: Pik | L53: 100 | M53: - | N53: 25 | P53: Nuova | S53: =IF(P53='Menu tendina'!A$5,0,IF(P53='Menu tendina'!A$4,'1. Precursorie'!N53/2,IF(P53='Menu tendina'!A$3,'1. Precursorie'!N53,IF(P53='Menu tendina'!A$2,'1. Precursorie'!M53,0)))) -> -
A54: 1. Precursorie | B54: 1. Sida | C54: P18E | D54: 1016e | E54: P18E | F54: 9000 | G54: 29983 | H54: 2° Gruppo SIDA - Zonale | I54: Zona 4 "Helvetica" | J54: Variante | K54: Pik | L54: 100 | M54: - | N54: 25 | P54: Usata | S54: =IF(P54='Menu tendina'!A$5,0,IF(P54='Menu tendina'!A$4,'1. Precursorie'!N54/2,IF(P54='Menu tendina'!A$3,'1. Precursorie'!N54,IF(P54='Menu tendina'!A$2,'1. Precursorie'!M54,0)))) -> 25
A55: 1. Precursorie | B55: 1. Sida | C55: P18F | D55: 1016f | E55: P18F | F55: 9000 | G55: 29983 | H55: 2° Gruppo SIDA - Zonale | I55: Zona 4 "Times" | J55: Variante | K55: Pik | L55: 100 | M55: - | N55: 25 | P55: Usata | S55: =IF(P55='Menu tendina'!A$5,0,IF(P55='Menu tendina'!A$4,'1. Precursorie'!N55/2,IF(P55='Menu tendina'!A$3,'1. Precursorie'!N55,IF(P55='Menu tendina'!A$2,'1. Precursorie'!M55,0)))) -> 25
A56: 1. Precursorie | B56: 1. Sida | C56: P18G | D56: 1016g | E56: P18G | F56: 9000 | G56: 29983 | H56: 2° Gruppo SIDA - Zonale | I56: Zona 5 "Helvetica" | J56: Variante | K56: Pik | L56: 100 | M56: - | N56: 45 | P56: Nuova | Q56: No | S56: =IF(P56='Menu tendina'!A$5,0,IF(P56='Menu tendina'!A$4,'1. Precursorie'!N56/2,IF(P56='Menu tendina'!A$3,'1. Precursorie'!N56,IF(P56='Menu tendina'!A$2,'1. Precursorie'!M56,0)))) -> -
A57: 1. Precursorie | B57: 1. Sida | C57: P18H | D57: 1016h | E57: P18H | F57: 9000 | G57: 29983 | H57: 2° Gruppo SIDA - Zonale | I57: Zona 5 "Times" | J57: Variante | K57: Pik | L57: 100 | M57: - | N57: 20 | P57: Manca | S57: =IF(P57='Menu tendina'!A$5,0,IF(P57='Menu tendina'!A$4,'1. Precursorie'!N57/2,IF(P57='Menu tendina'!A$3,'1. Precursorie'!N57,IF(P57='Menu tendina'!A$2,'1. Precursorie'!M57,0)))) -> 0
A58: 1. Precursorie | B58: 1. Sida | C58: P18L | D58: - | E58: - | F58: 9000 | G58: 29983 | H58: 2° Gruppo SIDA - Zonale | I58: Zona 7 "Helvetica" | J58: Variante | K58: Pik | L58: - | M58: - | N58: P.A.R. | P58: Manca | S58: =IF(P58='Menu tendina'!A$5,0,IF(P58='Menu tendina'!A$4,'1. Precursorie'!N58/2,IF(P58='Menu tendina'!A$3,'1. Precursorie'!N58,IF(P58='Menu tendina'!A$2,'1. Precursorie'!M58,0)))) -> 0
A59: 1. Precursorie | B59: 1. Sida | C59: P19 | D59: 1017 | E59: P19 | F59: 3000 | G59: 31079 | H59: 2° Gruppo SIDA | I59: - | J59: - | K59: Pik | L59: 200 | M59: 200 | N59: 25 | P59: Manca | S59: =IF(P59='Menu tendina'!A$5,0,IF(P59='Menu tendina'!A$4,'1. Precursorie'!N59/2,IF(P59='Menu tendina'!A$3,'1. Precursorie'!N59,IF(P59='Menu tendina'!A$2,'1. Precursorie'!M59,0)))) -> 0
A60: 1. Precursorie | B60: 1. Sida | C60: P20 | D60: 1018 | E60: P20 | F60: 9000 | G60: 31079 | H60: 2° Gruppo SIDA | I60: - | J60: - | K60: Pik | L60: 100 | M60: 350 | N60: 150 | P60: Manca | S60: =IF(P60='Menu tendina'!A$5,0,IF(P60='Menu tendina'!A$4,'1. Precursorie'!N60/2,IF(P60='Menu tendina'!A$3,'1. Precursorie'!N60,IF(P60='Menu tendina'!A$2,'1. Precursorie'!M60,0)))) -> 0
A61: 1. Precursorie | B61: 1. Sida | C61: P21 | D61: 1022 | E61: P21 | F61: 3000 | G61: 31107 | H61: 2° Gruppo SIDA | I61: - | J61: - | K61: Pik | L61: 400 | M61: 65 | N61: 20 | P61: Nuova | Q61: No | S61: =IF(P61='Menu tendina'!A$5,0,IF(P61='Menu tendina'!A$4,'1. Precursorie'!N61/2,IF(P61='Menu tendina'!A$3,'1. Precursorie'!N61,IF(P61='Menu tendina'!A$2,'1. Precursorie'!M61,0)))) -> 65
A62: 1. Precursorie | B62: 1. Sida | C62: P22 | D62: 1023 | E62: P22 | F62: 6000 | G62: 31107 | H62: 2° Gruppo SIDA | I62: - | J62: - | K62: Pik | L62: 300 | M62: 85 | N62: 20 | P62: Usata | Q62: Sì | S62: =IF(P62='Menu tendina'!A$5,0,IF(P62='Menu tendina'!A$4,'1. Precursorie'!N62/2,IF(P62='Menu tendina'!A$3,'1. Precursorie'!N62,IF(P62='Menu tendina'!A$2,'1. Precursorie'!M62,0)))) -> 20
A63: 1. Precursorie | B63: 1. Sida | C63: P23 | D63: 1024 | E63: P23 | F63: 9000 | G63: 31107 | H63: 2° Gruppo SIDA | I63: - | J63: - | K63: Pik | L63: 200 | M63: 85 | N63: 30 | P63: Usata | Q63: Sì | S63: =IF(P63='Menu tendina'!A$5,0,IF(P63='Menu tendina'!A$4,'1. Precursorie'!N63/2,IF(P63='Menu tendina'!A$3,'1. Precursorie'!N63,IF(P63='Menu tendina'!A$2,'1. Precursorie'!M63,0)))) -> 30
A64: 1. Precursorie | B64: 1. Sida | C64: P24 | D64: 1025 | E64: P24 | F64: 3000 | G64: 31138 | H64: 2° Gruppo SIDA | I64: Matrice Lato Valore a 5 Cifre | J64: - | K64: Pik | L64: 500 | M64: 70 | N64: 20 | P64: Usata | Q64: Sì | S64: =IF(P64='Menu tendina'!A$5,0,IF(P64='Menu tendina'!A$4,'1. Precursorie'!N64/2,IF(P64='Menu tendina'!A$3,'1. Precursorie'!N64,IF(P64='Menu tendina'!A$2,'1. Precursorie'!M64,0)))) -> 20
A65: 1. Precursorie | B65: 1. Sida | C65: P24A | D65: - | E65: - | F65: 3000 | G65: 31138 | H65: 2° Gruppo SIDA | I65: Matrice Lato Valore a 6 Cifre | J65: Variante | K65: Pik | L65: - | M65: 100 | N65: 35 | P65: Manca | S65: =IF(P65='Menu tendina'!A$5,0,IF(P65='Menu tendina'!A$4,'1. Precursorie'!N65/2,IF(P65='Menu tendina'!A$3,'1. Precursorie'!N65,IF(P65='Menu tendina'!A$2,'1. Precursorie'!M65,0)))) -> 0
A66: 1. Precursorie | B66: 1. Sida | C66: P25 | D66: 1026 | E66: P25 | F66: 6000 | G66: 31138 | H66: 2° Gruppo SIDA | I66: - | J66: - | K66: Pik | L66: 300 | M66: 80 | N66: 20 | P66: Usata | Q66: Sì | S66: =IF(P66='Menu tendina'!A$5,0,IF(P66='Menu tendina'!A$4,'1. Precursorie'!N66/2,IF(P66='Menu tendina'!A$3,'1. Precursorie'!N66,IF(P66='Menu tendina'!A$2,'1. Precursorie'!M66,0)))) -> 20
A67: 1. Precursorie | B67: 1. Sida | C67: P26 | D67: 1027 | E67: P26 | F67: 9000 | G67: 31138 | H67: 2° Gruppo SIDA | I67: - | J67: - | K67: Pik | L67: 400 | M67: 75 | N67: 20 | P67: Usata | Q67: Sì | S67: =IF(P67='Menu tendina'!A$5,0,IF(P67='Menu tendina'!A$4,'1. Precursorie'!N67/2,IF(P67='Menu tendina'!A$3,'1. Precursorie'!N67,IF(P67='Menu tendina'!A$2,'1. Precursorie'!M67,0)))) -> 20
A68: 1. Precursorie | B68: 1. Sida | C68: P27 | D68: 1028 | E68: P27 | F68: 3000 | G68: 31168 | H68: 2° Gruppo SIDA | I68: - | J68: - | K68: Pik | L68: 500 | M68: 70 | N68: 20 | P68: Nuova | Q68: Sì | S68: =IF(P68='Menu tendina'!A$5,0,IF(P68='Menu tendina'!A$4,'1. Precursorie'!N68/2,IF(P68='Menu tendina'!A$3,'1. Precursorie'!N68,IF(P68='Menu tendina'!A$2,'1. Precursorie'!M68,0)))) -> 70
A69: 1. Precursorie | B69: 1. Sida | C69: P28 | D69: 1029 | E69: P28 | F69: 6000 | G69: 31168 | H69: 2° Gruppo SIDA | I69: - | J69: - | K69: Pik | L69: 300 | M69: 80 | N69: 35 | P69: Usata | Q69: Sì | S69: =IF(P69='Menu tendina'!A$5,0,IF(P69='Menu tendina'!A$4,'1. Precursorie'!N69/2,IF(P69='Menu tendina'!A$3,'1. Precursorie'!N69,IF(P69='Menu tendina'!A$2,'1. Precursorie'!M69,0)))) -> 35
A70: 1. Precursorie | B70: 1. Sida | C70: P29 | D70: 1030 | E70: P29 | F70: 3000 | G70: 31199 | H70: 2° Gruppo SIDA | I70: - | J70: - | K70: Pik | L70: 500 | M70: 70 | N70: 20 | P70: Usata | Q70: Sì | S70: =IF(P70='Menu tendina'!A$5,0,IF(P70='Menu tendina'!A$4,'1. Precursorie'!N70/2,IF(P70='Menu tendina'!A$3,'1. Precursorie'!N70,IF(P70='Menu tendina'!A$2,'1. Precursorie'!M70,0)))) -> 20
A71: 1. Precursorie | B71: 1. Sida | C71: P30 | D71: 1031 | E71: P30 | F71: 6000 | G71: 31199 | H71: 2° Gruppo SIDA | I71: - | J71: - | K71: Pik | L71: 300 | M71: 75 | N71: 20 | P71: Usata | Q71: Sì | S71: =IF(P71='Menu tendina'!A$5,0,IF(P71='Menu tendina'!A$4,'1. Precursorie'!N71/2,IF(P71='Menu tendina'!A$3,'1. Precursorie'!N71,IF(P71='Menu tendina'!A$2,'1. Precursorie'!M71,0)))) -> 20
A72: 1. Precursorie | B72: 1. Sida | C72: P31 | D72: 1032 | E72: P31 | F72: 3000 | G72: 31229 | H72: 2° Gruppo SIDA | I72: - | J72: - | K72: Pik | L72: 500 | M72: 65 | N72: 20 | P72: Usata | Q72: Sì | S72: =IF(P72='Menu tendina'!A$5,0,IF(P72='Menu tendina'!A$4,'1. Precursorie'!N72/2,IF(P72='Menu tendina'!A$3,'1. Precursorie'!N72,IF(P72='Menu tendina'!A$2,'1. Precursorie'!M72,0)))) -> 20
A73: 1. Precursorie | B73: 1. Sida | C73: P32 | D73: 1033 | E73: P32 | F73: 6000 | G73: 31229 | H73: 2° Gruppo SIDA | I73: - | J73: - | K73: Pik | L73: 300 | M73: 20 | N73: 10 | P73: Nuova | Q73: No | S73: =IF(P73='Menu tendina'!A$5,0,IF(P73='Menu tendina'!A$4,'1. Precursorie'!N73/2,IF(P73='Menu tendina'!A$3,'1. Precursorie'!N73,IF(P73='Menu tendina'!A$2,'1. Precursorie'!M73,0)))) -> 20
A74: 1. Precursorie | B74: 1. Sida | C74: P33 | D74: 1034 | E74: P33 | F74: 9000 | G74: 31229 | H74: 2° Gruppo SIDA | I74: - | J74: - | K74: Pik | L74: 100 | M74: P.A.R. | N74: 380 | P74: Manca | S74: =IF(P74='Menu tendina'!A$5,0,IF(P74='Menu tendina'!A$4,'1. Precursorie'!N74/2,IF(P74='Menu tendina'!A$3,'1. Precursorie'!N74,IF(P74='Menu tendina'!A$2,'1. Precursorie'!M74,0)))) -> 0
A75: 1. Precursorie | B75: 1. Sida | C75: P34 | D75: 1038 | E75: P34 | F75: 3000 | G75: 31533 | H75: 3° Gruppo SIDA | I75: - | J75: - | K75: Pik | L75: 100 | M75: 70 | N75: 12 | P75: Usata | Q75: Sì | S75: =IF(P75='Menu tendina'!A$5,0,IF(P75='Menu tendina'!A$4,'1. Precursorie'!N75/2,IF(P75='Menu tendina'!A$3,'1. Precursorie'!N75,IF(P75='Menu tendina'!A$2,'1. Precursorie'!M75,0)))) -> 12
A76: 1. Precursorie | B76: 1. Sida | C76: P35 | D76: 1039 | E76: P35 | F76: 6000 | G76: 31533 | H76: 3° Gruppo SIDA | I76: - | J76: - | K76: Pik | L76: 300 | M76: 50 | N76: 10 | P76: Usata | Q76: Sì | S76: =IF(P76='Menu tendina'!A$5,0,IF(P76='Menu tendina'!A$4,'1. Precursorie'!N76/2,IF(P76='Menu tendina'!A$3,'1. Precursorie'!N76,IF(P76='Menu tendina'!A$2,'1. Precursorie'!M76,0)))) -> 10
A77: 1. Precursorie | B77: 1. Sida | C77: P36 | D77: 1040 | E77: P36 | F77: 9000 | G77: 31533 | H77: 3° Gruppo SIDA | I77: - | J77: - | K77: Pik | L77: 200 | M77: 60 | N77: 10 | P77: Nuova | Q77: Sì | S77: =IF(P77='Menu tendina'!A$5,0,IF(P77='Menu tendina'!A$4,'1. Precursorie'!N77/2,IF(P77='Menu tendina'!A$3,'1. Precursorie'!N77,IF(P77='Menu tendina'!A$2,'1. Precursorie'!M77,0)))) -> 60
A78: 1. Precursorie | B78: 1. Sida | C78: P37 | D78: 1044 | E78: P37 | F78: 3000 | G78: 31564 | H78: 3° Gruppo SIDA | I78: - | J78: - | K78: Pik | L78: 500 | M78: 40 | N78: 8 | P78: Usata | Q78: Sì | S78: =IF(P78='Menu tendina'!A$5,0,IF(P78='Menu tendina'!A$4,'1. Precursorie'!N78/2,IF(P78='Menu tendina'!A$3,'1. Precursorie'!N78,IF(P78='Menu tendina'!A$2,'1. Precursorie'!M78,0)))) -> 8
A79: 1. Precursorie | B79: 1. Sida | C79: P38 | D79: 1045 | E79: P38 | F79: 6000 | G79: 31564 | H79: 3° Gruppo SIDA | I79: - | J79: - | K79: Pik | L79: 500 | M79: 60 | N79: 8 | P79: Nuova | Q79: No | S79: =IF(P79='Menu tendina'!A$5,0,IF(P79='Menu tendina'!A$4,'1. Precursorie'!N79/2,IF(P79='Menu tendina'!A$3,'1. Precursorie'!N79,IF(P79='Menu tendina'!A$2,'1. Precursorie'!M79,0)))) -> 60
A80: 1. Precursorie | B80: 1. Sida | C80: P39 | D80: 1046 | E80: P39 | F80: 9000 | G80: 31564 | H80: 3° Gruppo SIDA | I80: - | J80: - | K80: Pik | L80: 400 | M80: 40 | N80: 6 | P80: Usata | Q80: Sì | S80: =IF(P80='Menu tendina'!A$5,0,IF(P80='Menu tendina'!A$4,'1. Precursorie'!N80/2,IF(P80='Menu tendina'!A$3,'1. Precursorie'!N80,IF(P80='Menu tendina'!A$2,'1. Precursorie'!M80,0)))) -> 6
A81: 1. Precursorie | B81: 1. Sida | C81: P40 | D81: 1047 | E81: P40 | F81: 3000 | G81: 31594 | H81: 3° Gruppo SIDA | I81: - | J81: - | K81: Pik | L81: 700 | M81: 30 | N81: 3 | P81: Usata | Q81: Sì | S81: =IF(P81='Menu tendina'!A$5,0,IF(P81='Menu tendina'!A$4,'1. Precursorie'!N81/2,IF(P81='Menu tendina'!A$3,'1. Precursorie'!N81,IF(P81='Menu tendina'!A$2,'1. Precursorie'!M81,0)))) -> 3
A82: 1. Precursorie | B82: 1. Sida | C82: P41 | D82: 1048 | E82: P41 | F82: 6000 | G82: 31594 | H82: 3° Gruppo SIDA | I82: - | J82: - | K82: Pik | L82: 500 | M82: 35 | N82: 4 | P82: Usata | Q82: Sì | S82: =IF(P82='Menu tendina'!A$5,0,IF(P82='Menu tendina'!A$4,'1. Precursorie'!N82/2,IF(P82='Menu tendina'!A$3,'1. Precursorie'!N82,IF(P82='Menu tendina'!A$2,'1. Precursorie'!M82,0)))) -> 4
A83: 1. Precursorie | B83: 1. Sida | C83: P42 | D83: 1049 | E83: P42 | F83: 9000 | G83: 31594 | H83: 3° Gruppo SIDA | I83: - | J83: - | K83: Pik | L83: 500 | M83: 35 | N83: 4 | P83: Usata | Q83: Sì | S83: =IF(P83='Menu tendina'!A$5,0,IF(P83='Menu tendina'!A$4,'1. Precursorie'!N83/2,IF(P83='Menu tendina'!A$3,'1. Precursorie'!N83,IF(P83='Menu tendina'!A$2,'1. Precursorie'!M83,0)))) -> 4
A84: 1. Precursorie | B84: 1. Sida | C84: P43 | D84: 1050 | E84: P43 | F84: 3000 | G84: 31686 | H84: 3° Gruppo SIDA | I84: - | J84: - | K84: Pik | L84: 700 | M84: 30 | N84: 3 | P84: Usata | Q84: Sì | S84: =IF(P84='Menu tendina'!A$5,0,IF(P84='Menu tendina'!A$4,'1. Precursorie'!N84/2,IF(P84='Menu tendina'!A$3,'1. Precursorie'!N84,IF(P84='Menu tendina'!A$2,'1. Precursorie'!M84,0)))) -> 3
A85: 1. Precursorie | B85: 1. Sida | C85: P44 | D85: 1051 | E85: P44 | F85: 3000 | G85: 31717 | H85: 3° Gruppo SIDA | I85: - | J85: - | K85: Pik | L85: 1100 | M85: 15 | N85: 3 | P85: Nuova | Q85: Sì | S85: =IF(P85='Menu tendina'!A$5,0,IF(P85='Menu tendina'!A$4,'1. Precursorie'!N85/2,IF(P85='Menu tendina'!A$3,'1. Precursorie'!N85,IF(P85='Menu tendina'!A$2,'1. Precursorie'!M85,0)))) -> 15
A86: 1. Precursorie | B86: 1. Sida | C86: P45 | D86: 1052 | E86: P45 | F86: 6000 | G86: 31717 | H86: 3° Gruppo SIDA | I86: - | J86: - | K86: Pik | L86: 400 | M86: 50 | N86: 4 | P86: Nuova | Q86: Sì | S86: =IF(P86='Menu tendina'!A$5,0,IF(P86='Menu tendina'!A$4,'1. Precursorie'!N86/2,IF(P86='Menu tendina'!A$3,'1. Precursorie'!N86,IF(P86='Menu tendina'!A$2,'1. Precursorie'!M86,0)))) -> 50
... A100: 1. Precursorie | B100: 1. Sida | C100: P59 | D100: 1069 | E100: P59 | F100: 6000 | G100: 32203 | H100: 3° Gruppo SIDA | I100: - | J100: - | K100: Pik | L100: 200 | M100: 15 | N100: 5 | P100: Nuova | Q100: Sì | S100: =IF(P100='Menu tendina'!A$5,0,IF(P100='Menu tendina'!A$4,'1. Precursorie'!N100/2,IF(P100='Menu tendina'!A$3,'1. Precursorie'!N100,IF(P100='Menu tendina'!A$2,'1. Precursorie'!M100,0)))) -> 15
A101: 1. Precursorie | B101: 2. Urmet | C101: P60 | D101: 1075 | E101: P60 | F101: 3000 | G101: 31.12.1986 | H101: Urmet Bianca | I101: - | J101: - | K101: Man | L101: - | M101: 200 | N101: 150 | P101: Usata | Q101: Sì | S101: =IF(P101='Menu tendina'!A$5,0,IF(P101='Menu tendina'!A$4,'1. Precursorie'!N101/2,IF(P101='Menu tendina'!A$3,'1. Precursorie'!N101,IF(P101='Menu tendina'!A$2,'1. Precursorie'!M101,0)))) -> 150
A102: 1. Precursorie | B102: 2. Urmet | C102: P61 | D102: 1076 | E102: P61 | F102: 5000 | G102: 31.12.1986 | H102: Urmet Bianca | I102: (N.M.) | J102: - | K102: Man | L102: - | M102: 800 | N102: 400 | P102: Nuova | Q102: Sì | S102: =IF(P102='Menu tendina'!A$5,0,IF(P102='Menu tendina'!A$4,'1. Precursorie'!N102/2,IF(P102='Menu tendina'!A$3,'1. Precursorie'!N102,IF(P102='Menu tendina'!A$2,'1. Precursorie'!M102,0)))) -> 800
A103: 1. Precursorie | B103: 2. Urmet | C103: P62 | D103: 1077 | E103: P62 | F103: 6000 | G103: 31.12.1986 | H103: Urmet Bianca | I103: - | J103: - | K103: Man | L103: - | M103: 200 | N103: 150 | P103: Nuova | Q103: Codici regolari | S103: =IF(P103='Menu tendina'!A$5,0,IF(P103='Menu tendina'!A$4,'1. Precursorie'!N103/2,IF(P103='Menu tendina'!A$3,'1. Precursorie'!N103,IF(P103='Menu tendina'!A$2,'1. Precursorie'!M103,0)))) -> 200
A104: 1. Precursorie | B104: 2. Urmet | C104: P63 | D104: 1078 | E104: P63 | F104: 10000 | G104: 31.12.1986 | H104: Urmet Bianca | I104: - | J104: - | K104: Man | L104: - | M104: 12 | N104: 6 | P104: Nuova | Q104: Sì | S104: =IF(P104='Menu tendina'!A$5,0,IF(P104='Menu tendina'!A$4,'1. Precursorie'!N104/2,IF(P104='Menu tendina'!A$3,'1. Precursorie'!N104,IF(P104='Menu tendina'!A$2,'1. Precursorie'!M104,0)))) -> 12
A105: 1. Precursorie | B105: 2. Urmet | C105: P64 | D105: 1079 | E105: P64 | F105: 20000 | G105: 31.12.1986 | H105: Urmet Bianca | I105: - | J105: - | K105: Man | L105: - | M105: 15 | N105: 8 | P105: Nuova | Q105: Sì | S105: =IF(P105='Menu tendina'!A$5,0,IF(P105='Menu tendina'!A$4,'1. Precursorie'!N105/2,IF(P105='Menu tendina'!A$3,'1. Precursorie'!N105,IF(P105='Menu tendina'!A$2,'1. Precursorie'!M105,0)))) -> 15
A106: 1. Precursorie | B106: 2. Urmet | C106: P65 | D106: 1085 | E106: P65 | F106: 5000 | G106: 31.12.1986 | H106: Urmet Rossa | I106: 7 Numeri (0 Normale) | J106: - | K106: Man | L106: 15 | M106: 400 | N106: 150 | P106: Usata | Q106: Sì | S106: =IF(P106='Menu tendina'!A$5,0,IF(P106='Menu tendina'!A$4,'1. Precursorie'!N106/2,IF(P106='Menu tendina'!A$3,'1. Precursorie'!N106,IF(P106='Menu tendina'!A$2,'1. Precursorie'!M106,0)))) -> 150
A107: 1. Precursorie | B107: 2. Urmet | C107: P65A | D107: 1085a | E107: P65A | F107: 5000 | G107: 31.12.1986 | H107: Urmet Rossa | I107: 7 Numeri (0 Barrato) | J107: Variante | K107: Man | L107: 25 | M107: 280 | N107: 120 | P107: Usata | Q107: Sì | S107: =IF(P107='Menu tendina'!A$5,0,IF(P107='Menu tendina'!A$4,'1. Precursorie'!N107/2,IF(P107='Menu tendina'!A$3,'1. Precursorie'!N107,IF(P107='Menu tendina'!A$2,'1. Precursorie'!M107,0)))) -> 120
A108: 1. Precursorie | B108: 2. Urmet | C108: P66 | D108: 1086 | E108: P66 | F108: 10000 | G108: 31.12.1986 | H108: Urmet Rossa | I108: 7 Numeri (0 Normale) | J108: - | K108: Man | L108: 15 | M108: 350 | N108: 100 | P108: Usata | Q108: Sì | S108: =IF(P108='Menu tendina'!A$5,0,IF(P108='Menu tendina'!A$4,'1. Precursorie'!N108/2,IF(P108='Menu tendina'!A$3,'1. Precursorie'!N108,IF(P108='Menu tendina'!A$2,'1. Precursorie'!M108,0)))) -> 100
A109: 1. Precursorie | B109: 2. Urmet | C109: P66A | D109: 1086a | E109: P66A | F109: 10000 | G109: 31.12.1986 | H109: Urmet Rossa | I109: 7 Numeri (0 Barrato) | J109: Variante | K109: Man | L109: 25 | M109: 250 | N109: 60 | P109: Usata | Q109: Sì | S109: =IF(P109='Menu tendina'!A$5,0,IF(P109='Menu tendina'!A$4,'1. Precursorie'!N109/2,IF(P109='Menu tendina'!A$3,'1. Precursorie'!N109,IF(P109='Menu tendina'!A$2,'1. Precursorie'!M109,0)))) -> 60
A110: 1. Precursorie | B110: 2. Urmet | C110: P67 | D110: 1087 | E110: P67 | F110: 5000 | G110: 31.12.1987 | H110: Urmet Rossa | I110: 6 Numeri | J110: - | K110: Man | L110: 100 | M110: 80 | N110: 15 | P110: Nuova | Q110: Sì | S110: =IF(P110='Menu tendina'!A$5,0,IF(P110='Menu tendina'!A$4,'1. Precursorie'!N110/2,IF(P110='Menu tendina'!A$3,'1. Precursorie'!N110,IF(P110='Menu tendina'!A$2,'1. Precursorie'!M110,0)))) -> 80
A111: 1. Precursorie | B111: 2. Urmet | C111: P67A | D111: 1089 | E111: P67A | F111: 5000 | G111: 31.12.1987 | H111: Urmet Rossa | I111: 8 Caratteri "Alfanumerica" | J111: Variante | K111: Man | L111: 100 | M111: 90 | N111: 15 | P111: Nuova | Q111: Codici regolari | S111: =IF(P111='Menu tendina'!A$5,0,IF(P111='Menu tendina'!A$4,'1. Precursorie'!N111/2,IF(P111='Menu tendina'!A$3,'1. Precursorie'!N111,IF(P111='Menu tendina'!A$2,'1. Precursorie'!M111,0)))) -> 90
A112: 1. Precursorie | B112: 2. Urmet | C112: P67B | D112: 1092 | E112: P67C | F112: 5000 | G112: 31.12.1987 | H112: Urmet Rossa | I112: 8 Caratteri "Alfanumerica" + Asterisco | J112: Variante | K112: Man | L112: 100 | M112: 80 | N112: 15 | P112: Nuova | Q112: Sì | S112: =IF(P112='Menu tendina'!A$5,0,IF(P112='Menu tendina'!A$4,'1. Precursorie'!N112/2,IF(P112='Menu tendina'!A$3,'1. Precursorie'!N112,IF(P112='Menu tendina'!A$2,'1. Precursorie'!M112,0)))) -> 80
A113: 1. Precursorie | B113: 2. Urmet | C113: P67C | D113: 1089a | E113: P67B | F113: 5000 | G113: 31.12.1987 | H113: Urmet Rossa | I113: 8 Caratteri (solo Lettere) | J113: Variante | K113: Man | L113: - | M113: 120 | N113: 55 | P113: Usata | Q113: Sì | S113: =IF(P113='Menu tendina'!A$5,0,IF(P113='Menu tendina'!A$4,'1. Precursorie'!N113/2,IF(P113='Menu tendina'!A$3,'1. Precursorie'!N113,IF(P113='Menu tendina'!A$2,'1. Precursorie'!M113,0)))) -> 55
...

Sheet 2. Private
A1: Genere | B1: Sottogenere | C1: N.Golden | D1: N. C&C | E1: N. AG | F1: Taglio | G1: Scadenza | H1: Titolo | I1: Pr. | J1: Note | K1: Var | L1: Tiratura | M1: Val 2025 Nuova | N1: Val 2025 Usata | P1: Presente | Q1: Magnetizzazione | R1: Codice | T1: Valore collezione
A2: 2. Private | B2: 1. Precursorie Omaggio | C2: PO1 | D2: 3001 | E2: 1 | F2: - | G2: - | H2: SIDA - "Sovrastampa: Omaggio" | I2: Pik | J2: Bandella sagomata | K2: - | L2: - | M2: 120 | N2: 60 | P2: Nuova | Q2: Sì | T2: =IF(P2='Menu tendina'!A$5,0,IF(P2='Menu tendina'!A$4,'2. Private'!N2/2,IF(P2='Menu tendina'!A$3,'2. Private'!N2,IF(P2='Menu tendina'!A$2,'2. Private'!M2,0)))) -> 120
A3: 2. Private | B3: 1. Precursorie Omaggio | C3: PO2 | D3: 3002 | E3: 2 | F3: 5 scatti | G3: - | H3: Fasce Orarie - Servizi 1 | I3: Pik | J3: Braille, filigrana, PatPen, banda grigia chiara piena, numerazione | K3: - | L3: - | M3: 450 | N3: 200 | P3: Nuova | Q3: Codici regolari | R3: 00/17/001/00012 - 04/6 | T3: =IF(P3='Menu tendina'!A$5,0,IF(P3='Menu tendina'!A$4,'2. Private'!N3/2,IF(P3='Menu tendina'!A$3,'2. Private'!N3,IF(P3='Menu tendina'!A$2,'2. Private'!M3,0)))) -> 450
A4: 2. Private | B4: 1. Precursorie Omaggio | C4: PO3 | D4: 3003 | E4: 3 | F4: 10 scatti | G4: - | H4: Fasce Orarie | I4: Pik | J4: Braille, filigrana, banda grigia retinata. No numerazione | K4: - | L4: - | M4: 180 | N4: 60 | P4: Usata | Q4: Sì | T4: =IF(P4='Menu tendina'!A$5,0,IF(P4='Menu tendina'!A$4,'2. Private'!N4/2,IF(P4='Menu tendina'!A$3,'2. Private'!N4,IF(P4='Menu tendina'!A$2,'2. Private'!M4,0)))) -> 60
A5: 2. Private | B5: 1. Precursorie Omaggio | C5: PO4 | D5: 3004 | E5: 4 | F5: 10 scatti | G5: - | H5: Fasce Orarie - (N.M.) | I5: Pik | J5: Banda grigia chiara piena. No Braille, filigrana, numerazione. | K5: - | L5: - | M5: 20 | N5: 8 | P5: Nuova | Q5: n/a | R5: n/a | T5: =IF(P5='Menu tendina'!A$5,0,IF(P5='Menu tendina'!A$4,'2. Private'!N5/2,IF(P5='Menu tendina'!A$3,'2. Private'!N5,IF(P5='Menu tendina'!A$2,'2. Private'!M5,0)))) -> 20
A6: 2. Private | B6: 1. Precursorie Omaggio | C6: PO5 | D6: 3005 | E6: 5 | F6: 10 scatti | G6: - | H6: Fasce Orarie | I6: Pik | J6: Filigrana, banda grigia scura. No braille, numerazione. | K6: - | L6: - | M6: 8 | N6: 3 | P6: Nuova | Q6: Codici Urmet | T6: =IF(P6='Menu tendina'!A$5,0,IF(P6='Menu tendina'!A$4,'2. Private'!N6/2,IF(P6='Menu tendina'!A$3,'2. Private'!N6,IF(P6='Menu tendina'!A$2,'2. Private'!M6,0)))) -> 8
A7: 2. Private | B7: 1. Precursorie Omaggio | C7: PO6 | D7: 3006 | E7: 1 | F7: 10 scatti | G7: - | H7: Abruzzi - Pescara | I7: Pik | J7: Con Banda grigia e OCR | K7: - | L7: - | M7: 120 | N7: 70 | P7: Nuova | Q7: No | T7: =IF(P7='Menu tendina'!A$5,0,IF(P7='Menu tendina'!A$4,'2. Private'!N7/2,IF(P7='Menu tendina'!A$3,'2. Private'!N7,IF(P7='Menu tendina'!A$2,'2. Private'!M7,0)))) -> 120
A8: 2. Private | B8: 1. Precursorie Omaggio | C8: PO7 | D8: 3009 | E8: 2 | F8: 10 scatti | G8: - | H8: Abruzzo - Pescara | I8: Pik | J8: Con Banda grigia e OCR | K8: - | L8: - | M8: 100 | N8: 60 | P8: Manca | T8: =IF(P8='Menu tendina'!A$5,0,IF(P8='Menu tendina'!A$4,'2. Private'!N8/2,IF(P8='Menu tendina'!A$3,'2. Private'!N8,IF(P8='Menu tendina'!A$2,'2. Private'!M8,0)))) -> 0
A9: 2. Private | B9: 1. Precursorie Omaggio | C9: PO8 | D9: 3011 | E9: 3 | F9: 10 scatti | G9: - | H9: Abruzzo - Penne | I9: Pik | J9: Con Banda grigia e OCR | K9: - | L9: - | M9: 70 | N9: 45 | P9: Nuova | Q9: Codici regolari | R9: 01/05/064/13947 - 04/10 | T9: =IF(P9='Menu tendina'!A$5,0,IF(P9='Menu tendina'!A$4,'2. Private'!N9/2,IF(P9='Menu tendina'!A$3,'2. Private'!N9,IF(P9='Menu tendina'!A$2,'2. Private'!M9,0)))) -> 70
A10: 2. Private | B10: 1. Precursorie Omaggio | C10: PO9 | D10: 3023 | E10: 4 | F10: 10 scatti | G10: - | H10: Emilia Romagna - Bologna | I10: Pik | J10: Con Banda grigia e OCR | K10: - | L10: - | M10: 130 | N10: 55 | P10: Usata | Q10: Sì | T10: =IF(P10='Menu tendina'!A$5,0,IF(P10='Menu tendina'!A$4,'2. Private'!N10/2,IF(P10='Menu tendina'!A$3,'2. Private'!N10,IF(P10='Menu tendina'!A$2,'2. Private'!M10,0)))) -> 55
A11: 2. Private | B11: 1. Precursorie Omaggio | C11: PO10 | D11: 3026 | E11: 5 | F11: 10 scatti | G11: - | H11: Emilia Romagna - Ferrara | I11: Pik | J11: Con Banda grigia e OCR | K11: - | L11: - | M11: 300 | N11: 100 | P11: Manca | T11: =IF(P11='Menu tendina'!A$5,0,IF(P11='Menu tendina'!A$4,'2. Private'!N11/2,IF(P11='Menu tendina'!A$3,'2. Private'!N11,IF(P11='Menu tendina'!A$2,'2. Private'!M11,0)))) -> 0
A12: 2. Private | B12: 1. Precursorie Omaggio | C12: PO11 | D12: 3029 | E12: 7 | F12: 10 scatti | G12: - | H12: Friuli - Palmanova - Immagine Grande | I12: Pik | J12: Con Banda grigia e OCR - Foto piccola | K12: - | L12: - | M12: 25 | N12: 18 | P12: Nuova | Q12: Codici regolari | R12: 01/05/064/09992 - 04/10 | T12: =IF(P12='Menu tendina'!A$5,0,IF(P12='Menu tendina'!A$4,'2. Private'!N12/2,IF(P12='Menu tendina'!A$3,'2. Private'!N12,IF(P12='Menu tendina'!A$2,'2. Private'!M12,0)))) -> 25
A13: 2. Private | B13: 1. Precursorie Omaggio | C13: PO12 | D13: 3028 | E13: 6 | F13: 10 scatti | G13: - | H13: Friuli - Palmanova - Immagine Piccola | I13: Pik | J13: Con Banda grigia e OCR - Foto grande | K13: - | L13: - | M13: 250 | N13: 180 | P13: Usata | T13: =IF(P13='Menu tendina'!A$5,0,IF(P13='Menu tendina'!A$4,'2. Private'!N13/2,IF(P13='Menu tendina'!A$3,'2. Private'!N13,IF(P13='Menu tendina'!A$2,'2. Private'!M13,0)))) -> 180
A14: 2. Private | B14: 1. Precursorie Omaggio | C14: PO13 | D14: 3032 | E14: 8 | F14: 10 scatti | G14: - | H14: Friuli - Trieste | I14: Pik | J14: Con Banda grigia e OCR | K14: - | L14: - | M14: 60 | N14: 40 | P14: Usata | T14: =IF(P14='Menu tendina'!A$5,0,IF(P14='Menu tendina'!A$4,'2. Private'!N14/2,IF(P14='Menu tendina'!A$3,'2. Private'!N14,IF(P14='Menu tendina'!A$2,'2. Private'!M14,0)))) -> 40
A15: 2. Private | B15: 1. Precursorie Omaggio | C15: PO14 | D15: 3046 | E15: Rit1 | F15: 10 scatti | G15: - | H15: Molise - Altilia - Ritirata (N.E.) | I15: Pik | J15: Con Banda grigia e OCR | K15: - | L15: - | M15: 650 | N15: 400 | P15: Manca | Q15: n/a | R15: n/a | T15: =IF(P15='Menu tendina'!A$5,0,IF(P15='Menu tendina'!A$4,'2. Private'!N15/2,IF(P15='Menu tendina'!A$3,'2. Private'!N15,IF(P15='Menu tendina'!A$2,'2. Private'!M15,0)))) -> 0
A16: 2. Private | B16: 1. Precursorie Omaggio | C16: PO15 | D16: 3049 | E16: 9 | F16: 10 scatti | G16: - | H16: Molise - Campobasso | I16: Pik | J16: Con Banda grigia e OCR | K16: - | L16: - | M16: 350 | N16: 170 | P16: Manca | T16: =IF(P16='Menu tendina'!A$5,0,IF(P16='Menu tendina'!A$4,'2. Private'!N16/2,IF(P16='Menu tendina'!A$3,'2. Private'!N16,IF(P16='Menu tendina'!A$2,'2. Private'!M16,0)))) -> 0
A17: 2. Private | B17: 1. Precursorie Omaggio | C17: PO16 | D17: 3051 | E17: 10 | F17: 10 scatti | G17: - | H17: Piemonte - Grinzane Cavour | I17: Pik | J17: Con Banda grigia e OCR | K17: - | L17: - | M17: 45 | N17: 25 | P17: Nuova | Q17: Codici regolari | R17: 01/05/064/13056 - 04/10 | T17: =IF(P17='Menu tendina'!A$5,0,IF(P17='Menu tendina'!A$4,'2. Private'!N17/2,IF(P17='Menu tendina'!A$3,'2. Private'!N17,IF(P17='Menu tendina'!A$2,'2. Private'!M17,0)))) -> 45
A18: 2. Private | B18: 1. Precursorie Omaggio | C18: PO17 | D18: 3054 | E18: 11 | F18: 10 scatti | G18: - | H18: Piemonte - Torino | I18: Pik | J18: Con Banda grigia e OCR | K18: - | L18: - | M18: 80 | N18: 45 | P18: Nuova | Q18: Codici regolari | R18: 01/05/064/09399 - 04/10 | T18: =IF(P18='Menu tendina'!A$5,0,IF(P18='Menu tendina'!A$4,'2. Private'!N18/2,IF(P18='Menu tendina'!A$3,'2. Private'!N18,IF(P18='Menu tendina'!A$2,'2. Private'!M18,0)))) -> 80
A19: 2. Private | B19: 1. Precursorie Omaggio | C19: PO18 | D19: 3062 | E19: 12 | F19: 10 scatti | G19: - | H19: Sicilia - Monreale | I19: Pik | J19: Con Banda grigia e OCR | K19: - | L19: - | M19: 25 | N19: 18 | P19: Nuova | Q19: Codici regolari | R19: 01/05/064/09425 - 04/10 | T19: =IF(P19='Menu tendina'!A$5,0,IF(P19='Menu tendina'!A$4,'2. Private'!N19/2,IF(P19='Menu tendina'!A$3,'2. Private'!N19,IF(P19='Menu tendina'!A$2,'2. Private'!M19,0)))) -> 25
A20: 2. Private | B20: 1. Precursorie Omaggio | C20: PO19 | D20: 3064 | E20: 13 | F20: 10 scatti | G20: - | H20: Sicilia - Trapani | I20: Pik | J20: Con Banda grigia e OCR | K20: - | L20: - | M20: 30 | N20: 22 | P20: Usata | T20: =IF(P20='Menu tendina'!A$5,0,IF(P20='Menu tendina'!A$4,'2. Private'!N20/2,IF(P20='Menu tendina'!A$3,'2. Private'!N20,IF(P20='Menu tendina'!A$2,'2. Private'!M20,0)))) -> 22
A21: 2. Private | B21: 1. Precursorie Omaggio | C21: PO20 | D21: 3067 | E21: 14 | F21: 10 scatti | G21: - | H21: Toscana - Magliano | I21: Pik | J21: Con Banda grigia e OCR | K21: - | L21: - | M21: 160 | N21: 100 | P21: Usata | T21: =IF(P21='Menu tendina'!A$5,0,IF(P21='Menu tendina'!A$4,'2. Private'!N21/2,IF(P21='Menu tendina'!A$3,'2. Private'!N21,IF(P21='Menu tendina'!A$2,'2. Private'!M21,0)))) -> 100
A22: 2. Private | B22: 1. Precursorie Omaggio | C22: PO21 | D22: 3070 | E22: 15 | F22: 10 scatti | G22: - | H22: Toscana - San Godenzo | I22: Pik | J22: Con Banda grigia e OCR | K22: - | L22: - | M22: 180 | N22: 120 | P22: Manca | T22: =IF(P22='Menu tendina'!A$5,0,IF(P22='Menu tendina'!A$4,'2. Private'!N22/2,IF(P22='Menu tendina'!A$3,'2. Private'!N22,IF(P22='Menu tendina'!A$2,'2. Private'!M22,0)))) -> 0
A23: 2. Private | B23: 1. Precursorie Omaggio | C23: PONE01 | D23: #N/A | E23: #N/A | F23: 10 scatti | G23: - | H23: Umbria - Assisi (N.M.) | I23: Pik | J23: Con Banda grigia e OCR | K23: - | M23: P.A.R. | N23: P.A.R. | P23: Manca | Q23: n/a | R23: n/a | T23: =IF(P23='Menu tendina'!A$5,0,IF(P23='Menu tendina'!A$4,'2. Private'!N23/2,IF(P23='Menu tendina'!A$3,'2. Private'!N23,IF(P23='Menu tendina'!A$2,'2. Private'!M23,0)))) -> 0
A24: 2. Private | B24: 1. Precursorie Omaggio | C24: PO22 | D24: 3077 | E24: 16 | F24: 10 scatti | G24: - | H24: Umbria - Perugia | I24: Pik | J24: Con Banda grigia e OCR - Foto piccola | K24: - | L24: - | M24: 25 | N24: 18 | P24: Nuova | Q24: Codici regolari | R24: 01/05/064/09729 - 04/10 | T24: =IF(P24='Menu tendina'!A$5,0,IF(P24='Menu tendina'!A$4,'2. Private'!N24/2,IF(P24='Menu tendina'!A$3,'2. Private'!N24,IF(P24='Menu tendina'!A$2,'2. Private'!M24,0)))) -> 25
A25: 2. Private | B25: 1. Precursorie Omaggio | C25: PO23 | D25: 3078 | E25: 17 | F25: 10 scatti | G25: - | H25: Umbria - Perugia | I25: Pik | J25: Con Banda grigia e OCR - Foto grande | K25: - | L25: - | M25: 250 | N25: 130 | P25: Manca | T25: =IF(P25='Menu tendina'!A$5,0,IF(P25='Menu tendina'!A$4,'2. Private'!N25/2,IF(P25='Menu tendina'!A$3,'2. Private'!N25,IF(P25='Menu tendina'!A$2,'2. Private'!M25,0)))) -> 0
A26: 2. Private | B26: 1. Precursorie Omaggio | C26: PO24 | D26: 3081 | E26: 18 | F26: 10 scatti | G26: - | H26: Valle Aosta - Ayas | I26: Pik | J26: Con Banda grigia e OCR | K26: - | L26: - | M26: 90 | N26: 55 | P26: Nuova | Q26: Codici regolari | R26: 01/05/064/09947 - 04/10 | T26: =IF(P26='Menu tendina'!A$5,0,IF(P26='Menu tendina'!A$4,'2. Private'!N26/2,IF(P26='Menu tendina'!A$3,'2. Private'!N26,IF(P26='Menu tendina'!A$2,'2. Private'!M26,0)))) -> 90
A27: 2. Private | B27: 1. Precursorie Omaggio | C27: PO25 | D27: 3083 | E27: 19 | F27: 10 scatti | G27: - | H27: Valle Aosta - Sarriod | I27: Pik | J27: Con Banda grigia e OCR | K27: - | L27: - | M27: 100 | N27: 55 | P27: Manca | T27: =IF(P27='Menu tendina'!A$5,0,IF(P27='Menu tendina'!A$4,'2. Private'!N27/2,IF(P27='Menu tendina'!A$3,'2. Private'!N27,IF(P27='Menu tendina'!A$2,'2. Private'!M27,0)))) -> 0
A28: 2. Private | B28: 1. Precursorie Omaggio | C28: PO26 | D28: 3086 | E28: 20 | F28: 10 scatti | G28: - | H28: Veneto - Gazzo Veronese | I28: Pik | J28: Con Banda grigia e OCR - Foto piccola | K28: - | L28: - | M28: 90 | N28: 55 | P28: Usata | Q28: Sì | T28: =IF(P28='Menu tendina'!A$5,0,IF(P28='Menu tendina'!A$4,'2. Private'!N28/2,IF(P28='Menu tendina'!A$3,'2. Private'!N28,IF(P28='Menu tendina'!A$2,'2. Private'!M28,0)))) -> 55
A29: 2. Private | B29: 1. Precursorie Omaggio | C29: PO27 | D29: 3087 | E29: 21 | F29: 10 scatti | G29: - | H29: Veneto - Gazzo Veronese | I29: Pik | J29: Con Banda grigia e OCR - Foto grande | K29: - | L29: - | M29: 80 | N29: 55 | P29: Nuova | Q29: Codici regolari | R29: 01/05/064/09313 - 04/10 | T29: =IF(P29='Menu tendina'!A$5,0,IF(P29='Menu tendina'!A$4,'2. Private'!N29/2,IF(P29='Menu tendina'!A$3,'2. Private'!N29,IF(P29='Menu tendina'!A$2,'2. Private'!M29,0)))) -> 80
A30: 2. Private | B30: 1. Precursorie Omaggio | C30: PONE02 | D30: #N/A | E30: #N/A | F30: 10 scatti | G30: - | H30: Veneto - Piazzola sul Brenta (N.M.) | I30: Pik | J30: Con Banda grigia e OCR | K30: - | M30: P.A.R. | N30: P.A.R. | P30: Manca | Q30: n/a | R30: n/a | T30: =IF(P30='Menu tendina'!A$5,0,IF(P30='Menu tendina'!A$4,'2. Private'!N30/2,IF(P30='Menu tendina'!A$3,'2. Private'!N30,IF(P30='Menu tendina'!A$2,'2. Private'!M30,0)))) -> 0
A31: 2. Private | B31: 1. Precursorie Omaggio | C31: PO28 | D31: 3007 | E31: 22 | F31: 10 scatti | G31: - | H31: Abruzzi - Pescara | I31: Tep | J31: Senza OCR | K31: - | L31: - | M31: 100 | N31: 60 | P31: Nuova | Q31: Codici regolari | R31: 01/04/022/03185 - 04/10 | T31: =IF(P31='Menu tendina'!A$5,0,IF(P31='Menu tendina'!A$4,'2. Private'!N31/2,IF(P31='Menu tendina'!A$3,'2. Private'!N31,IF(P31='Menu tendina'!A$2,'2. Private'!M31,0)))) -> 100
A32: 2. Private | B32: 1. Precursorie Omaggio | C32: PO29 | D32: 3008 | E32: 23 | F32: 10 scatti | G32: - | H32: Abruzzi - Penne | I32: Tep | J32: Senza OCR | K32: - | L32: - | M32: 80 | N32: 50 | P32: Nuova | Q32: Codici regolari | R32: 01/04/022/03188 - 04/10 | T32: =IF(P32='Menu tendina'!A$5,0,IF(P32='Menu tendina'!A$4,'2. Private'!N32/2,IF(P32='Menu tendina'!A$3,'2. Private'!N32,IF(P32='Menu tendina'!A$2,'2. Private'!M32,0)))) -> 80
A33: 2. Private | B33: 1. Precursorie Omaggio | C33: PO30 | D33: 3010 | E33: 24 | F33: 10 scatti | G33: - | H33: Abruzzo - Pescara | I33: Tep | J33: Senza OCR | K33: - | L33: - | M33: 400 | N33: 240 | P33: Manca | T33: =IF(P33='Menu tendina'!A$5,0,IF(P33='Menu tendina'!A$4,'2. Private'!N33/2,IF(P33='Menu tendina'!A$3,'2. Private'!N33,IF(P33='Menu tendina'!A$2,'2. Private'!M33,0)))) -> 0
A34: 2. Private | B34: 1. Precursorie Omaggio | C34: PO31 | D34: 3012 | E34: 25 | F34: 10 scatti | G34: - | H34: Abruzzo - Penne | I34: Tep | J34: Senza OCR | K34: - | L34: - | M34: 300 | N34: 180 | P34: Manca | T34: =IF(P34='Menu tendina'!A$5,0,IF(P34='Menu tendina'!A$4,'2. Private'!N34/2,IF(P34='Menu tendina'!A$3,'2. Private'!N34,IF(P34='Menu tendina'!A$2,'2. Private'!M34,0)))) -> 0
A35: 2. Private | B35: 1. Precursorie Omaggio | C35: PO32 | D35: 3014 | E35: 26 | F35: 10 scatti | G35: - | H35: Basilicata - Grumento | I35: Tep | J35: Senza OCR | K35: - | L35: - | M35: 55 | N35: 35 | P35: Nuova | Q35: Codici regolari | R35: 01/04/024/24589 - 04/10 | T35: =IF(P35='Menu tendina'!A$5,0,IF(P35='Menu tendina'!A$4,'2. Private'!N35/2,IF(P35='Menu tendina'!A$3,'2. Private'!N35,IF(P35='Menu tendina'!A$2,'2. Private'!M35,0)))) -> 55
A36: 2. Private | B36: 1. Precursorie Omaggio | C36: PO33 | D36: 3015 | E36: 27 | F36: 10 scatti | G36: - | H36: Basilicata - Matera | I36: Tep | J36: Senza OCR | K36: - | L36: - | M36: 55 | N36: 35 | P36: Nuova | Q36: Codici regolari | R36: 01/04/021/23176 - 04/10 | T36: =IF(P36='Menu tendina'!A$5,0,IF(P36='Menu tendina'!A$4,'2. Private'!N36/2,IF(P36='Menu tendina'!A$3,'2. Private'!N36,IF(P36='Menu tendina'!A$2,'2. Private'!M36,0)))) -> 55
A37: 2. Private | B37: 1. Precursorie Omaggio | C37: PO34 | D37: 3017 | E37: 28 | F37: 10 scatti | G37: - | H37: Calabria - Reggio Calabria | I37: Tep | J37: Senza OCR | K37: - | L37: - | M37: 45 | N37: 25 | P37: Nuova | Q37: No | T37: =IF(P37='Menu tendina'!A$5,0,IF(P37='Menu tendina'!A$4,'2. Private'!N37/2,IF(P37='Menu tendina'!A$3,'2. Private'!N37,IF(P37='Menu tendina'!A$2,'2. Private'!M37,0)))) -> 45
A38: 2. Private | B38: 1. Precursorie Omaggio | C38: PO35 | D38: 3019 | E38: 29 | F38: 10 scatti | G38: - | H38: Calabria - Serra San Bruno | I38: Tep | J38: Senza OCR | K38: - | L38: - | M38: 55 | N38: 30 | P38: Nuova | Q38: Codici regolari | R38: 01/04/024/19944 - 04/10 | T38: =IF(P38='Menu tendina'!A$5,0,IF(P38='Menu tendina'!A$4,'2. Private'!N38/2,IF(P38='Menu tendina'!A$3,'2. Private'!N38,IF(P38='Menu tendina'!A$2,'2. Private'!M38,0)))) -> 55
A39: 2. Private | B39: 1. Precursorie Omaggio | C39: PO36 | D39: 3020 | E39: 30 | F39: 10 scatti | G39: - | H39: Campania - Ercolano | I39: Tep | J39: Senza OCR | K39: - | L39: - | M39: 65 | N39: 35 | P39: Nuova | Q39: Codici regolari | R39: 01/04/022/16265 - 04/10 | T39: =IF(P39='Menu tendina'!A$5,0,IF(P39='Menu tendina'!A$4,'2. Private'!N39/2,IF(P39='Menu tendina'!A$3,'2. Private'!N39,IF(P39='Menu tendina'!A$2,'2. Private'!M39,0)))) -> 65
A40: 2. Private | B40: 1. Precursorie Omaggio | C40: PO37 | D40: 3021 | E40: 31 | F40: 10 scatti | G40: - | H40: Campania - Sessa Aurunca | I40: Tep | J40: Senza OCR | K40: - | L40: - | M40: 90 | N40: 55 | P40: Nuova | Q40: Codici regolari | R40: 01/04/022/21223 - 04/10 | T40: =IF(P40='Menu tendina'!A$5,0,IF(P40='Menu tendina'!A$4,'2. Private'!N40/2,IF(P40='Menu tendina'!A$3,'2. Private'!N40,IF(P40='Menu tendina'!A$2,'2. Private'!M40,0)))) -> 90
A41: 2. Private | B41: 1. Precursorie Omaggio | C41: PO38 | D41: 3024 | E41: 32 | F41: 10 scatti | G41: - | H41: Emilia Romagna - Bologna | I41: Tep | J41: Senza OCR | K41: - | L41: - | M41: 60 | N41: 40 | P41: Nuova | Q41: Codici regolari | R41: 01/04/022/13413 - 04/10 | T41: =IF(P41='Menu tendina'!A$5,0,IF(P41='Menu tendina'!A$4,'2. Private'!N41/2,IF(P41='Menu tendina'!A$3,'2. Private'!N41,IF(P41='Menu tendina'!A$2,'2. Private'!M41,0)))) -> 60
A42: 2. Private | B42: 1. Precursorie Omaggio | C42: PO39 | D42: 3027 | E42: 33 | F42: 10 scatti | G42: - | H42: Emilia Romagna - Ferrara | I42: Tep | J42: Senza OCR | K42: - | L42: - | M42: 55 | N42: 35 | P42: Nuova | Q42: Codici regolari | R42: 01/04/022/06686 - 04/10 | T42: =IF(P42='Menu tendina'!A$5,0,IF(P42='Menu tendina'!A$4,'2. Private'!N42/2,IF(P42='Menu tendina'!A$3,'2. Private'!N42,IF(P42='Menu tendina'!A$2,'2. Private'!M42,0)))) -> 55
A43: 2. Private | B43: 1. Precursorie Omaggio | C43: PO40 | D43: 3030 | E43: 34 | F43: 10 scatti | G43: - | H43: Friuli - Palmanova | I43: Tep | J43: Senza OCR | K43: - | L43: - | M43: 55 | N43: 35 | P43: Nuova | Q43: Codici regolari | R43: 01/04/023/15282 - 04/10 | T43: =IF(P43='Menu tendina'!A$5,0,IF(P43='Menu tendina'!A$4,'2. Private'!N43/2,IF(P43='Menu tendina'!A$3,'2. Private'!N43,IF(P43='Menu tendina'!A$2,'2. Private'!M43,0)))) -> 55
A44: 2. Private | B44: 1. Precursorie Omaggio | C44: PO41 | D44: 3033 | E44: 35 | F44: 10 scatti | G44: - | H44: Friuli - Trieste | I44: Tep | J44: Senza OCR | K44: - | L44: - | M44: 80 | N44: 45 | P44: Nuova | Q44: Codici regolari | R44: 01/04/021/11056 - 04/10 | T44: =IF(P44='Menu tendina'!A$5,0,IF(P44='Menu tendina'!A$4,'2. Private'!N44/2,IF(P44='Menu tendina'!A$3,'2. Private'!N44,IF(P44='Menu tendina'!A$2,'2. Private'!M44,0)))) -> 80
A45: 2. Private | B45: 1. Precursorie Omaggio | C45: PO42 | D45: 3034 | E45: 36 | F45: 10 scatti | G45: - | H45: Lazio - Roma (Apollo di Veio) | I45: Tep | J45: Senza OCR | K45: - | L45: - | M45: 85 | N45: 55 | P45: Nuova | Q45: Codici regolari | R45: 01/04/022/17728 - 04/10 | T45: =IF(P45='Menu tendina'!A$5,0,IF(P45='Menu tendina'!A$4,'2. Private'!N45/2,IF(P45='Menu tendina'!A$3,'2. Private'!N45,IF(P45='Menu tendina'!A$2,'2. Private'!M45,0)))) -> 85
A46: 2. Private | B46: 1. Precursorie Omaggio | C46: PO43 | D46: 3035 | E46: 37 | F46: 10 scatti | G46: - | H46: Lazio - Roma (Testa femminile) | I46: Tep | J46: Senza OCR | K46: - | L46: - | M46: 90 | N46: 60 | P46: Nuova | Q46: Codici regolari | R46: 01/04/023/12440 - 04/10 | T46: =IF(P46='Menu tendina'!A$5,0,IF(P46='Menu tendina'!A$4,'2. Private'!N46/2,IF(P46='Menu tendina'!A$3,'2. Private'!N46,IF(P46='Menu tendina'!A$2,'2. Private'!M46,0)))) -> 90
A47: 2. Private | B47: 1. Precursorie Omaggio | C47: PO44 | D47: 3037 | E47: 38 | F47: 10 scatti | G47: - | H47: Liguria - Portofino | I47: Tep | J47: Senza OCR | K47: - | L47: - | M47: 90 | N47: 55 | P47: Nuova | Q47: Codici regolari | R47: 01/04/024/10733 - 04/10 | T47: =IF(P47='Menu tendina'!A$5,0,IF(P47='Menu tendina'!A$4,'2. Private'!N47/2,IF(P47='Menu tendina'!A$3,'2. Private'!N47,IF(P47='Menu tendina'!A$2,'2. Private'!M47,0)))) -> 90
A48: 2. Private | B48: 1. Precursorie Omaggio | C48: PO45 | D48: 3038 | E48: 39 | F48: 10 scatti | G48: - | H48: Liguria - Riomaggiore | I48: Tep | J48: Senza OCR | K48: - | L48: - | M48: 55 | N48: 35 | P48: Nuova | Q48: Codici regolari | R48: 01/04/024/17458 - 04/10 | T48: =IF(P48='Menu tendina'!A$5,0,IF(P48='Menu tendina'!A$4,'2. Private'!N48/2,IF(P48='Menu tendina'!A$3,'2. Private'!N48,IF(P48='Menu tendina'!A$2,'2. Private'!M48,0)))) -> 55
A49: 2. Private | B49: 1. Precursorie Omaggio | C49: PO46 | D49: 3040 | E49: 40 | F49: 10 scatti | G49: - | H49: Lombardia - Bergamo | I49: Tep | J49: Senza OCR | K49: - | L49: - | M49: 85 | N49: 55 | P49: Nuova | Q49: Codici regolari | R49: 01/04/021/21063 - 04/10 | T49: =IF(P49='Menu tendina'!A$5,0,IF(P49='Menu tendina'!A$4,'2. Private'!N49/2,IF(P49='Menu tendina'!A$3,'2. Private'!N49,IF(P49='Menu tendina'!A$2,'2. Private'!M49,0)))) -> 85
... A57: 2. Private | B57: 1. Precursorie Omaggio | C57: PO54 | D57: 3056 | E57: 48 | F57: 10 scatti | G57: - | H57: Puglia - Alberobello | I57: Tep | J57: Senza OCR | K57: - | L57: - | M57: 90 | N57: 60 | P57: Nuova | Q57: Codici regolari | R57: 01/04/021/23574 - 04/10 | T57: =IF(P57='Menu tendina'!A$5,0,IF(P57='Menu tendina'!A$4,'2. Private'!N57/2,IF(P57='Menu tendina'!A$3,'2. Private'!N57,IF(P57='Menu tendina'!A$2,'2. Private'!M57,0)))) -> 90
A58: 2. Private | B58: 1. Precursorie Omaggio | C58: PO55 | D58: 3058 | E58: 49 | F58: 10 scatti | G58: - | H58: Puglia - Castellana Grotte | I58: Tep | J58: Senza OCR | K58: - | L58: - | M58: 90 | N58: 60 | P58: 2a scelta | T58: =IF(P58='Menu tendina'!A$5,0,IF(P58='Menu tendina'!A$4,'2. Private'!N58/2,IF(P58='Menu tendina'!A$3,'2. Private'!N58,IF(P58='Menu tendina'!A$2,'2. Private'!M58,0)))) -> 30
A59: 2. Private | B59: 1. Precursorie Omaggio | C59: PO56 | D59: 3059 | E59: 50 | F59: 10 scatti | G59: - | H59: Sardegna - Arbatax | I59: Tep | J59: Senza OCR | K59: - | L59: - | M59: 90 | N59: 60 | P59: Nuova | Q59: Codici regolari | R59: 01/04/021/19429 - 04/10 | T59: =IF(P59='Menu tendina'!A$5,0,IF(P59='Menu tendina'!A$4,'2. Private'!N59/2,IF(P59='Menu tendina'!A$3,'2. Private'!N59,IF(P59='Menu tendina'!A$2,'2. Private'!M59,0)))) -> 90
A60: 2. Private | B60: 1. Precursorie Omaggio | C60: PO57 | D60: 3060 | E60: 51 | F60: 10 scatti | G60: - | H60: Sardegna - Goni | I60: Tep | J60: Senza OCR | K60: - | L60: - | M60: 60 | N60: 40 | P60: Manca | T60: =IF(P60='Menu tendina'!A$5,0,IF(P60='Menu tendina'!A$4,'2. Private'!N60/2,IF(P60='Menu tendina'!A$3,'2. Private'!N60,IF(P60='Menu tendina'!A$2,'2. Private'!M60,0)))) -> 0
A61: 2. Private | B61: 1. Precursorie Omaggio | C61: PO58 | D61: 3063 | E61: 52 | F61: 10 scatti | G61: - | H61: Sicilia - Monreale | I61: Tep | J61: Senza OCR | K61: - | L61: - | M61: 100 | N61: 50 | P61: Nuova | Q61: Codici regolari | R61: 01/04/022/06698 - 04/10 | T61: =IF(P61='Menu tendina'!A$5,0,IF(P61='Menu tendina'!A$4,'2. Private'!N61/2,IF(P61='Menu tendina'!A$3,'2. Private'!N61,IF(P61='Menu tendina'!A$2,'2. Private'!M61,0)))) -> 100
A62: 2. Private | B62: 1. Precursorie Omaggio | C62: PO59 | D62: 3065 | E62: 53 | F62: 10 scatti | G62: - | H62: Sicilia - Trapani | I62: Tep | J62: Senza OCR | K62: - | L62: - | M62: 70 | N62: 45 | P62: Nuova | Q62: Codici regolari | R62: 01/04/023/02249 - 04/10 | T62: =IF(P62='Menu tendina'!A$5,0,IF(P62='Menu tendina'!A$4,'2. Private'!N62/2,IF(P62='Menu tendina'!A$3,'2. Private'!N62,IF(P62='Menu tendina'!A$2,'2. Private'!M62,0)))) -> 70
A63: 2. Private | B63: 1. Precursorie Omaggio | C63: PO60 | D63: 3068 | E63: 54 | F63: 10 scatti | G63: - | H63: Toscana - Magliano | I63: Tep | J63: Senza OCR | K63: - | L63: - | M63: 90 | N63: 50 | P63: Nuova | Q63: No | T63: =IF(P63='Menu tendina'!A$5,0,IF(P63='Menu tendina'!A$4,'2. Private'!N63/2,IF(P63='Menu tendina'!A$3,'2. Private'!N63,IF(P63='Menu tendina'!A$2,'2. Private'!M63,0)))) -> 90
A64: 2. Private | B64: 1. Precursorie Omaggio | C64: PO61 | D64: 3071 | E64: 55 | F64: 10 scatti | G64: - | H64: Toscana - San Godenzo | I64: Tep | J64: Senza OCR | K64: - | L64: - | M64: 100 | N64: 60 | P64: Usata | Q64: Sì | T64: =IF(P64='Menu tendina'!A$5,0,IF(P64='Menu tendina'!A$4,'2. Private'!N64/2,IF(P64='Menu tendina'!A$3,'2. Private'!N64,IF(P64='Menu tendina'!A$2,'2. Private'!M64,0)))) -> 60
A65: 2. Private | B65: 1. Precursorie Omaggio | C65: PO62 | D65: 3072 | E65: 56 | F65: 10 scatti | G65: - | H65: Trentino - Appiano | I65: Tep | J65: Senza OCR | K65: - | L65: - | M65: 60 | N65: 40 | P65: Nuova | Q65: Codici regolari | R65: 01/04/021/10631 - 04/10 | T65: =IF(P65='Menu tendina'!A$5,0,IF(P65='Menu tendina'!A$4,'2. Private'!N65/2,IF(P65='Menu tendina'!A$3,'2. Private'!N65,IF(P65='Menu tendina'!A$2,'2. Private'!M65,0)))) -> 60
A66: 2. Private | B66: 1. Precursorie Omaggio | C66: PO63 | D66: 3073 | E66: 57 | F66: 10 scatti | G66: - | H66: Trentino - Segonzano | I66: Tep | J66: Senza OCR | K66: - | L66: - | M66: 60 | N66: 40 | P66: Nuova | Q66: Codici regolari | R66: 01/04/024/22797 - 04/10 | T66: =IF(P66='Menu tendina'!A$5,0,IF(P66='Menu tendina'!A$4,'2. Private'!N66/2,IF(P66='Menu tendina'!A$3,'2. Private'!N66,IF(P66='Menu tendina'!A$2,'2. Private'!M66,0)))) -> 60
A67: 2. Private | B67: 1. Precursorie Omaggio | C67: PO64 | D67: 3076 | E67: 58 | F67: 10 scatti | G67: - | H67: Umbria - Assisi | I67: Tep | J67: Senza OCR | K67: - | L67: - | M67: 50 | N67: 30 | P67: Nuova | Q67: Codici regolari | R67: 01/04/023/01441 - 04/10 | T67: =IF(P67='Menu tendina'!A$5,0,IF(P67='Menu tendina'!A$4,'2. Private'!N67/2,IF(P67='Menu tendina'!A$3,'2. Private'!N67,IF(P67='Menu tendina'!A$2,'2. Private'!M67,0)))) -> 50
A68: 2. Private | B68: 1. Precursorie Omaggio | C68: PO65 | D68: 3079 | E68: 59 | F68: 10 scatti | G68: - | H68: Umbria - Perugia | I68: Tep | J68: Senza OCR | K68: - | L68: - | M68: 90 | N68: 45 | P68: Nuova | Q68: Codici regolari | R68: 01/04/022/12305 - 04/10 | T68: =IF(P68='Menu tendina'!A$5,0,IF(P68='Menu tendina'!A$4,'2. Private'!N68/2,IF(P68='Menu tendina'!A$3,'2. Private'!N68,IF(P68='Menu tendina'!A$2,'2. Private'!M68,0)))) -> 90
A69: 2. Private | B69: 1. Precursorie Omaggio | C69: PO66 | D69: 3082 | E69: 60 | F69: 10 scatti | G69: - | H69: Valle Aosta - Ayas | I69: Tep | J69: Senza OCR | K69: - | L69: - | M69: 55 | N69: 35 | P69: Nuova | Q69: Codici regolari | R69: 01/04/021/04931 - 04/10 | T69: =IF(P69='Menu tendina'!A$5,0,IF(P69='Menu tendina'!A$4,'2. Private'!N69/2,IF(P69='Menu tendina'!A$3,'2. Private'!N69,IF(P69='Menu tendina'!A$2,'2. Private'!M69,0)))) -> 55
A70: 2. Private | B70: 1. Precursorie Omaggio | C70: PO67 | D70: 3084 | E70: 61 | F70: 10 scatti | G70: - | H70: Valle Aosta - Sarriod | I70: Tep | J70: Senza OCR | K70: - | L70: - | M70: 75 | N70: 45 | P70: Nuova | Q70: Codici regolari | R70: 01/04/022/03002 - 04/10 | T70: =IF(P70='Menu tendina'!A$5,0,IF(P70='Menu tendina'!A$4,'2. Private'!N70/2,IF(P70='Menu tendina'!A$3,'2. Private'!N70,IF(P70='Menu tendina'!A$2,'2. Private'!M70,0)))) -> 75
A71: 2. Private | B71: 1. Precursorie Omaggio | C71: PO68 | D71: 3088 | E71: 62 | F71: 10 scatti | G71: - | H71: Veneto - Gazzo Veronese | I71: Tep | J71: Senza OCR | K71: - | L71: - | M71: 50 | N71: 30 | P71: Nuova | Q71: Codici regolari | R71: 01/04/021/12318 - 04/10 | T71: =IF(P71='Menu tendina'!A$5,0,IF(P71='Menu tendina'!A$4,'2. Private'!N71/2,IF(P71='Menu tendina'!A$3,'2. Private'!N71,IF(P71='Menu tendina'!A$2,'2. Private'!M71,0)))) -> 50
A72: 2. Private | B72: 1. Precursorie Omaggio | C72: PO69 | D72: 3090 | E72: 63 | F72: 10 scatti | G72: - | H72: Veneto - Piazzola sul Brenta | I72: Tep | J72: Senza OCR | K72: - | L72: - | M72: 50 | N72: 30 | P72: Nuova | Q72: Codici regolari | R72: 01/04/024/13631 - 04/10 | T72: =IF(P72='Menu tendina'!A$5,0,IF(P72='Menu tendina'!A$4,'2. Private'!N72/2,IF(P72='Menu tendina'!A$3,'2. Private'!N72,IF(P72='Menu tendina'!A$2,'2. Private'!M72,0)))) -> 50
A73: 2. Private | B73: 1. Precursorie Omaggio | C73: PO70 | D73: 3013 | E73: 64 | F73: 10 scatti | G73: - | H73: Abruzzo - Penne | I73: Tep | J73: Con OCR senza banda grigia | K73: - | L73: - | M73: 35 | N73: 20 | P73: Manca | T73: =IF(P73='Menu tendina'!A$5,0,IF(P73='Menu tendina'!A$4,'2. Private'!N73/2,IF(P73='Menu tendina'!A$3,'2. Private'!N73,IF(P73='Menu tendina'!A$2,'2. Private'!M73,0)))) -> 0
A74: 2. Private | B74: 1. Precursorie Omaggio | C74: PO71 | D74: 3016 | E74: 65 | F74: 10 scatti | G74: - | H74: Basilicata - Matera | I74: Tep | J74: Con OCR senza banda grigia | K74: - | L74: - | M74: 35 | N74: 20 | P74: Manca | T74: =IF(P74='Menu tendina'!A$5,0,IF(P74='Menu tendina'!A$4,'2. Private'!N74/2,IF(P74='Menu tendina'!A$3,'2. Private'!N74,IF(P74='Menu tendina'!A$2,'2. Private'!M74,0)))) -> 0
A75: 2. Private | B75: 1. Precursorie Omaggio | C75: PO72 | D75: 3018 | E75: 66 | F75: 10 scatti | G75: - | H75: Calabria - Reggio Calabria | I75: Tep | J75: Con OCR senza banda grigia | K75: - | L75: - | M75: 35 | N75: 20 | P75: Manca | T75: =IF(P75='Menu tendina'!A$5,0,IF(P75='Menu tendina'!A$4,'2. Private'!N75/2,IF(P75='Menu tendina'!A$3,'2. Private'!N75,IF(P75='Menu tendina'!A$2,'2. Private'!M75,0)))) -> 0
A76: 2. Private | B76: 1. Precursorie Omaggio | C76: PO73 | D76: 3022 | E76: 67 | F76: 10 scatti | G76: - | H76: Campania - Sessa Aurunca | I76: Tep | J76: Con OCR senza banda grigia | K76: - | L76: - | M76: 35 | N76: 20 | P76: Manca | T76: =IF(P76='Menu tendina'!A$5,0,IF(P76='Menu tendina'!A$4,'2. Private'!N76/2,IF(P76='Menu tendina'!A$3,'2. Private'!N76,IF(P76='Menu tendina'!A$2,'2. Private'!M76,0)))) -> 0
A77: 2. Private | B77: 1. Precursorie Omaggio | C77: PO74 | D77: 3025 | E77: 68 | F77: 10 scatti | G77: - | H77: Emilia Romagna - Bologna | I77: Tep | J77: Con OCR senza banda grigia | K77: - | L77: - | M77: 35 | N77: 20 | P77: Nuova | Q77: Codici regolari | R77: 01/05/064/29734 - 04/10 | T77: =IF(P77='Menu tendina'!A$5,0,IF(P77='Menu tendina'!A$4,'2. Private'!N77/2,IF(P77='Menu tendina'!A$3,'2. Private'!N77,IF(P77='Menu tendina'!A$2,'2. Private'!M77,0)))) -> 35
A78: 2. Private | B78: 1. Precursorie Omaggio | C78: PO75 | D78: 3031 | E78: 69 | F78: 10 scatti | G78: - | H78: Friuli - Palmanova | I78: Tep | J78: Con OCR senza banda grigia | K78: - | L78: - | M78: 35 | N78: 20 | P78: Usata | Q78: Sì | T78: =IF(P78='Menu tendina'!A$5,0,IF(P78='Menu tendina'!A$4,'2. Private'!N78/2,IF(P78='Menu tendina'!A$3,'2. Private'!N78,IF(P78='Menu tendina'!A$2,'2. Private'!M78,0)))) -> 20
A79: 2. Private | B79: 1. Precursorie Omaggio | C79: PO76 | D79: 3036 | E79: 70 | F79: 10 scatti | G79: - | H79: Lazio - Roma (Testa femminile) | I79: Tep | J79: Con OCR senza banda grigia | K79: - | L79: - | M79: 35 | N79: 20 | P79: Manca | T79: =IF(P79='Menu tendina'!A$5,0,IF(P79='Menu tendina'!A$4,'2. Private'!N79/2,IF(P79='Menu tendina'!A$3,'2. Private'!N79,IF(P79='Menu tendina'!A$2,'2. Private'!M79,0)))) -> 0
A80: 2. Private | B80: 1. Precursorie Omaggio | C80: PO77 | D80: 3039 | E80: 71 | F80: 10 scatti | G80: - | H80: Liguria - Rio Maggiore | I80: Tep | J80: Con OCR senza banda grigia | K80: - | L80: - | M80: 35 | N80: 20 | P80: Nuova | Q80: Codici regolari | R80: 01/05/064/33218 - 04/10 | T80: =IF(P80='Menu tendina'!A$5,0,IF(P80='Menu tendina'!A$4,'2. Private'!N80/2,IF(P80='Menu tendina'!A$3,'2. Private'!N80,IF(P80='Menu tendina'!A$2,'2. Private'!M80,0)))) -> 35
A81: 2. Private | B81: 1. Precursorie Omaggio | C81: PO78 | D81: 3042 | E81: 72 | F81: 10 scatti | G81: - | H81: Lombardia - Valtellina | I81: Tep | J81: Con OCR senza banda grigia | K81: - | L81: - | M81: 35 | N81: 20 | P81: Manca | T81: =IF(P81='Menu tendina'!A$5,0,IF(P81='Menu tendina'!A$4,'2. Private'!N81/2,IF(P81='Menu tendina'!A$3,'2. Private'!N81,IF(P81='Menu tendina'!A$2,'2. Private'!M81,0)))) -> 0
A82: 2. Private | B82: 1. Precursorie Omaggio | C82: PO79 | D82: 3045 | E82: 73 | F82: 10 scatti | G82: - | H82: Marche - Ascoli | I82: Tep | J82: Con OCR senza banda grigia | K82: - | L82: - | M82: 35 | N82: 20 | P82: Manca | T82: =IF(P82='Menu tendina'!A$5,0,IF(P82='Menu tendina'!A$4,'2. Private'!N82/2,IF(P82='Menu tendina'!A$3,'2. Private'!N82,IF(P82='Menu tendina'!A$2,'2. Private'!M82,0)))) -> 0
A83: 2. Private | B83: 1. Precursorie Omaggio | C83: PO80 | D83: 3048 | E83: 74 | F83: 10 scatti | G83: - | H83: Molise - Altilia | I83: Tep | J83: Con OCR senza banda grigia | K83: - | L83: - | M83: 35 | N83: 20 | P83: Nuova | Q83: Codici Urmet | T83: =IF(P83='Menu tendina'!A$5,0,IF(P83='Menu tendina'!A$4,'2. Private'!N83/2,IF(P83='Menu tendina'!A$3,'2. Private'!N83,IF(P83='Menu tendina'!A$2,'2. Private'!M83,0)))) -> 35
A84: 2. Private | B84: 1. Precursorie Omaggio | C84: PO81 | D84: 3053 | E84: 75 | F84: 10 scatti | G84: - | H84: Piemonte - Grinzane Cavour | I84: Tep | J84: Con OCR senza banda grigia | K84: - | L84: - | M84: 35 | N84: 20 | P84: Nuova | Q84: Codici Urmet | T84: =IF(P84='Menu tendina'!A$5,0,IF(P84='Menu tendina'!A$4,'2. Private'!N84/2,IF(P84='Menu tendina'!A$3,'2. Private'!N84,IF(P84='Menu tendina'!A$2,'2. Private'!M84,0)))) -> 35
A85: 2. Private | B85: 1. Precursorie Omaggio | C85: PO82 | D85: 3057 | E85: 76 | F85: 10 scatti | G85: - | H85: Puglia - Alberobello | I85: Tep | J85: Con OCR senza banda grigia | K85: - | L85: - | M85: 35 | N85: 20 | P85: Usata | Q85: Sì | T85: =IF(P85='Menu tendina'!A$5,0,IF(P85='Menu tendina'!A$4,'2. Private'!N85/2,IF(P85='Menu tendina'!A$3,'2. Private'!N85,IF(P85='Menu tendina'!A$2,'2. Private'!M85,0)))) -> 20
A86: 2. Private | B86: 1. Precursorie Omaggio | C86: PO83 | D86: 3061 | E86: 77 | F86: 10 scatti | G86: - | H86: Sardegna - Goni | I86: Tep | J86: Con OCR senza banda grigia | K86: - | L86: - | M86: 35 | N86: 20 | P86: Usata | T86: =IF(P86='Menu tendina'!A$5,0,IF(P86='Menu tendina'!A$4,'2. Private'!N86/2,IF(P86='Menu tendina'!A$3,'2. Private'!N86,IF(P86='Menu tendina'!A$2,'2. Private'!M86,0)))) -> 20
A87: 2. Private | B87: 1. Precursorie Omaggio | C87: PO84 | D87: 3066 | E87: 78 | F87: 10 scatti | G87: - | H87: Sicilia - Trapani | I87: Tep | J87: Con OCR senza banda grigia | K87: - | L87: - | M87: 35 | N87: 20 | P87: Nuova | Q87: Codici regolari | R87: 01/05/064/35361 - 04/10 | T87: =IF(P87='Menu tendina'!A$5,0,IF(P87='Menu tendina'!A$4,'2. Private'!N87/2,IF(P87='Menu tendina'!A$3,'2. Private'!N87,IF(P87='Menu tendina'!A$2,'2. Private'!M87,0)))) -> 35
A88: 2. Private | B88: 1. Precursorie Omaggio | C88: PO85 | D88: 3069 | E88: 79 | F88: 10 scatti | G88: - | H88: Toscana - Magliano | I88: Tep | J88: Con OCR senza banda grigia | K88: - | L88: - | M88: 35 | N88: 20 | P88: Manca | T88: =IF(P88='Menu tendina'!A$5,0,IF(P88='Menu tendina'!A$4,'2. Private'!N88/2,IF(P88='Menu tendina'!A$3,'2. Private'!N88,IF(P88='Menu tendina'!A$2,'2. Private'!M88,0)))) -> 0
A89: 2. Private | B89: 1. Precursorie Omaggio | C89: PO86 | D89: 3074 | E89: 80 | F89: 10 scatti | G89: - | H89: Trentino - Segonzano | I89: Tep | J89: Con OCR senza banda grigia | K89: - | L89: - | M89: 35 | N89: 20 | P89: Manca | T89: =IF(P89='Menu tendina'!A$5,0,IF(P89='Menu tendina'!A$4,'2. Private'!N89/2,IF(P89='Menu tendina'!A$3,'2. Private'!N89,IF(P89='Menu tendina'!A$2,'2. Private'!M89,0)))) -> 0
A90: 2. Private | B90: 1. Precursorie Omaggio | C90: PO87 | D90: 3080 | E90: 81 | F90: 10 scatti | G90: - | H90: Umbria - Perugia | I90: Tep | J90: Con OCR senza banda grigia | K90: - | L90: - | M90: 35 | N90: 20 | P90: Nuova | Q90: Codici regolari | R90: 01/05/064/39331 - 04/10 | T90: =IF(P90='Menu tendina'!A$5,0,IF(P90='Menu tendina'!A$4,'2. Private'!N90/2,IF(P90='Menu tendina'!A$3,'2. Private'!N90,IF(P90='Menu tendina'!A$2,'2. Private'!M90,0)))) -> 35
A91: 2. Private | B91: 1. Precursorie Omaggio | C91: PO88 | D91: 3085 | E91: 82 | F91: 10 scatti | G91: - | H91: Valle Aosta - Sarriod | I91: Tep | J91: Con OCR senza banda grigia | K91: - | L91: - | M91: 35 | N91: 20 | P91: Nuova | Q91: Codici regolari | R91: 01/05/064/30601 - 04/10 | T91: =IF(P91='Menu tendina'!A$5,0,IF(P91='Menu tendina'!A$4,'2. Private'!N91/2,IF(P91='Menu tendina'!A$3,'2. Private'!N91,IF(P91='Menu tendina'!A$2,'2. Private'!M91,0)))) -> 35
A92: 2. Private | B92: 1. Precursorie Omaggio | C92: PO89 | D92: 3091 | E92: 83 | F92: 10 scatti | G92: - | H92: Veneto - Piazzola sul Brenta | I92: Tep | J92: Con OCR senza banda grigia | K92: - | L92: - | M92: 35 | N92: 20 | P92: Nuova | Q92: Codici regolari | R92: 01/05/064/31710 - 04/10 | T92: =IF(P92='Menu tendina'!A$5,0,IF(P92='Menu tendina'!A$4,'2. Private'!N92/2,IF(P92='Menu tendina'!A$3,'2. Private'!N92,IF(P92='Menu tendina'!A$2,'2. Private'!M92,0)))) -> 35
A93: 2. Private | B93: 2. Omaggio private | C93: OP1 | D93: 3092 | E93: 1 | F93: 10 scatti | G93: - | H93: IP con l'Italia | I93: Man | K93: - | L93: 27 | M93: 2 | N93: 1 | P93: Nuova | Q93: Codici regolari | R93: 01/05/213/05982 - 04/10 | T93: =IF(P93='Menu tendina'!A$5,0,IF(P93='Menu tendina'!A$4,'2. Private'!N93/2,IF(P93='Menu tendina'!A$3,'2. Private'!N93,IF(P93='Menu tendina'!A$2,'2. Private'!M93,0)))) -> 2
A94: 2. Private | B94: 2. Omaggio private | C94: OP2 | D94: 3093 | E94: 2 | F94: 10 scatti | G94: - | H94: Mascotte Ciao | I94: Man | K94: - | L94: 27 | M94: 2 | N94: 1 | P94: Nuova | Q94: Codici regolari | R94: 01/05/064/60424 - 04/10 | T94: =IF(P94='Menu tendina'!A$5,0,IF(P94='Menu tendina'!A$4,'2. Private'!N94/2,IF(P94='Menu tendina'!A$3,'2. Private'!N94,IF(P94='Menu tendina'!A$2,'2. Private'!M94,0)))) -> 2
A95: 2. Private | B95: 2. Omaggio private | C95: OP3 | D95: 3094 | E95: 5 | F95: 10 scatti | G95: - | H95: Pagine Gialle '90 - Campania | I95: Tep | K95: - | L95: 0.5 | M95: 100 | N95: 70 | P95: Manca | T95: =IF(P95='Menu tendina'!A$5,0,IF(P95='Menu tendina'!A$4,'2. Private'!N95/2,IF(P95='Menu tendina'!A$3,'2. Private'!N95,IF(P95='Menu tendina'!A$2,'2. Private'!M95,0)))) -> 0
A96: 2. Private | B96: 2. Omaggio private | C96: OP4 | D96: 3095 | E96: 6 | F96: 10 scatti | G96: - | H96: Pagine Gialle '90 - Emilia Romagna | I96: Tep | K96: - | L96: 0.5 | M96: 100 | N96: 70 | P96: Manca | T96: =IF(P96='Menu tendina'!A$5,0,IF(P96='Menu tendina'!A$4,'2. Private'!N96/2,IF(P96='Menu tendina'!A$3,'2. Private'!N96,IF(P96='Menu tendina'!A$2,'2. Private'!M96,0)))) -> 0
A97: 2. Private | B97: 2. Omaggio private | C97: OP5 | D97: 3096 | E97: 7 | F97: 10 scatti | G97: - | H97: Pagine Gialle '90 - Friuli | I97: Tep | K97: - | L97: 0.5 | M97: 100 | N97: 70 | P97: Manca | T97: =IF(P97='Menu tendina'!A$5,0,IF(P97='Menu tendina'!A$4,'2. Private'!N97/2,IF(P97='Menu tendina'!A$3,'2. Private'!N97,IF(P97='Menu tendina'!A$2,'2. Private'!M97,0)))) -> 0
A98: 2. Private | B98: 2. Omaggio private | C98: OP6 | D98: 3097 | E98: 8 | F98: 10 scatti | G98: - | H98: Pagine Gialle '90 - Lazio | I98: Tep | K98: - | L98: 0.5 | M98: 100 | N98: 70 | P98: Manca | T98: =IF(P98='Menu tendina'!A$5,0,IF(P98='Menu tendina'!A$4,'2. Private'!N98/2,IF(P98='Menu tendina'!A$3,'2. Private'!N98,IF(P98='Menu tendina'!A$2,'2. Private'!M98,0)))) -> 0
A99: 2. Private | B99: 2. Omaggio private | C99: OP7 | D99: 3098 | E99: 9 | F99: 10 scatti | G99: - | H99: Pagine Gialle '90 - Liguria | I99: Tep | K99: - | L99: 0.5 | M99: 100 | N99: 70 | P99: Manca | T99: =IF(P99='Menu tendina'!A$5,0,IF(P99='Menu tendina'!A$4,'2. Private'!N99/2,IF(P99='Menu tendina'!A$3,'2. Private'!N99,IF(P99='Menu tendina'!A$2,'2. Private'!M99,0)))) -> 0
A100: 2. Private | B100: 2. Omaggio private | C100: OP8 | D100: 3099 | E100: 10 | F100: 10 scatti | G100: - | H100: Pagine Gialle '90 - Lombardia | I100: Tep | K100: - | L100: 0.5 | M100: 100 | N100: 70 | P100: Manca | T100: =IF(P100='Menu tendina'!A$5,0,IF(P100='Menu tendina'!A$4,'2. Private'!N100/2,IF(P100='Menu tendina'!A$3,'2. Private'!N100,IF(P100='Menu tendina'!A$2,'2. Private'!M100,0)))) -> 0
A101: 2. Private | B101: 2. Omaggio private | C101: OP9 | D101: 3100 | E101: 11 | F101: 10 scatti | G101: - | H101: Pagine Gialle '90 - Piemonte | I101: Tep | K101: - | L101: 0.5 | M101: 100 | N101: 70 | P101: Manca | T101: =IF(P101='Menu tendina'!A$5,0,IF(P101='Menu tendina'!A$4,'2. Private'!N101/2,IF(P101='Menu tendina'!A$3,'2. Private'!N101,IF(P101='Menu tendina'!A$2,'2. Private'!M101,0)))) -> 0
A102: 2. Private | B102: 2. Omaggio private | C102: OP10 | D102: 3101 | E102: 12 | F102: 10 scatti | G102: - | H102: Pagine Gialle '90 - Puglia | I102: Tep | K102: - | L102: 0.5 | M102: 100 | N102: 70 | P102: Manca | T102: =IF(P102='Menu tendina'!A$5,0,IF(P102='Menu tendina'!A$4,'2. Private'!N102/2,IF(P102='Menu tendina'!A$3,'2. Private'!N102,IF(P102='Menu tendina'!A$2,'2. Private'!M102,0)))) -> 0
A103: 2. Private | B103: 2. Omaggio private | C103: OP11 | D103: 3102 | E103: 13 | F103: 10 scatti | G103: - | H103: Pagine Gialle '90 - Sardegna | I103: Tep | K103: - | L103: 0.5 | M103: 100 | N103: 70 | P103: Manca | T103: =IF(P103='Menu tendina'!A$5,0,IF(P103='Menu tendina'!A$4,'2. Private'!N103/2,IF(P103='Menu tendina'!A$3,'2. Private'!N103,IF(P103='Menu tendina'!A$2,'2. Private'!M103,0)))) -> 0
A104: 2. Private | B104: 2. Omaggio private | C104: OP12 | D104: 3103 | E104: 14 | F104: 10 scatti | G104: - | H104: Pagine Gialle '90 - Sicilia | I104: Tep | K104: - | L104: 0.5 | M104: 100 | N104: 70 | P104: Manca | T104: =IF(P104='Menu tendina'!A$5,0,IF(P104='Menu tendina'!A$4,'2. Private'!N104/2,IF(P104='Menu tendina'!A$3,'2. Private'!N104,IF(P104='Menu tendina'!A$2,'2. Private'!M104,0)))) -> 0
A105: 2. Private | B105: 2. Omaggio private | C105: OP13 | D105: 3104 | E105: 15 | F105: 10 scatti | G105: - | H105: Pagine Gialle '90 - Toscana | I105: Tep | K105: - | L105: 0.5 | M105: 100 | N105: 70 | P105: Manca | T105: =IF(P105='Menu tendina'!A$5,0,IF(P105='Menu tendina'!A$4,'2. Private'!N105/2,IF(P105='Menu tendina'!A$3,'2. Private'!N105,IF(P105='Menu tendina'!A$2,'2. Private'!M105,0)))) -> 0
A106: 2. Private | B106: 2. Omaggio private | C106: OP14 | D106: 3105 | E106: 16 | F106: 10 scatti | G106: - | H106: Pagine Gialle '90 - Veneto | I106: Tep | K106: - | L106: 0.5 | M106: 100 | N106: 70 | P106: Manca | T106: =IF(P106='Menu tendina'!A$5,0,IF(P106='Menu tendina'!A$4,'2. Private'!N106/2,IF(P106='Menu tendina'!A$3,'2. Private'!N106,IF(P106='Menu tendina'!A$2,'2. Private'!M106,0)))) -> 0
A107: 2. Private | B107: 2. Omaggio private | C107: OP15 | D107: 3106 | E107: 3 | F107: 10 scatti | G107: - | H107: Natale '90 - Botticelli | I107: Pik | K107: - | L107: 132 | M107: 2 | N107: 1 | P107: Nuova | Q107: Codici regolari | R107: 01/07/208/11881 - 04/10 | T107: =IF(P107='Menu tendina'!A$5,0,IF(P107='Menu tendina'!A$4,'2. Private'!N107/2,IF(P107='Menu tendina'!A$3,'2. Private'!N107,IF(P107='Menu tendina'!A$2,'2. Private'!M107,0)))) -> 2
...

Sheet 3. SIP
A1: Genere | B1: Sottogenere | C1: N.Golden | D1: N. C&C | E1: N. AG | F1: Taglio | G1: Scadenza | H1: Titolo | I1: Pr. | J1: Note | K1: Var | L1: Tiratura | M1: Val 2025 Nuova | N1: Val 2025 Usata | P1: Presente | Q1: Magnetizzazione | R1: Codici | T1: Valore collezione
A2: 3. Ordinarie | B2: 1. Fasce Orarie | C2: 1 | D2: 1101 | E2: 1 | F2: 5000 | G2: 31.12.89 | H2: Fasce Orarie | I2: Pik | J2: Braille, filigrana, banda grigia chiara piena, numerazione (Lotti 211/213) | K2: - | L2: 150 | M2: 45 | N2: 10 | P2: Nuova | Q2: No | T2: =IF(P2='Menu tendina'!A$5,0,IF(P2='Menu tendina'!A$4,'3. SIP'!N2/2,IF(P2='Menu tendina'!A$3,'3. SIP'!N2,IF(P2='Menu tendina'!A$2,'3. SIP'!M2,0)))) -> 45
A3: 3. Ordinarie | B3: 1. Fasce Orarie | C3: 1A | D3: 1101A | E3: 1A | F3: 5000 | G3: 31.12.89 | H3: Fasce Orarie | I3: Pik | J3: Braille, filigrana, banda grigia chiara retinata, numerazione (Lotti 251/265) | K3: Variante | L3: - | M3: 45 | N3: 10 | P3: Nuova | Q3: No | T3: =IF(P3='Menu tendina'!A$5,0,IF(P3='Menu tendina'!A$4,'3. SIP'!N3/2,IF(P3='Menu tendina'!A$3,'3. SIP'!N3,IF(P3='Menu tendina'!A$2,'3. SIP'!M3,0)))) -> 45
A4: 3. Ordinarie | B4: 1. Fasce Orarie | C4: 2 | D4: 1102 | E4: 2 | F4: 10000 | G4: 31.12.89 | H4: Fasce Orarie | I4: Pik | J4: Braille, filigrana, banda grigia chiara piena, numerazione (Lotti 211/213) | K4: - | L4: 150 | M4: 40 | N4: 10 | P4: Nuova | Q4: No | T4: =IF(P4='Menu tendina'!A$5,0,IF(P4='Menu tendina'!A$4,'3. SIP'!N4/2,IF(P4='Menu tendina'!A$3,'3. SIP'!N4,IF(P4='Menu tendina'!A$2,'3. SIP'!M4,0)))) -> 40
A5: 3. Ordinarie | B5: 1. Fasce Orarie | C5: 2A | D5: 1102A | E5: 2A | F5: 10000 | G5: 31.12.89 | H5: Fasce Orarie | I5: Pik | J5: Braille, filigrana, banda brigia chiara retinata, numerazione (Lotti 251/265) | K5: Variante | L5: - | M5: 40 | N5: 10 | P5: Nuova | Q5: Sì | T5: =IF(P5='Menu tendina'!A$5,0,IF(P5='Menu tendina'!A$4,'3. SIP'!N5/2,IF(P5='Menu tendina'!A$3,'3. SIP'!N5,IF(P5='Menu tendina'!A$2,'3. SIP'!M5,0)))) -> 40
A6: 3. Ordinarie | B6: 1. Fasce Orarie | C6: 3 | D6: 1101B | E6: 3 | F6: 5000 | G6: 31.12.89 | H6: Fasce Orarie | I6: Pik | J6: (N.E.) (N.M.) Braille, filigrana, numerazione. Manca banda grigia | K6: - | L6: 200 | M6: 10 | N6: 8 | P6: Nuova | Q6: n/a | T6: =IF(P6='Menu tendina'!A$5,0,IF(P6='Menu tendina'!A$4,'3. SIP'!N6/2,IF(P6='Menu tendina'!A$3,'3. SIP'!N6,IF(P6='Menu tendina'!A$2,'3. SIP'!M6,0)))) -> 10
A7: 3. Ordinarie | B7: 1. Fasce Orarie | C7: 4 | D7: 1102B | E7: 4 | F7: 10000 | G7: 31.12.89 | H7: Fasce Orarie | I7: Pik | J7: (N.E.) (N.M.) Braille, filigrana, numerazione. Manca banda grigia | K7: - | L7: 100 | M7: 50 | N7: 25 | P7: Nuova | Q7: n/a | T7: =IF(P7='Menu tendina'!A$5,0,IF(P7='Menu tendina'!A$4,'3. SIP'!N7/2,IF(P7='Menu tendina'!A$3,'3. SIP'!N7,IF(P7='Menu tendina'!A$2,'3. SIP'!M7,0)))) -> 50
A8: 3. Ordinarie | B8: 1. Fasce Orarie | C8: 5 | D8: 1103 | E8: 5 | F8: 5000 | G8: 31.12.89 | H8: Fasce Orarie | I8: Pik | J8: (N.E.) (N.M.) Filigrana, banda grigia retinata chiara. Manca braille, numerazione | K8: - | L8: - | M8: 120 | N8: 70 | P8: Nuova | Q8: n/a | T8: =IF(P8='Menu tendina'!A$5,0,IF(P8='Menu tendina'!A$4,'3. SIP'!N8/2,IF(P8='Menu tendina'!A$3,'3. SIP'!N8,IF(P8='Menu tendina'!A$2,'3. SIP'!M8,0)))) -> 120
A9: 3. Ordinarie | B9: 1. Fasce Orarie | C9: 5A | D9: 1103a | E9: 5A | F9: 5000 | G9: 31.12.89 | H9: Fasce Orarie | I9: Pik | J9: (N.M.) Filigrana, banda grigia chiara retinata, numerazione A. Manca braille | K9: Variante | L9: 100 | M9: 10 | N9: 6 | P9: Nuova | Q9: n/a | T9: =IF(P9='Menu tendina'!A$5,0,IF(P9='Menu tendina'!A$4,'3. SIP'!N9/2,IF(P9='Menu tendina'!A$3,'3. SIP'!N9,IF(P9='Menu tendina'!A$2,'3. SIP'!M9,0)))) -> 10
A10: 3. Ordinarie | B10: 1. Fasce Orarie | C10: 5B | D10: 1103b | E10: 5B | F10: 5000 | G10: 31.12.89 | H10: Fasce Orarie | I10: Pik | J10: (N.M.) Filigrana, banda grigia chiara retinata, numerazione B. Manca braille | K10: Variante | L10: 100 | M10: 10 | N10: 6 | P10: Nuova | Q10: n/a | T10: =IF(P10='Menu tendina'!A$5,0,IF(P10='Menu tendina'!A$4,'3. SIP'!N10/2,IF(P10='Menu tendina'!A$3,'3. SIP'!N10,IF(P10='Menu tendina'!A$2,'3. SIP'!M10,0)))) -> 10
A11: 3. Ordinarie | B11: 1. Fasce Orarie | C11: 5C | D11: 1103c | E11: 5C | F11: 5000 | G11: 31.12.89 | H11: Fasce Orarie | I11: Pik | J11: (N.M.) Filigrana, banda grigia chiara retinata, numerazione C. Manca braille | K11: Variante | L11: 100 | M11: 10 | N11: 6 | P11: Nuova | Q11: n/a | T11: =IF(P11='Menu tendina'!A$5,0,IF(P11='Menu tendina'!A$4,'3. SIP'!N11/2,IF(P11='Menu tendina'!A$3,'3. SIP'!N11,IF(P11='Menu tendina'!A$2,'3. SIP'!M11,0)))) -> 10
A12: 3. Ordinarie | B12: 1. Fasce Orarie | C12: 5D | D12: 1103d | E12: 5D | F12: 5000 | G12: 31.12.89 | H12: Fasce Orarie | I12: Pik | J12: (N.M.) Filigrana, banda grigia chiara retinata, numerazione D. Manca braille | K12: Variante | L12: 100 | M12: 10 | N12: 6 | P12: Nuova | Q12: n/a | T12: =IF(P12='Menu tendina'!A$5,0,IF(P12='Menu tendina'!A$4,'3. SIP'!N12/2,IF(P12='Menu tendina'!A$3,'3. SIP'!N12,IF(P12='Menu tendina'!A$2,'3. SIP'!M12,0)))) -> 10
A13: 3. Ordinarie | B13: 1. Fasce Orarie | C13: 6 | D13: 1104 | E13: 6 | F13: 10000 | G13: 31.12.89 | H13: Fasce Orarie | I13: Pik | J13: (N.E.) (N.M.) Filigrana, banda grigia chiara retinata. Manca braille, numerazione | K13: - | L13: - | M13: 150 | N13: 90 | P13: Nuova | Q13: n/a | T13: =IF(P13='Menu tendina'!A$5,0,IF(P13='Menu tendina'!A$4,'3. SIP'!N13/2,IF(P13='Menu tendina'!A$3,'3. SIP'!N13,IF(P13='Menu tendina'!A$2,'3. SIP'!M13,0)))) -> 150
A14: 3. Ordinarie | B14: 1. Fasce Orarie | C14: 6A | D14: 1104a | E14: 6A | F14: 10000 | G14: 31.12.89 | H14: Fasce Orarie | I14: Pik | J14: (N.M.) Filigrana, banda grigia chiara retinata, numerazione A. Manca braille | K14: Variante | L14: 100 | M14: 12 | N14: 7 | P14: Nuova | Q14: n/a | T14: =IF(P14='Menu tendina'!A$5,0,IF(P14='Menu tendina'!A$4,'3. SIP'!N14/2,IF(P14='Menu tendina'!A$3,'3. SIP'!N14,IF(P14='Menu tendina'!A$2,'3. SIP'!M14,0)))) -> 12
A15: 3. Ordinarie | B15: 1. Fasce Orarie | C15: 6B | D15: 1104b | E15: 6B | F15: 10000 | G15: 31.12.89 | H15: Fasce Orarie | I15: Pik | J15: (N.M.) Filigrana, banda grigia chiara retinata, numerazione B. Manca braille | K15: Variante | L15: 100 | M15: 12 | N15: 7 | P15: Nuova | Q15: n/a | T15: =IF(P15='Menu tendina'!A$5,0,IF(P15='Menu tendina'!A$4,'3. SIP'!N15/2,IF(P15='Menu tendina'!A$3,'3. SIP'!N15,IF(P15='Menu tendina'!A$2,'3. SIP'!M15,0)))) -> 12
A16: 3. Ordinarie | B16: 1. Fasce Orarie | C16: 6C | D16: 1104c | E16: 6C | F16: 10000 | G16: 31.12.89 | H16: Fasce Orarie | I16: Pik | J16: (N.M.) Filigrana, banda grigia chiara retinata, numerazione C. Manca braille | K16: Variante | L16: 100 | M16: 12 | N16: 7 | P16: Nuova | Q16: n/a | T16: =IF(P16='Menu tendina'!A$5,0,IF(P16='Menu tendina'!A$4,'3. SIP'!N16/2,IF(P16='Menu tendina'!A$3,'3. SIP'!N16,IF(P16='Menu tendina'!A$2,'3. SIP'!M16,0)))) -> 12
A17: 3. Ordinarie | B17: 1. Fasce Orarie | C17: 6D | D17: 1104d | E17: 6D | F17: 10000 | G17: 31.12.89 | H17: Fasce Orarie | I17: Pik | J17: (N.M.) Filigrana, banda grigia chiara retinata, numerazione D. Manca braille | K17: Variante | L17: 100 | M17: 12 | N17: 7 | P17: Nuova | Q17: n/a | T17: =IF(P17='Menu tendina'!A$5,0,IF(P17='Menu tendina'!A$4,'3. SIP'!N17/2,IF(P17='Menu tendina'!A$3,'3. SIP'!N17,IF(P17='Menu tendina'!A$2,'3. SIP'!M17,0)))) -> 12
A18: 3. Ordinarie | B18: 1. Fasce Orarie | C18: 7 | D18: 1105 | E18: 7 | F18: 5000 | G18: 31.12.89 | H18: Fasce Orarie | I18: Pik | J18: Banda grigia chiara retinata. Manca braille, filigrana, numerazione | K18: - | L18: - | M18: 25 | N18: 15 | P18: Nuova | Q18: No | T18: =IF(P18='Menu tendina'!A$5,0,IF(P18='Menu tendina'!A$4,'3. SIP'!N18/2,IF(P18='Menu tendina'!A$3,'3. SIP'!N18,IF(P18='Menu tendina'!A$2,'3. SIP'!M18,0)))) -> 25
A19: 3. Ordinarie | B19: 1. Fasce Orarie | C19: 8 | D19: 1106 | E19: 8 | F19: 10000 | G19: 31.12.89 | H19: Fasce Orarie | I19: Pik | J19: Banda grigia chiara retinata. Manca braille, filigrana, numerazione | K19: - | L19: - | M19: 30 | N19: 20 | P19: Nuova | Q19: No | T19: =IF(P19='Menu tendina'!A$5,0,IF(P19='Menu tendina'!A$4,'3. SIP'!N19/2,IF(P19='Menu tendina'!A$3,'3. SIP'!N19,IF(P19='Menu tendina'!A$2,'3. SIP'!M19,0)))) -> 30
A20: 3. Ordinarie | B20: 1. Fasce Orarie | C20: 9 | D20: 1107 | E20: 9 | F20: 5000 | G20: 31.12.89 | H20: Fasce Orarie | I20: Pik | J20: Banda grigia scura piena. Manca braille, filigrana, numerazione | K20: - | L20: 6.000 | M20: 4 | N20: 0.3 | P20: Nuova | Q20: Codici regolari | T20: =IF(P20='Menu tendina'!A$5,0,IF(P20='Menu tendina'!A$4,'3. SIP'!N20/2,IF(P20='Menu tendina'!A$3,'3. SIP'!N20,IF(P20='Menu tendina'!A$2,'3. SIP'!M20,0)))) -> 4
A21: 3. Ordinarie | B21: 1. Fasce Orarie | C21: 9A | D21: 1107a | E21: 9A | F21: 5000 | G21: 31.12.89 | H21: Fasce Orarie | I21: Pik | J21: Banda grigia scura retinata. Manca braille, filigrana, numerazione | K21: Variante | L21: - | M21: 4 | N21: 0.5 | P21: Nuova | Q21: Codici regolari | T21: =IF(P21='Menu tendina'!A$5,0,IF(P21='Menu tendina'!A$4,'3. SIP'!N21/2,IF(P21='Menu tendina'!A$3,'3. SIP'!N21,IF(P21='Menu tendina'!A$2,'3. SIP'!M21,0)))) -> 4
A22: 3. Ordinarie | B22: 1. Fasce Orarie | C22: 10 | D22: 1107b | E22: 10 | F22: 10000 | G22: 31.12.89 | H22: Fasce Orarie | I22: Pik | J22: (N.M.) Banda grigia scura piena. Manca braille, filigrana, numerazione | K22: - | L22: 200 | M22: 35 | N22: 20 | P22: Nuova | Q22: n/a | T22: =IF(P22='Menu tendina'!A$5,0,IF(P22='Menu tendina'!A$4,'3. SIP'!N22/2,IF(P22='Menu tendina'!A$3,'3. SIP'!N22,IF(P22='Menu tendina'!A$2,'3. SIP'!M22,0)))) -> 35
A23: 3. Ordinarie | B23: 1. Fasce Orarie | C23: 11 | D23: 1108 | E23: 11 | F23: 5000 | G23: 31.12.89 | H23: Fasce Orarie | I23: Man | J23: Cartoncino. Banda grigia scura piena. Manca braille, filigrana, numerazione | K23: - | L23: 750 | M23: 2.5 | N23: 0.5 | P23: Nuova | Q23: Codici Urmet | T23: =IF(P23='Menu tendina'!A$5,0,IF(P23='Menu tendina'!A$4,'3. SIP'!N23/2,IF(P23='Menu tendina'!A$3,'3. SIP'!N23,IF(P23='Menu tendina'!A$2,'3. SIP'!M23,0)))) -> 2.5
A24: 3. Ordinarie | B24: 1. Fasce Orarie | C24: 12 | D24: 1109 | E24: 12 | F24: 10000 | G24: 31.12.89 | H24: Fasce Orarie | I24: Man | J24: Cartoncino. Banda grigia scura piena. Manca braille, filigrana, numerazione | K24: - | L24: 500 | M24: 40 | N24: 0.6 | P24: Nuova | Q24: Codici regolari | T24: =IF(P24='Menu tendina'!A$5,0,IF(P24='Menu tendina'!A$4,'3. SIP'!N24/2,IF(P24='Menu tendina'!A$3,'3. SIP'!N24,IF(P24='Menu tendina'!A$2,'3. SIP'!M24,0)))) -> 40
A25: 3. Ordinarie | B25: 1. Fasce Orarie | C25: 13 | D25: 1112 | E25: 13 | F25: 5000 | G25: 30.06.90 | H25: Fasce Orarie | I25: Pik | J25: Filigrana, banda grigia scura piena. Manca numerazione | K25: - | L25: 5.800 | M25: 3 | N25: 0.3 | P25: Nuova | Q25: No | T25: =IF(P25='Menu tendina'!A$5,0,IF(P25='Menu tendina'!A$4,'3. SIP'!N25/2,IF(P25='Menu tendina'!A$3,'3. SIP'!N25,IF(P25='Menu tendina'!A$2,'3. SIP'!M25,0)))) -> 3
A26: 3. Ordinarie | B26: 1. Fasce Orarie | C26: 13A | D26: 1112a | E26: 13A | F26: 5000 | G26: 30.06.90 | H26: Fasce Orarie | I26: Pik | J26: Filigrana, banda grigia scura retinata. Manca numerazione | K26: Variante | L26: - | M26: 4.5 | N26: 0.5 | P26: Nuova | Q26: Codici Urmet | T26: =IF(P26='Menu tendina'!A$5,0,IF(P26='Menu tendina'!A$4,'3. SIP'!N26/2,IF(P26='Menu tendina'!A$3,'3. SIP'!N26,IF(P26='Menu tendina'!A$2,'3. SIP'!M26,0)))) -> 4.5
A27: 3. Ordinarie | B27: 1. Fasce Orarie | C27: 14 | D27: 1113 | E27: 14 | F27: 10000 | G27: 30.06.90 | H27: Fasce Orarie | I27: Pik | J27: Filigrana, banda grigia scura piena. Manca numerazione | K27: - | L27: 4.800 | M27: 4 | N27: 0.3 | P27: Nuova | Q27: Codici Urmet | T27: =IF(P27='Menu tendina'!A$5,0,IF(P27='Menu tendina'!A$4,'3. SIP'!N27/2,IF(P27='Menu tendina'!A$3,'3. SIP'!N27,IF(P27='Menu tendina'!A$2,'3. SIP'!M27,0)))) -> 4
A28: 3. Ordinarie | B28: 1. Fasce Orarie | C28: 14A | D28: 1113a | E28: 14A | F28: 10000 | G28: 30.06.90 | H28: Fasce Orarie | I28: Pik | J28: Filigrana, banda grigia scura retinata. Manca numerazione | K28: Variante | L28: - | M28: 5 | N28: 0.5 | P28: Nuova | Q28: Codici Urmet | T28: =IF(P28='Menu tendina'!A$5,0,IF(P28='Menu tendina'!A$4,'3. SIP'!N28/2,IF(P28='Menu tendina'!A$3,'3. SIP'!N28,IF(P28='Menu tendina'!A$2,'3. SIP'!M28,0)))) -> 5
A29: 3. Ordinarie | B29: 1. Fasce Orarie | C29: 15 | D29: 5208 | E29: 15 | F29: 5000 | G29: 30.06.90 | H29: Fasce Orarie | I29: Pik | J29: (N.E.) (N.M.) Filigrana, CAB, numerazione, banda grigia scura. Manca zero del mese | K29: - | L29: - | M29: 150 | N29: 90 | P29: Nuova | Q29: n/a | T29: =IF(P29='Menu tendina'!A$5,0,IF(P29='Menu tendina'!A$4,'3. SIP'!N29/2,IF(P29='Menu tendina'!A$3,'3. SIP'!N29,IF(P29='Menu tendina'!A$2,'3. SIP'!M29,0)))) -> 150
A30: 3. Ordinarie | B30: 1. Fasce Orarie | C30: 16 | D30: 8209 | E30: 16 | F30: 10000 | G30: 30.06.90 | H30: Fasce Orarie | I30: Pik | J30: (N.E.) (N.M.) Filigrana, CAB, numerazione, banda grigia scura | K30: - | L30: - | M30: 300 | N30: 180 | P30: Manca | Q30: n/a | T30: =IF(P30='Menu tendina'!A$5,0,IF(P30='Menu tendina'!A$4,'3. SIP'!N30/2,IF(P30='Menu tendina'!A$3,'3. SIP'!N30,IF(P30='Menu tendina'!A$2,'3. SIP'!M30,0)))) -> 0
A31: 3. Ordinarie | B31: 1. Fasce Orarie | C31: 17 | D31: 1114a | E31: 17A | F31: 5000 | G31: 30.06.90 | H31: Fasce Orarie | I31: Tec | J31: Braille, filigrana, banda grigia chiara piena, numerazione con A stretta | K31: - | L31: 275 | M31: 400 | N31: 70 | P31: Usata | T31: =IF(P31='Menu tendina'!A$5,0,IF(P31='Menu tendina'!A$4,'3. SIP'!N31/2,IF(P31='Menu tendina'!A$3,'3. SIP'!N31,IF(P31='Menu tendina'!A$2,'3. SIP'!M31,0)))) -> 70
A32: 3. Ordinarie | B32: 1. Fasce Orarie | C32: 17A | D32: 1114 | E32: 17 | F32: 5000 | G32: 30.06.90 | H32: Fasce Orarie | I32: Tec | J32: Braille, filigrana, banda grigia chiara piena, numerazione con A larga | K32: Variante | L32: 100 | M32: P.A.R. | N32: 130 | P32: Usata | T32: =IF(P32='Menu tendina'!A$5,0,IF(P32='Menu tendina'!A$4,'3. SIP'!N32/2,IF(P32='Menu tendina'!A$3,'3. SIP'!N32,IF(P32='Menu tendina'!A$2,'3. SIP'!M32,0)))) -> 130
A33: 3. Ordinarie | B33: 1. Fasce Orarie | C33: 18 | D33: 1115 | E33: 18 | F33: 10000 | G33: 30.06.90 | H33: Fasce Orarie | I33: Tec | J33: Braille, filigrana, banda grigia chiara piena, numerazione | K33: - | L33: 25 | M33: P.A.R. | N33: 350 | P33: Usata | Q33: Sì | T33: =IF(P33='Menu tendina'!A$5,0,IF(P33='Menu tendina'!A$4,'3. SIP'!N33/2,IF(P33='Menu tendina'!A$3,'3. SIP'!N33,IF(P33='Menu tendina'!A$2,'3. SIP'!M33,0)))) -> 350
A34: 3. Ordinarie | B34: 1. Fasce Orarie | C34: 19 | D34: 1116 | E34: 19 | F34: 5000 | G34: 30.06.90 | H34: Fasce Orarie | I34: Pos | J34: Braille, filigrana, banda grigia chiara piena, numerazione con 88 finale | K34: - | L34: 3.000 | M34: 4 | N34: 0.3 | P34: Nuova | Q34: Codici regolari | T34: =IF(P34='Menu tendina'!A$5,0,IF(P34='Menu tendina'!A$4,'3. SIP'!N34/2,IF(P34='Menu tendina'!A$3,'3. SIP'!N34,IF(P34='Menu tendina'!A$2,'3. SIP'!M34,0)))) -> 4
A35: 3. Ordinarie | B35: 1. Fasce Orarie | C35: 19A | D35: 1116a | E35: 19A | F35: 5000 | G35: 30.06.90 | H35: Fasce Orarie | I35: Pos | J35: Braille, filigrana, banda grigia chiara piena, numerazione con 89 finale | K35: Variante | L35: - | M35: 50 | N35: 1 | P35: Nuova | R35: Non leggibile | T35: =IF(P35='Menu tendina'!A$5,0,IF(P35='Menu tendina'!A$4,'3. SIP'!N35/2,IF(P35='Menu tendina'!A$3,'3. SIP'!N35,IF(P35='Menu tendina'!A$2,'3. SIP'!M35,0)))) -> 50
A36: 3. Ordinarie | B36: 1. Fasce Orarie | C36: 20 | D36: 1117 | E36: 20 | F36: 10000 | G36: 30.06.90 | H36: Fasce Orarie | I36: Pos | J36: Braille, filigrana, banda grigia chiara piena, numerazione | K36: - | L36: 1.075 | M36: 2.5 | N36: 0.4 | P36: Nuova | Q36: Codici Urmet | T36: =IF(P36='Menu tendina'!A$5,0,IF(P36='Menu tendina'!A$4,'3. SIP'!N36/2,IF(P36='Menu tendina'!A$3,'3. SIP'!N36,IF(P36='Menu tendina'!A$2,'3. SIP'!M36,0)))) -> 2.5
A37: 3. Ordinarie | B37: 1. Fasce Orarie | C37: 21 | D37: 1118 | E37: 21 | F37: 5000 | G37: 30.06.90 | H37: Fasce Orarie | I37: Pos | J37: Braille, filigrana, banda grigia chiara piena. Manca numerazione | K37: - | L37: 750 | M37: 3 | N37: 0.5 | P37: Nuova | Q37: Codici Urmet | T37: =IF(P37='Menu tendina'!A$5,0,IF(P37='Menu tendina'!A$4,'3. SIP'!N37/2,IF(P37='Menu tendina'!A$3,'3. SIP'!N37,IF(P37='Menu tendina'!A$2,'3. SIP'!M37,0)))) -> 3
A38: 3. Ordinarie | B38: 1. Fasce Orarie | C38: 21A | D38: - | E38: - | F38: 5000 | G38: 30.06.90 | H38: Fasce Orarie | I38: Pos | J38: Filigrana, banda grigia chiara piena. Manca Braille, numerazione | K38: Variante | L38: - | M38: 3 | N38: 35 | P38: Manca | T38: =IF(P38='Menu tendina'!A$5,0,IF(P38='Menu tendina'!A$4,'3. SIP'!N38/2,IF(P38='Menu tendina'!A$3,'3. SIP'!N38,IF(P38='Menu tendina'!A$2,'3. SIP'!M38,0)))) -> 0
A39: 3. Ordinarie | B39: 1. Fasce Orarie | C39: 22 | D39: 1119 | E39: 22 | F39: 10000 | G39: 30.06.90 | H39: Fasce Orarie | I39: Pos | J39: Braille, filigrana, banda grigia chiara piena. Manca numerazione | K39: - | L39: 600 | M39: 4 | N39: 0.6 | P39: Nuova | Q39: Codici Urmet | T39: =IF(P39='Menu tendina'!A$5,0,IF(P39='Menu tendina'!A$4,'3. SIP'!N39/2,IF(P39='Menu tendina'!A$3,'3. SIP'!N39,IF(P39='Menu tendina'!A$2,'3. SIP'!M39,0)))) -> 4
A40: 3. Ordinarie | B40: 1. Fasce Orarie | C40: 22A | D40: 1119a | E40: - | F40: 10000 | G40: 30.06.90 | H40: Fasce Orarie | I40: Pos | J40: Braille, filigrana, banda grigia chiara retinata. Manca numerazione | K40: Variante | L40: - | M40: 4 | N40: 2 | P40: Manca | T40: =IF(P40='Menu tendina'!A$5,0,IF(P40='Menu tendina'!A$4,'3. SIP'!N40/2,IF(P40='Menu tendina'!A$3,'3. SIP'!N40,IF(P40='Menu tendina'!A$2,'3. SIP'!M40,0)))) -> 0
A41: 3. Ordinarie | B41: 1. Fasce Orarie | C41: 23 | D41: 1120 | E41: 23 | F41: 5000 | G41: 31.12.90 | H41: Fasce Orarie | I41: Pik | J41: Braille, filigrana, banda grigia piena chiara, numerazione da 117 a 123 | K41: - | L41: 5200 | M41: 3.5 | N41: 0.2 | P41: Nuova | Q41: Sì | T41: =IF(P41='Menu tendina'!A$5,0,IF(P41='Menu tendina'!A$4,'3. SIP'!N41/2,IF(P41='Menu tendina'!A$3,'3. SIP'!N41,IF(P41='Menu tendina'!A$2,'3. SIP'!M41,0)))) -> 3.5
A42: 3. Ordinarie | B42: 1. Fasce Orarie | C42: 23A | D42: 1120a | E42: 23A | F42: 5000 | G42: 31.12.90 | H42: Fasce Orarie | I42: Pik | J42: Braille, filigrana, banda grigia chiara retinata chiara, numerazione da 098 a 116 | K42: Variante | L42: - | M42: 20 | N42: 3 | P42: Nuova | Q42: Codici regolari | T42: =IF(P42='Menu tendina'!A$5,0,IF(P42='Menu tendina'!A$4,'3. SIP'!N42/2,IF(P42='Menu tendina'!A$3,'3. SIP'!N42,IF(P42='Menu tendina'!A$2,'3. SIP'!M42,0)))) -> 20
A43: 3. Ordinarie | B43: 1. Fasce Orarie | C43: 23B | D43: - | E43: - | F43: 5000 | G43: 31.12.90 | H43: Fasce Orarie | I43: Pik | J43: Braille, filigrana, banda grigia chiara retinata scura, numerazione da 098 a 116 | K43: Variante | L43: - | M43: 20 | N43: 3 | P43: Nuova | Q43: Codici regolari | T43: =IF(P43='Menu tendina'!A$5,0,IF(P43='Menu tendina'!A$4,'3. SIP'!N43/2,IF(P43='Menu tendina'!A$3,'3. SIP'!N43,IF(P43='Menu tendina'!A$2,'3. SIP'!M43,0)))) -> 20
A44: 3. Ordinarie | B44: 1. Fasce Orarie | C44: 24 | D44: 1121 | E44: 24 | F44: 5000 | G44: 31.12.90 | H44: Fasce Orarie | I44: Man | J44: Cartoncino. Manca CAB e numerazione | K44: - | L44: 700 | M44: 5 | N44: 0.6 | P44: Nuova | Q44: No | T44: =IF(P44='Menu tendina'!A$5,0,IF(P44='Menu tendina'!A$4,'3. SIP'!N44/2,IF(P44='Menu tendina'!A$3,'3. SIP'!N44,IF(P44='Menu tendina'!A$2,'3. SIP'!M44,0)))) -> 5
A45: 3. Ordinarie | B45: 1. Fasce Orarie | C45: 25 | D45: 1122 | E45: 25 | F45: 10000 | G45: 31.12.90 | H45: Fasce Orarie | I45: Man | J45: Cartoncino. Manca CAB e numerazione | K45: - | L45: 500 | M45: 5 | N45: 0.6 | P45: Nuova | Q45: Codici Urmet | T45: =IF(P45='Menu tendina'!A$5,0,IF(P45='Menu tendina'!A$4,'3. SIP'!N45/2,IF(P45='Menu tendina'!A$3,'3. SIP'!N45,IF(P45='Menu tendina'!A$2,'3. SIP'!M45,0)))) -> 5
A46: 3. Ordinarie | B46: 1. Fasce Orarie | C46: 26 | D46: 1124 | E46: 26 | F46: 5000 | G46: 31.12.90 | H46: Fasce Orarie | I46: Pos | J46: Senza numerazione | K46: - | L46: 750 | M46: 25 | N46: 1.5 | P46: Nuova | Q46: Codici regolari | T46: =IF(P46='Menu tendina'!A$5,0,IF(P46='Menu tendina'!A$4,'3. SIP'!N46/2,IF(P46='Menu tendina'!A$3,'3. SIP'!N46,IF(P46='Menu tendina'!A$2,'3. SIP'!M46,0)))) -> 25
A47: 3. Ordinarie | B47: 1. Fasce Orarie | C47: 27 | D47: 1125 | E47: 27 | F47: 10000 | G47: 31.12.90 | H47: Fasce Orarie | I47: Pos | J47: Senza numerazione | K47: - | L47: 600 | M47: 30 | N47: 1.5 | P47: Nuova | Q47: Codici Urmet | T47: =IF(P47='Menu tendina'!A$5,0,IF(P47='Menu tendina'!A$4,'3. SIP'!N47/2,IF(P47='Menu tendina'!A$3,'3. SIP'!N47,IF(P47='Menu tendina'!A$2,'3. SIP'!M47,0)))) -> 30
A48: 3. Ordinarie | B48: 1. Fasce Orarie | C48: 27A | D48: 5210 | E48: 27A | F48: 20000 | G48: 31.12.90 | H48: Fasce Orarie | I48: Man | J48: Senza numerazione | K48: Variante | L48: 100 | M48: 10 | N48: 6 | P48: Nuova | Q48: n/a | R48: n/a | T48: =IF(P48='Menu tendina'!A$5,0,IF(P48='Menu tendina'!A$4,'3. SIP'!N48/2,IF(P48='Menu tendina'!A$3,'3. SIP'!N48,IF(P48='Menu tendina'!A$2,'3. SIP'!M48,0)))) -> 10
A49: 3. Ordinarie | B49: 1. Fasce Orarie | C49: 27B | D49: 5211 | E49: 27B | F49: 30000 | G49: 31.12.90 | H49: Fasce Orarie | I49: Man | J49: Senza numerazione | K49: Variante | L49: 120 | M49: 10 | N49: 6 | P49: Nuova | Q49: n/a | R49: n/a | T49: =IF(P49='Menu tendina'!A$5,0,IF(P49='Menu tendina'!A$4,'3. SIP'!N49/2,IF(P49='Menu tendina'!A$3,'3. SIP'!N49,IF(P49='Menu tendina'!A$2,'3. SIP'!M49,0)))) -> 10
A50: 3. Ordinarie | B50: 1. Fasce Orarie | C50: 28 | D50: 1127 | E50: 28 | F50: 5000 | G50: 30.06.91 | H50: Fasce Orarie | I50: Pos | J50: CAB. Manca numerazione | K50: - | L50: 750 | M50: 15 | N50: 1.5 | P50: Nuova | Q50: Sì | R50: Non leggibile | T50: =IF(P50='Menu tendina'!A$5,0,IF(P50='Menu tendina'!A$4,'3. SIP'!N50/2,IF(P50='Menu tendina'!A$3,'3. SIP'!N50,IF(P50='Menu tendina'!A$2,'3. SIP'!M50,0)))) -> 15
A51: 3. Ordinarie | B51: 1. Fasce Orarie | C51: 29 | D51: 1128 | E51: 29 | F51: 10000 | G51: 30.06.91 | H51: Fasce Orarie | I51: Pos | J51: CAB. Manca numerazione | K51: - | L51: 600 | M51: 25 | N51: 1.5 | P51: Nuova | Q51: Codici Urmet | T51: =IF(P51='Menu tendina'!A$5,0,IF(P51='Menu tendina'!A$4,'3. SIP'!N51/2,IF(P51='Menu tendina'!A$3,'3. SIP'!N51,IF(P51='Menu tendina'!A$2,'3. SIP'!M51,0)))) -> 25
A52: 3. Ordinarie | B52: 1. Fasce Orarie | C52: 30 | D52: 1129 | E52: 30 | F52: 5000 | G52: 30.06.91 | H52: Fasce Orarie | I52: Pos | J52: CAB, numerazione | K52: - | L52: 1.180 | M52: 10 | N52: 0.4 | P52: Nuova | Q52: Codici Urmet | T52: =IF(P52='Menu tendina'!A$5,0,IF(P52='Menu tendina'!A$4,'3. SIP'!N52/2,IF(P52='Menu tendina'!A$3,'3. SIP'!N52,IF(P52='Menu tendina'!A$2,'3. SIP'!M52,0)))) -> 10
A53: 3. Ordinarie | B53: 1. Fasce Orarie | C53: 31 | D53: 1130 | E53: 31 | F53: 10000 | G53: 30.06.91 | H53: Fasce Orarie | I53: Pos | J53: CAB, numerazione | K53: - | L53: 800 | M53: 15 | N53: 0.5 | P53: Nuova | Q53: Codici regolari | T53: =IF(P53='Menu tendina'!A$5,0,IF(P53='Menu tendina'!A$4,'3. SIP'!N53/2,IF(P53='Menu tendina'!A$3,'3. SIP'!N53,IF(P53='Menu tendina'!A$2,'3. SIP'!M53,0)))) -> 15
A54: 3. Ordinarie | B54: 1. Fasce Orarie | C54: 32 | D54: 1131 | E54: 32 | F54: 5000 | G54: 31.12.91 | H54: Fasce Orarie | I54: Pik | J54: Banda grigia | K54: - | L54: 2.000 | M54: 20 | N54: 0.3 | P54: Nuova | Q54: Codici Urmet | T54: =IF(P54='Menu tendina'!A$5,0,IF(P54='Menu tendina'!A$4,'3. SIP'!N54/2,IF(P54='Menu tendina'!A$3,'3. SIP'!N54,IF(P54='Menu tendina'!A$2,'3. SIP'!M54,0)))) -> 20
A55: 3. Ordinarie | B55: 1. Fasce Orarie | C55: 33 | D55: 1132 | E55: 33 | F55: 10000 | G55: 31.12.91 | H55: Fasce Orarie | I55: Pik | J55: Banda grigia | K55: - | L55: 800 | M55: 25 | N55: 0.5 | P55: Nuova | Q55: Codici regolari | T55: =IF(P55='Menu tendina'!A$5,0,IF(P55='Menu tendina'!A$4,'3. SIP'!N55/2,IF(P55='Menu tendina'!A$3,'3. SIP'!N55,IF(P55='Menu tendina'!A$2,'3. SIP'!M55,0)))) -> 25
A56: 3. Ordinarie | B56: 1. Fasce Orarie | C56: 34 | D56: 1133 | E56: 34 | F56: 5000 | G56: 31.12.91 | H56: Fasce Orarie | I56: Pik | J56: CAB, numerazione | K56: - | L56: 5.200 | M56: 20 | N56: 0.3 | P56: Nuova | Q56: Codici regolari | T56: =IF(P56='Menu tendina'!A$5,0,IF(P56='Menu tendina'!A$4,'3. SIP'!N56/2,IF(P56='Menu tendina'!A$3,'3. SIP'!N56,IF(P56='Menu tendina'!A$2,'3. SIP'!M56,0)))) -> 20
A57: 3. Ordinarie | B57: 1. Fasce Orarie | C57: 35 | D57: 1134 | E57: 35 | F57: 10000 | G57: 31.12.91 | H57: Fasce Orarie | I57: Pik | J57: CAB, numerazione | K57: - | L57: 4.400 | M57: 6 | N57: 0.3 | P57: Nuova | Q57: Codici regolari | T57: =IF(P57='Menu tendina'!A$5,0,IF(P57='Menu tendina'!A$4,'3. SIP'!N57/2,IF(P57='Menu tendina'!A$3,'3. SIP'!N57,IF(P57='Menu tendina'!A$2,'3. SIP'!M57,0)))) -> 6
A58: 3. Ordinarie | B58: 1. Fasce Orarie | C58: 36 | D58: 1135 | E58: 36 | F58: 5000 | G58: 31.12.91 | H58: Fasce Orarie | I58: Man | J58: Cartoncino, banda grigia, CAB. Manca numerazione | K58: - | L58: 400 | M58: 5 | N58: 0.6 | P58: Nuova | Q58: Codici regolari | T58: =IF(P58='Menu tendina'!A$5,0,IF(P58='Menu tendina'!A$4,'3. SIP'!N58/2,IF(P58='Menu tendina'!A$3,'3. SIP'!N58,IF(P58='Menu tendina'!A$2,'3. SIP'!M58,0)))) -> 5
A59: 3. Ordinarie | B59: 1. Fasce Orarie | C59: 37 | D59: 1136 | E59: 37 | F59: 10000 | G59: 31.12.91 | H59: Fasce Orarie | I59: Man | J59: Cartoncino, banda grigia, CAB. Manca numerazione | K59: - | L59: 200 | M59: 6 | N59: 0.7 | P59: Nuova | Q59: Codici Urmet | T59: =IF(P59='Menu tendina'!A$5,0,IF(P59='Menu tendina'!A$4,'3. SIP'!N59/2,IF(P59='Menu tendina'!A$3,'3. SIP'!N59,IF(P59='Menu tendina'!A$2,'3. SIP'!M59,0)))) -> 6
A60: 3. Ordinarie | B60: 1. Fasce Orarie | C60: 38 | D60: 1137 | E60: 38 | F60: 10000 | G60: 31.12.91 | H60: Fasce Orarie | I60: Man | J60: Polipropilene, filigrana, CAB, numerazione. | K60: - | L60: 1.800 | M60: 8 | N60: 0.4 | P60: Nuova | Q60: Codici regolari | T60: =IF(P60='Menu tendina'!A$5,0,IF(P60='Menu tendina'!A$4,'3. SIP'!N60/2,IF(P60='Menu tendina'!A$3,'3. SIP'!N60,IF(P60='Menu tendina'!A$2,'3. SIP'!M60,0)))) -> 8
A61: 3. Ordinarie | B61: 1. Fasce Orarie | C61: 39 | D61: 1138 | E61: 39 | F61: 5000 | G61: 31.12.91 | H61: Fasce Orarie | I61: Tep | J61: Filigrana in rilievo | K61: - | L61: 900 | M61: 15 | N61: 0.5 | P61: Nuova | Q61: Codici regolari | T61: =IF(P61='Menu tendina'!A$5,0,IF(P61='Menu tendina'!A$4,'3. SIP'!N61/2,IF(P61='Menu tendina'!A$3,'3. SIP'!N61,IF(P61='Menu tendina'!A$2,'3. SIP'!M61,0)))) -> 15
A62: 3. Ordinarie | B62: 1. Fasce Orarie | C62: 39A | D62: 1138a | E62: - | F62: 5000 | G62: 31.12.91 | H62: Fasce Orarie | I62: Tep | J62: Filigrana non in rilievo | K62: - | L62: - | M62: 9 | N62: 1 | P62: Nuova | Q62: Codici Urmet | T62: =IF(P62='Menu tendina'!A$5,0,IF(P62='Menu tendina'!A$4,'3. SIP'!N62/2,IF(P62='Menu tendina'!A$3,'3. SIP'!N62,IF(P62='Menu tendina'!A$2,'3. SIP'!M62,0)))) -> 9
A63: 3. Ordinarie | B63: 1. Fasce Orarie | C63: 40 | D63: 1139 | E63: 40 | F63: 10000 | G63: 31.12.91 | H63: Fasce Orarie | I63: Tep | J63: Filigrana in rilievo | K63: - | L63: 1.000 | M63: 20 | N63: 0.5 | P63: Nuova | Q63: Codici Urmet | T63: =IF(P63='Menu tendina'!A$5,0,IF(P63='Menu tendina'!A$4,'3. SIP'!N63/2,IF(P63='Menu tendina'!A$3,'3. SIP'!N63,IF(P63='Menu tendina'!A$2,'3. SIP'!M63,0)))) -> 20
A64: 3. Ordinarie | B64: 1. Fasce Orarie | C64: 40A | D64: 1139a | E64: - | F64: 10000 | G64: 31.12.91 | H64: Fasce Orarie | I64: Tep | J64: Filigrana non in rilievo | K64: - | L64: - | M64: 8 | N64: 1 | P64: Nuova | Q64: Codici Urmet | T64: =IF(P64='Menu tendina'!A$5,0,IF(P64='Menu tendina'!A$4,'3. SIP'!N64/2,IF(P64='Menu tendina'!A$3,'3. SIP'!N64,IF(P64='Menu tendina'!A$2,'3. SIP'!M64,0)))) -> 8
A65: 3. Ordinarie | B65: 1. Fasce Orarie | C65: 41 | D65: 1144 | E65: 41 | F65: 5000 | G65: 30.06.92 | H65: Fasce Orarie | I65: Pik | K65: - | L65: 9.200 | M65: 3 | N65: 0.2 | P65: Nuova | Q65: Codici Urmet | T65: =IF(P65='Menu tendina'!A$5,0,IF(P65='Menu tendina'!A$4,'3. SIP'!N65/2,IF(P65='Menu tendina'!A$3,'3. SIP'!N65,IF(P65='Menu tendina'!A$2,'3. SIP'!M65,0)))) -> 3
A66: 3. Ordinarie | B66: 1. Fasce Orarie | C66: 42 | D66: 1145 | E66: 42 | F66: 10000 | G66: 30.06.92 | H66: Fasce Orarie | I66: Pik | K66: - | L66: 4.000 | M66: 4 | N66: 0.4 | P66: Nuova | Q66: Codici Urmet | T66: =IF(P66='Menu tendina'!A$5,0,IF(P66='Menu tendina'!A$4,'3. SIP'!N66/2,IF(P66='Menu tendina'!A$3,'3. SIP'!N66,IF(P66='Menu tendina'!A$2,'3. SIP'!M66,0)))) -> 4
A67: 3. Ordinarie | B67: 1. Fasce Orarie | C67: 43 | D67: 1146 | E67: 43 | F67: 5000 | G67: 30.06.92 | H67: Fasce Orarie | I67: Man | J67: Manca lo zero del mese | K67: - | L67: 10.000 | M67: 5 | N67: 0.2 | P67: Nuova | Q67: Codici Urmet | R67: Carica da 30.000 | T67: =IF(P67='Menu tendina'!A$5,0,IF(P67='Menu tendina'!A$4,'3. SIP'!N67/2,IF(P67='Menu tendina'!A$3,'3. SIP'!N67,IF(P67='Menu tendina'!A$2,'3. SIP'!M67,0)))) -> 5
A68: 3. Ordinarie | B68: 1. Fasce Orarie | C68: 44 | D68: 1147 | E68: 44 | F68: 10000 | G68: 30.06.92 | H68: Fasce Orarie | I68: Man | J68: Manca lo zero del mese | K68: - | L68: 4.200 | M68: 8 | N68: 0.4 | P68: Nuova | Q68: Codici regolari | T68: =IF(P68='Menu tendina'!A$5,0,IF(P68='Menu tendina'!A$4,'3. SIP'!N68/2,IF(P68='Menu tendina'!A$3,'3. SIP'!N68,IF(P68='Menu tendina'!A$2,'3. SIP'!M68,0)))) -> 8
A69: 3. Ordinarie | B69: 1. Fasce Orarie | C69: 45 | D69: 1148 | E69: 45 | F69: 5000 | G69: 30.06.92 | H69: Fasce Orarie | I69: Tep | K69: - | L69: 4.600 | M69: 20 | N69: 0.4 | P69: Nuova | Q69: Codici Urmet | T69: =IF(P69='Menu tendina'!A$5,0,IF(P69='Menu tendina'!A$4,'3. SIP'!N69/2,IF(P69='Menu tendina'!A$3,'3. SIP'!N69,IF(P69='Menu tendina'!A$2,'3. SIP'!M69,0)))) -> 20
A70: 3. Ordinarie | B70: 1. Fasce Orarie | C70: 46 | D70: 1149 | E70: 46 | F70: 10000 | G70: 30.06.92 | H70: Fasce Orarie | I70: Tep | K70: - | L70: 1.200 | M70: 10 | N70: 0.5 | P70: Nuova | Q70: Codici Urmet | T70: =IF(P70='Menu tendina'!A$5,0,IF(P70='Menu tendina'!A$4,'3. SIP'!N70/2,IF(P70='Menu tendina'!A$3,'3. SIP'!N70,IF(P70='Menu tendina'!A$2,'3. SIP'!M70,0)))) -> 10
A71: 3. Ordinarie | B71: 1. Fasce Orarie | C71: 47 | D71: 1150 | E71: 47 | F71: 10000 | G71: 31.12.92 | H71: Fasce Orarie | I71: Pik | J71: Logo Pikappa sul fronte a destra | K71: - | L71: 800 | M71: 20 | N71: 0.6 | P71: Nuova | Q71: Codici Urmet | T71: =IF(P71='Menu tendina'!A$5,0,IF(P71='Menu tendina'!A$4,'3. SIP'!N71/2,IF(P71='Menu tendina'!A$3,'3. SIP'!N71,IF(P71='Menu tendina'!A$2,'3. SIP'!M71,0)))) -> 20
A72: 3. Ordinarie | B72: 1. Fasce Orarie | C72: 48 | D72: 1151 | E72: 48 | F72: 5000 | G72: 31.12.92 | H72: Fasce Orarie | I72: Pik | J72: Logo Pikappa sul retro | K72: - | L72: 5.700 | M72: 12 | N72: 0.3 | P72: Nuova | Q72: Codici Urmet | T72: =IF(P72='Menu tendina'!A$5,0,IF(P72='Menu tendina'!A$4,'3. SIP'!N72/2,IF(P72='Menu tendina'!A$3,'3. SIP'!N72,IF(P72='Menu tendina'!A$2,'3. SIP'!M72,0)))) -> 12
A73: 3. Ordinarie | B73: 1. Fasce Orarie | C73: 49 | D73: 1152 | E73: 49 | F73: 10000 | G73: 31.12.92 | H73: Fasce Orarie | I73: Pik | J73: Logo Pikappa sul retro | K73: - | L73: 2.700 | M73: 15 | N73: 0.4 | P73: Nuova | Q73: Codici regolari | T73: =IF(P73='Menu tendina'!A$5,0,IF(P73='Menu tendina'!A$4,'3. SIP'!N73/2,IF(P73='Menu tendina'!A$3,'3. SIP'!N73,IF(P73='Menu tendina'!A$2,'3. SIP'!M73,0)))) -> 15
A74: 3. Ordinarie | B74: 1. Fasce Orarie | C74: 50 | D74: 1153 | E74: 50 | F74: 5000 | G74: 31.12.92 | H74: Fasce Orarie | I74: Pik | J74: Aggiunta scritta "La carta non è rimborsabile" | K74: - | L74: 4.600 | M74: 20 | N74: 0.4 | P74: Nuova | Q74: Codici Urmet | T74: =IF(P74='Menu tendina'!A$5,0,IF(P74='Menu tendina'!A$4,'3. SIP'!N74/2,IF(P74='Menu tendina'!A$3,'3. SIP'!N74,IF(P74='Menu tendina'!A$2,'3. SIP'!M74,0)))) -> 20
A75: 3. Ordinarie | B75: 1. Fasce Orarie | C75: 51 | D75: 1154 | E75: 51 | F75: 10000 | G75: 31.12.92 | H75: Fasce Orarie | I75: Pik | J75: Aggiunta scritta "La carta non è rimborsabile" | K75: - | L75: 2.100 | M75: 25 | N75: 0.6 | P75: Nuova | Q75: Sì | R75: Non leggibile | T75: =IF(P75='Menu tendina'!A$5,0,IF(P75='Menu tendina'!A$4,'3. SIP'!N75/2,IF(P75='Menu tendina'!A$3,'3. SIP'!N75,IF(P75='Menu tendina'!A$2,'3. SIP'!M75,0)))) -> 25
A76: 3. Ordinarie | B76: 1. Fasce Orarie | C76: 52 | D76: 1155 | E76: 52 | F76: 5000 | G76: 31.12.92 | H76: Fasce Orarie | I76: Man | J76: Logo Mantegazza lungo (17mm) | K76: - | L76: 11.400 | M76: 2.5 | N76: 0.2 | P76: Nuova | Q76: Codici regolari | T76: =IF(P76='Menu tendina'!A$5,0,IF(P76='Menu tendina'!A$4,'3. SIP'!N76/2,IF(P76='Menu tendina'!A$3,'3. SIP'!N76,IF(P76='Menu tendina'!A$2,'3. SIP'!M76,0)))) -> 2.5
A77: 3. Ordinarie | B77: 1. Fasce Orarie | C77: 52A | D77: 1155A | E77: 52A | F77: 5000 | G77: 31.12.92 | H77: Fasce Orarie | I77: Man | J77: Logo Mantegazza corto (15mm) | K77: - | L77: - | M77: 25 | N77: 1 | P77: Usata | T77: =IF(P77='Menu tendina'!A$5,0,IF(P77='Menu tendina'!A$4,'3. SIP'!N77/2,IF(P77='Menu tendina'!A$3,'3. SIP'!N77,IF(P77='Menu tendina'!A$2,'3. SIP'!M77,0)))) -> 1
A78: 3. Ordinarie | B78: 1. Fasce Orarie | C78: 53 | D78: 1156 | E78: 53 | F78: 10000 | G78: 31.12.92 | H78: Fasce Orarie | I78: Man | J78: Logo Mantegazza lungo (17mm) | K78: - | L78: 5.400 | M78: 10 | N78: 0.4 | P78: Nuova | Q78: Sì | R78: Non leggibile | T78: =IF(P78='Menu tendina'!A$5,0,IF(P78='Menu tendina'!A$4,'3. SIP'!N78/2,IF(P78='Menu tendina'!A$3,'3. SIP'!N78,IF(P78='Menu tendina'!A$2,'3. SIP'!M78,0)))) -> 10
A79: 3. Ordinarie | B79: 1. Fasce Orarie | C79: 53A | D79: 1156A | E79: 53A | F79: 10000 | G79: 31.12.92 | H79: Fasce Orarie | I79: Man | J79: Logo Mantegazza corto (15mm) | K79: - | L79: - | M79: 30 | N79: 1.3 | P79: Usata | T79: =IF(P79='Menu tendina'!A$5,0,IF(P79='Menu tendina'!A$4,'3. SIP'!N79/2,IF(P79='Menu tendina'!A$3,'3. SIP'!N79,IF(P79='Menu tendina'!A$2,'3. SIP'!M79,0)))) -> 1.3
A80: 3. Ordinarie | B80: 1. Fasce Orarie | C80: 54 | D80: 1157 | E80: 54 | F80: 5000 | G80: 31.12.92 | H80: Fasce Orarie | I80: Man | J80: Aggiunta scritta "La carta non è rimborsabile" | K80: - | L80: 2.200 | M80: 20 | N80: 0.5 | P80: Nuova | Q80: Codici Urmet | T80: =IF(P80='Menu tendina'!A$5,0,IF(P80='Menu tendina'!A$4,'3. SIP'!N80/2,IF(P80='Menu tendina'!A$3,'3. SIP'!N80,IF(P80='Menu tendina'!A$2,'3. SIP'!M80,0)))) -> 20
A81: 3. Ordinarie | B81: 1. Fasce Orarie | C81: 55 | D81: 1158 | E81: 55 | F81: 10000 | G81: 31.12.92 | H81: Fasce Orarie - Logo Mantegazza da 17mm | I81: Man | J81: Aggiunta scritta "La carta non è rimborsabile". Logo Mantegazza lungo (17mm) | K81: - | L81: 1.400 | M81: 25 | N81: 0.6 | P81: Nuova | Q81: Codici Urmet | T81: =IF(P81='Menu tendina'!A$5,0,IF(P81='Menu tendina'!A$4,'3. SIP'!N81/2,IF(P81='Menu tendina'!A$3,'3. SIP'!N81,IF(P81='Menu tendina'!A$2,'3. SIP'!M81,0)))) -> 25
A82: 3. Ordinarie | B82: 1. Fasce Orarie | C82: 55A | D82: 1158A | E82: 55A | F82: 10000 | G82: 31.12.92 | H82: Fasce Orarie - Logo Mantegazza da 15mm | I82: Man | J82: Aggiunta scritta "La carta non è rimborsabile". Logo Mantegazza corto (15mm) | K82: - | L82: 600 | M82: 35 | N82: 1 | P82: Usata | T82: =IF(P82='Menu tendina'!A$5,0,IF(P82='Menu tendina'!A$4,'3. SIP'!N82/2,IF(P82='Menu tendina'!A$3,'3. SIP'!N82,IF(P82='Menu tendina'!A$2,'3. SIP'!M82,0)))) -> 1
A83: 3. Ordinarie | B83: 1. Fasce Orarie | C83: 56 | D83: 1164 | E83: 56 | F83: 10000 | G83: 31.12.92 | H83: Fasce Orarie - PVC Lucido | I83: Tep | J83: In PVC lucido | K83: - | L83: 1.000 | M83: 50 | N83: 0.8 | P83: Nuova | T83: =IF(P83='Menu tendina'!A$5,0,IF(P83='Menu tendina'!A$4,'3. SIP'!N83/2,IF(P83='Menu tendina'!A$3,'3. SIP'!N83,IF(P83='Menu tendina'!A$2,'3. SIP'!M83,0)))) -> 50
A84: 3. Ordinarie | B84: 1. Fasce Orarie | C84: 57 | D84: 1163 | E84: 57 | F84: 5000 | G84: 31.12.92 | H84: Fasce Orarie | I84: Tep | J84: In PVC opaco | K84: - | L84: 3.200 | M84: 15 | N84: 0.5 | P84: Nuova | Q84: Codici regolari | T84: =IF(P84='Menu tendina'!A$5,0,IF(P84='Menu tendina'!A$4,'3. SIP'!N84/2,IF(P84='Menu tendina'!A$3,'3. SIP'!N84,IF(P84='Menu tendina'!A$2,'3. SIP'!M84,0)))) -> 15
A85: 3. Ordinarie | B85: 1. Fasce Orarie | C85: 58 | D85: 1164 | E85: 58 | F85: 10000 | G85: 31.12.92 | H85: Fasce Orarie | I85: Tep | J85: In PVC opaco | K85: - | L85: 1.200 | M85: 30 | N85: 0.8 | P85: Nuova | Q85: Codici Urmet | T85: =IF(P85='Menu tendina'!A$5,0,IF(P85='Menu tendina'!A$4,'3. SIP'!N85/2,IF(P85='Menu tendina'!A$3,'3. SIP'!N85,IF(P85='Menu tendina'!A$2,'3. SIP'!M85,0)))) -> 30
A86: 3. Ordinarie | B86: 1. Fasce Orarie | C86: 59 | D86: 1165 | E86: 59 | F86: 5000 | G86: 31.12.92 | H86: Fasce Orarie | I86: Tep | J86: Aggiunta scritta "La carta non è rimborsabile" | K86: - | L86: 900 | M86: 15 | N86: 1 | P86: Nuova | Q86: Codici Urmet | T86: =IF(P86='Menu tendina'!A$5,0,IF(P86='Menu tendina'!A$4,'3. SIP'!N86/2,IF(P86='Menu tendina'!A$3,'3. SIP'!N86,IF(P86='Menu tendina'!A$2,'3. SIP'!M86,0)))) -> 15
A87: 3. Ordinarie | B87: 1. Fasce Orarie | C87: 60 | D87: 1166 | E87: 60 | F87: 10000 | G87: 31.12.92 | H87: Fasce Orarie | I87: Tep | J87: Aggiunta scritta "La carta non è rimborsabile" | K87: - | L87: 500 | M87: 50 | N87: 2 | P87: Nuova | Q87: Codici Urmet | T87: =IF(P87='Menu tendina'!A$5,0,IF(P87='Menu tendina'!A$4,'3. SIP'!N87/2,IF(P87='Menu tendina'!A$3,'3. SIP'!N87,IF(P87='Menu tendina'!A$2,'3. SIP'!M87,0)))) -> 50
A88: 4. Pubbliche Figurate | B88: 2. SIP | C88: 61 | D88: 2140 | E88: 1 | F88: 10000 | G88: 30.06.91 | H88: Festo nell'automazione industriale | I88: Tep | K88: - | L88: 65 | M88: 60 | N88: 25 | P88: Nuova | Q88: Codici regolari | T88: =IF(P88='Menu tendina'!A$5,0,IF(P88='Menu tendina'!A$4,'3. SIP'!N88/2,IF(P88='Menu tendina'!A$3,'3. SIP'!N88,IF(P88='Menu tendina'!A$2,'3. SIP'!M88,0)))) -> 60
A89: 4. Pubbliche Figurate | B89: 2. SIP | C89: 61A | D89: - | E89: - | F89: 10000 | G89: 30.06.91 | H89: Festo nell'automazione industriale | I89: Tep | J89: Senza filigrana | K89: Variante | L89: - | M89: P.A.R. | N89: 200 | P89: Manca | T89: =IF(P89='Menu tendina'!A$5,0,IF(P89='Menu tendina'!A$4,'3. SIP'!N89/2,IF(P89='Menu tendina'!A$3,'3. SIP'!N89,IF(P89='Menu tendina'!A$2,'3. SIP'!M89,0)))) -> 0
A90: 4. Pubbliche Figurate | B90: 2. SIP | C90: 62 | D90: 2141 | E90: 2 | F90: 5000 | G90: 31.12.91 | H90: Italia '90 - IP con l'Italia | I90: Man | K90: - | L90: 500 | M90: 5 | N90: 1 | P90: Nuova | Q90: Codici Urmet | T90: =IF(P90='Menu tendina'!A$5,0,IF(P90='Menu tendina'!A$4,'3. SIP'!N90/2,IF(P90='Menu tendina'!A$3,'3. SIP'!N90,IF(P90='Menu tendina'!A$2,'3. SIP'!M90,0)))) -> 5
A91: 4. Pubbliche Figurate | B91: 2. SIP | C91: 63 | D91: 2142 | E91: 3 | F91: 10000 | G91: 31.12.91 | H91: Italia '90 - IP con l'Italia | I91: Man | K91: - | L91: 500 | M91: 5 | N91: 1 | P91: Nuova | Q91: Codici Urmet | T91: =IF(P91='Menu tendina'!A$5,0,IF(P91='Menu tendina'!A$4,'3. SIP'!N91/2,IF(P91='Menu tendina'!A$3,'3. SIP'!N91,IF(P91='Menu tendina'!A$2,'3. SIP'!M91,0)))) -> 5
A92: 4. Pubbliche Figurate | B92: 2. SIP | C92: 64 | D92: 2143 | E92: 4 | F92: 5000 | G92: 30.6.92 | H92: Italia '90 - IP con l'Italia | I92: Man | K92: - | L92: 2150 | M92: 2 | N92: 0.5 | P92: Nuova | Q92: Codici Urmet | T92: =IF(P92='Menu tendina'!A$5,0,IF(P92='Menu tendina'!A$4,'3. SIP'!N92/2,IF(P92='Menu tendina'!A$3,'3. SIP'!N92,IF(P92='Menu tendina'!A$2,'3. SIP'!M92,0)))) -> 2
A93: 4. Pubbliche Figurate | B93: 2. SIP | C93: 65 | D93: 2144 | E93: 5 | F93: 5000 | G93: 31.12.91 | H93: Italia '90 - Stadio Bari | I93: Man | K93: - | L93: 150 | M93: 15 | N93: 5 | P93: Nuova | Q93: Codici regolari | R93: 01/05/205/65028 - 04/25 | T93: =IF(P93='Menu tendina'!A$5,0,IF(P93='Menu tendina'!A$4,'3. SIP'!N93/2,IF(P93='Menu tendina'!A$3,'3. SIP'!N93,IF(P93='Menu tendina'!A$2,'3. SIP'!M93,0)))) -> 15
A94: 4. Pubbliche Figurate | B94: 2. SIP | C94: 66 | D94: 2145 | E94: 6 | F94: 5000 | G94: 31.12.91 | H94: Italia '90 - Stadio Bologna | I94: Man | K94: - | L94: 150 | M94: 15 | N94: 5 | P94: Nuova | Q94: Codici regolari | R94: 01/05/151/53782 - 04/25 | T94: =IF(P94='Menu tendina'!A$5,0,IF(P94='Menu tendina'!A$4,'3. SIP'!N94/2,IF(P94='Menu tendina'!A$3,'3. SIP'!N94,IF(P94='Menu tendina'!A$2,'3. SIP'!M94,0)))) -> 15
A95: 4. Pubbliche Figurate | B95: 2. SIP | C95: 67 | D95: 2146 | E95: 7 | F95: 5000 | G95: 31.12.91 | H95: Italia '90 - Stadio Cagliari | I95: Man | K95: - | L95: 150 | M95: 15 | N95: 5 | P95: Nuova | Q95: No | T95: =IF(P95='Menu tendina'!A$5,0,IF(P95='Menu tendina'!A$4,'3. SIP'!N95/2,IF(P95='Menu tendina'!A$3,'3. SIP'!N95,IF(P95='Menu tendina'!A$2,'3. SIP'!M95,0)))) -> 15
A96: 4. Pubbliche Figurate | B96: 2. SIP | C96: 68 | D96: 2147 | E96: 8 | F96: 5000 | G96: 31.12.91 | H96: Italia '90 - Stadio Firenze | I96: Man | K96: - | L96: 150 | M96: 15 | N96: 5 | P96: Nuova | Q96: Sì | R96: Non leggibile | T96: =IF(P96='Menu tendina'!A$5,0,IF(P96='Menu tendina'!A$4,'3. SIP'!N96/2,IF(P96='Menu tendina'!A$3,'3. SIP'!N96,IF(P96='Menu tendina'!A$2,'3. SIP'!M96,0)))) -> 15
A97: 4. Pubbliche Figurate | B97: 2. SIP | C97: 69 | D97: 2148 | E97: 9 | F97: 5000 | G97: 31.12.91 | H97: Italia '90 - Stadio Genova | I97: Man | K97: - | L97: 150 | M97: 15 | N97: 5 | P97: Nuova | Q97: Codici regolari | R97: 01/05/218/30789 - 04/25 | T97: =IF(P97='Menu tendina'!A$5,0,IF(P97='Menu tendina'!A$4,'3. SIP'!N97/2,IF(P97='Menu tendina'!A$3,'3. SIP'!N97,IF(P97='Menu tendina'!A$2,'3. SIP'!M97,0)))) -> 15
A98: 4. Pubbliche Figurate | B98: 2. SIP | C98: 70 | D98: 2149 | E98: 10 | F98: 5000 | G98: 31.12.91 | H98: Italia '90 - Stadio Milano | I98: Man | K98: - | L98: 150 | M98: 15 | N98: 5 | P98: Nuova | Q98: Sì | R98: Non leggibile | T98: =IF(P98='Menu tendina'!A$5,0,IF(P98='Menu tendina'!A$4,'3. SIP'!N98/2,IF(P98='Menu tendina'!A$3,'3. SIP'!N98,IF(P98='Menu tendina'!A$2,'3. SIP'!M98,0)))) -> 15
A99: 4. Pubbliche Figurate | B99: 2. SIP | C99: 71 | D99: 2150 | E99: 11 | F99: 5000 | G99: 31.12.91 | H99: Italia '90 - Stadio Napoli | I99: Man | K99: - | L99: 150 | M99: 15 | N99: 5 | P99: Nuova | Q99: Codici regolari | R99: 01/05/206/65056 - 04/25 | T99: =IF(P99='Menu tendina'!A$5,0,IF(P99='Menu tendina'!A$4,'3. SIP'!N99/2,IF(P99='Menu tendina'!A$3,'3. SIP'!N99,IF(P99='Menu tendina'!A$2,'3. SIP'!M99,0)))) -> 15
A100: 4. Pubbliche Figurate | B100: 2. SIP | C100: 72 | D100: 2151 | E100: 12 | F100: 5000 | G100: 31.12.91 | H100: Italia '90 - Stadio Palermo | I100: Man | K100: - | L100: 150 | M100: 15 | N100: 5 | P100: Nuova | Q100: Codici regolari | R100: 01/05/218/23081 - 04/25 | T100: =IF(P100='Menu tendina'!A$5,0,IF(P100='Menu tendina'!A$4,'3. SIP'!N100/2,IF(P100='Menu tendina'!A$3,'3. SIP'!N100,IF(P100='Menu tendina'!A$2,'3. SIP'!M100,0)))) -> 15
...

Sheet 4. Telecom lire
A1: Genere | B1: Sottogenere | C1: N.Golden | D1: N. C&C | E1: N. AG | F1: Taglio | G1: Scadenza | H1: Titolo | I1: Pr. | J1: Note | K1: Var | L1: Tiratura | M1: Val 2025 Nuova | N1: Val 2025 Usata | P1: Presente | Q1: Magnetizzazione | S1: Valore collezione
A2: 4. Pubbliche Figurate | B2: 3. Telecom lire | C2: 396 | D2: 2452 | E2: 1 | F2: 5000 | G2: 31.12.96 | H2: Sport - Ginnastica | I2: Man | K2: - | L2: 30 | M2: 2.5 | N2: 2.5 | P2: Nuova | S2: =IF(P2='Menu tendina'!A$5,0,IF(P2='Menu tendina'!A$4,'4. Telecom lire'!N2/2,IF(P2='Menu tendina'!A$3,'4. Telecom lire'!N2,IF(P2='Menu tendina'!A$2,'4. Telecom lire'!M2,0)))) -> 2.5
A3: 4. Pubbliche Figurate | B3: 3. Telecom lire | C3: 397 | D3: 2453 | E3: 2 | F3: 10000 | G3: 31.12.96 | H3: Sport - Sci | I3: Man | K3: - | L3: 30 | M3: 2.5 | N3: 2 | P3: Nuova | S3: =IF(P3='Menu tendina'!A$5,0,IF(P3='Menu tendina'!A$4,'4. Telecom lire'!N3/2,IF(P3='Menu tendina'!A$3,'4. Telecom lire'!N3,IF(P3='Menu tendina'!A$2,'4. Telecom lire'!M3,0)))) -> 2.5
A4: 4. Pubbliche Figurate | B4: 3. Telecom lire | C4: 398 | D4: 2454 | E4: 3 | F4: 5000 | G4: 31.12.96 | H4: Sport - Equitazione | I4: Man | K4: - | L4: 30 | M4: 2.5 | N4: 2 | P4: Nuova | S4: =IF(P4='Menu tendina'!A$5,0,IF(P4='Menu tendina'!A$4,'4. Telecom lire'!N4/2,IF(P4='Menu tendina'!A$3,'4. Telecom lire'!N4,IF(P4='Menu tendina'!A$2,'4. Telecom lire'!M4,0)))) -> 2.5
A5: 4. Pubbliche Figurate | B5: 3. Telecom lire | C5: 399 | D5: 2455 | E5: 4 | F5: 10000 | G5: 31.12.96 | H5: Sport - Calcio | I5: Man | K5: - | L5: 30 | M5: 2.5 | N5: 2 | P5: Nuova | S5: =IF(P5='Menu tendina'!A$5,0,IF(P5='Menu tendina'!A$4,'4. Telecom lire'!N5/2,IF(P5='Menu tendina'!A$3,'4. Telecom lire'!N5,IF(P5='Menu tendina'!A$2,'4. Telecom lire'!M5,0)))) -> 2.5
A6: 4. Pubbliche Figurate | B6: 3. Telecom lire | C6: 400 | D6: 2456 | E6: 5 | F6: 5000 | G6: 31.12.96 | H6: Sport - Motociclismo | I6: Man | K6: - | L6: 30 | M6: 2.5 | N6: 2 | P6: Nuova | S6: =IF(P6='Menu tendina'!A$5,0,IF(P6='Menu tendina'!A$4,'4. Telecom lire'!N6/2,IF(P6='Menu tendina'!A$3,'4. Telecom lire'!N6,IF(P6='Menu tendina'!A$2,'4. Telecom lire'!M6,0)))) -> 2.5
A7: 4. Pubbliche Figurate | B7: 3. Telecom lire | C7: 401 | D7: 2457 | E7: 6 | F7: 10000 | G7: 31.12.96 | H7: Sport - Ciclismo | I7: Man | K7: - | L7: 30 | M7: 2.5 | N7: 2 | P7: Nuova | S7: =IF(P7='Menu tendina'!A$5,0,IF(P7='Menu tendina'!A$4,'4. Telecom lire'!N7/2,IF(P7='Menu tendina'!A$3,'4. Telecom lire'!N7,IF(P7='Menu tendina'!A$2,'4. Telecom lire'!M7,0)))) -> 2.5
A8: 4. Pubbliche Figurate | B8: 3. Telecom lire | C8: 402 | D8: 2458 | E8: 7 | F8: 5000 | G8: 31.12.96 | H8: Sport - Pallanuoto | I8: Man | K8: - | L8: 30 | M8: 2.5 | N8: 2 | P8: Nuova | S8: =IF(P8='Menu tendina'!A$5,0,IF(P8='Menu tendina'!A$4,'4. Telecom lire'!N8/2,IF(P8='Menu tendina'!A$3,'4. Telecom lire'!N8,IF(P8='Menu tendina'!A$2,'4. Telecom lire'!M8,0)))) -> 2.5
A9: 4. Pubbliche Figurate | B9: 3. Telecom lire | C9: 403 | D9: 2459 | E9: 8 | F9: 10000 | G9: 31.12.96 | H9: Sport - Canotaggio | I9: Man | K9: - | L9: 30 | M9: 2.5 | N9: 2 | P9: Nuova | S9: =IF(P9='Menu tendina'!A$5,0,IF(P9='Menu tendina'!A$4,'4. Telecom lire'!N9/2,IF(P9='Menu tendina'!A$3,'4. Telecom lire'!N9,IF(P9='Menu tendina'!A$2,'4. Telecom lire'!M9,0)))) -> 2.5
A10: 4. Pubbliche Figurate | B10: 3. Telecom lire | C10: 404 | D10: 2442 | E10: 17 | F10: 5000 | G10: 31.12.96 | H10: R2 - Avviso di chiamata | I10: Man | K10: - | L10: 2035 | M10: 3 | N10: 0.2 | P10: Nuova | S10: =IF(P10='Menu tendina'!A$5,0,IF(P10='Menu tendina'!A$4,'4. Telecom lire'!N10/2,IF(P10='Menu tendina'!A$3,'4. Telecom lire'!N10,IF(P10='Menu tendina'!A$2,'4. Telecom lire'!M10,0)))) -> 3
A11: 4. Pubbliche Figurate | B11: 3. Telecom lire | C11: 405 | D11: 2443 | E11: 18 | F11: 10000 | G11: 31.12.96 | H11: R2 - Avviso di chiamata | I11: Man | K11: - | L11: 4000 | M11: 1 | N11: 0.2 | P11: Nuova | S11: =IF(P11='Menu tendina'!A$5,0,IF(P11='Menu tendina'!A$4,'4. Telecom lire'!N11/2,IF(P11='Menu tendina'!A$3,'4. Telecom lire'!N11,IF(P11='Menu tendina'!A$2,'4. Telecom lire'!M11,0)))) -> 1
A12: 4. Pubbliche Figurate | B12: 3. Telecom lire | C12: 406 | D12: 2444 | E12: 19 | F12: 5000 | G12: 31.12.96 | H12: R2 - Avviso di chiamata | I12: Tec | K12: - | L12: 2500 | M12: 1 | N12: 0.2 | P12: Nuova | S12: =IF(P12='Menu tendina'!A$5,0,IF(P12='Menu tendina'!A$4,'4. Telecom lire'!N12/2,IF(P12='Menu tendina'!A$3,'4. Telecom lire'!N12,IF(P12='Menu tendina'!A$2,'4. Telecom lire'!M12,0)))) -> 1
A13: 4. Pubbliche Figurate | B13: 3. Telecom lire | C13: 407 | D13: 2445 | E13: 20 | F13: 10000 | G13: 31.12.96 | H13: R2 - Avviso di chiamata | I13: Tec | K13: - | L13: 2500 | M13: 5 | N13: 0.2 | P13: Nuova | S13: =IF(P13='Menu tendina'!A$5,0,IF(P13='Menu tendina'!A$4,'4. Telecom lire'!N13/2,IF(P13='Menu tendina'!A$3,'4. Telecom lire'!N13,IF(P13='Menu tendina'!A$2,'4. Telecom lire'!M13,0)))) -> 5
... A82: 4. Pubbliche Figurate | B82: 3. Telecom lire | C82: 476 | D82: 2530 | E82: 81 | F82: 5000 | G82: 30.06.97 | H82: 9° Convegno Città di Piacenza | I82: Man | K82: - | L82: 30 | M82: 1.5 | N82: 1 | P82: Nuova | S82: =IF(P82='Menu tendina'!A$5,0,IF(P82='Menu tendina'!A$4,'4. Telecom lire'!N82/2,IF(P82='Menu tendina'!A$3,'4. Telecom lire'!N82,IF(P82='Menu tendina'!A$2,'4. Telecom lire'!M82,0)))) -> 1.5
A83: 4. Pubbliche Figurate | B83: 3. Telecom lire | C83: 477 | D83: 2531 | E83: 84 | F83: 5000 | G83: 30.06.97 | H83: Telefono pubblico | I83: Man | J83: Numerica | K83: - | L83: 18713 | M83: 1 | N83: 0.2 | P83: Nuova | S83: =IF(P83='Menu tendina'!A$5,0,IF(P83='Menu tendina'!A$4,'4. Telecom lire'!N83/2,IF(P83='Menu tendina'!A$3,'4. Telecom lire'!N83,IF(P83='Menu tendina'!A$2,'4. Telecom lire'!M83,0)))) -> 1
A84: 4. Pubbliche Figurate | B84: 3. Telecom lire | C84: 477A | D84: 2531A | E84: 84A | F84: 5000 | G84: 30.06.97 | H84: Telefono pubblico | I84: Man | J84: Alfanumerica | K84: Variante | L84: - | M84: 1.5 | N84: 0.2 | P84: Nuova | S84: =IF(P84='Menu tendina'!A$5,0,IF(P84='Menu tendina'!A$4,'4. Telecom lire'!N84/2,IF(P84='Menu tendina'!A$3,'4. Telecom lire'!N84,IF(P84='Menu tendina'!A$2,'4. Telecom lire'!M84,0)))) -> 1.5
A85: 4. Pubbliche Figurate | B85: 3. Telecom lire | C85: 477B | D85: - | E85: - | F85: 5000 | G85: 30.06.97 | H85: Telefono pubblico | I85: Man | J85: Alfanumerica con A finale | K85: Variante | L85: - | M85: 0 | N85: 300 | P85: Manca | S85: =IF(P85='Menu tendina'!A$5,0,IF(P85='Menu tendina'!A$4,'4. Telecom lire'!N85/2,IF(P85='Menu tendina'!A$3,'4. Telecom lire'!N85,IF(P85='Menu tendina'!A$2,'4. Telecom lire'!M85,0)))) -> 0
A86: 4. Pubbliche Figurate | B86: 3. Telecom lire | C86: 478 | D86: 2532 | E86: 85 | F86: 10000 | G86: 30.06.97 | H86: Telefono pubblico | I86: Man | J86: Numerica | K86: - | L86: 13000 | M86: 1 | N86: 0.2 | P86: Nuova | S86: =IF(P86='Menu tendina'!A$5,0,IF(P86='Menu tendina'!A$4,'4. Telecom lire'!N86/2,IF(P86='Menu tendina'!A$3,'4. Telecom lire'!N86,IF(P86='Menu tendina'!A$2,'4. Telecom lire'!M86,0)))) -> 1
A87: 4. Pubbliche Figurate | B87: 3. Telecom lire | C87: 478A | D87: 2532A | E87: 85A | F87: 10000 | G87: 30.06.97 | H87: Telefono pubblico | I87: Man | J87: Alfanumerica | K87: Variante | L87: - | M87: 2.5 | N87: 0.2 | P87: Nuova | S87: =IF(P87='Menu tendina'!A$5,0,IF(P87='Menu tendina'!A$4,'4. Telecom lire'!N87/2,IF(P87='Menu tendina'!A$3,'4. Telecom lire'!N87,IF(P87='Menu tendina'!A$2,'4. Telecom lire'!M87,0)))) -> 2.5
A88: 4. Pubbliche Figurate | B88: 3. Telecom lire | C88: 479 | D88: 2533 | E88: 86 | F88: 15000 | G88: 30.06.97 | H88: Telefono pubblico | I88: Man | J88: Alfanumerica | K88: - | L88: 1000 | M88: 1 | N88: 0.2 | P88: Nuova | S88: =IF(P88='Menu tendina'!A$5,0,IF(P88='Menu tendina'!A$4,'4. Telecom lire'!N88/2,IF(P88='Menu tendina'!A$3,'4. Telecom lire'!N88,IF(P88='Menu tendina'!A$2,'4. Telecom lire'!M88,0)))) -> 1
A89: 4. Pubbliche Figurate | B89: 3. Telecom lire | C89: 479A | D89: 2533A | E89: 86A | F89: 15000 | G89: 30.06.97 | H89: Telefono pubblico | I89: Man | J89: Numerica | K89: Variante | L89: - | M89: - | N89: 300 | P89: Manca | S89: =IF(P89='Menu tendina'!A$5,0,IF(P89='Menu tendina'!A$4,'4. Telecom lire'!N89/2,IF(P89='Menu tendina'!A$3,'4. Telecom lire'!N89,IF(P89='Menu tendina'!A$2,'4. Telecom lire'!M89,0)))) -> 0
A90: 4. Pubbliche Figurate | B90: 3. Telecom lire | C90: 480 | D90: 2545 | E90: 87 | F90: 5000 | G90: 31.12.97 | H90: Telefono pubblico | I90: Tec | K90: - | L90: 5000 | M90: 1 | N90: 0.2 | P90: Nuova | S90: =IF(P90='Menu tendina'!A$5,0,IF(P90='Menu tendina'!A$4,'4. Telecom lire'!N90/2,IF(P90='Menu tendina'!A$3,'4. Telecom lire'!N90,IF(P90='Menu tendina'!A$2,'4. Telecom lire'!M90,0)))) -> 1
A91: 4. Pubbliche Figurate | B91: 3. Telecom lire | C91: 481 | D91: 2536 | E91: 82 | F91: 10000 | G91: 30.06.97 | H91: Vinitaly | I91: Man | K91: - | L91: 75 | M91: 1.5 | N91: 1 | P91: Nuova | S91: =IF(P91='Menu tendina'!A$5,0,IF(P91='Menu tendina'!A$4,'4. Telecom lire'!N91/2,IF(P91='Menu tendina'!A$3,'4. Telecom lire'!N91,IF(P91='Menu tendina'!A$2,'4. Telecom lire'!M91,0)))) -> 1.5
A92: 4. Pubbliche Figurate | B92: 3. Telecom lire | C92: 482 | D92: 2551 | E92: 113 | F92: 10000 | G92: 30.06.98 | H92: Un approdo sicuro | I92: Ces | K92: - | L92: 5000 | M92: 1 | N92: 0.2 | P92: Nuova | S92: =IF(P92='Menu tendina'!A$5,0,IF(P92='Menu tendina'!A$4,'4. Telecom lire'!N92/2,IF(P92='Menu tendina'!A$3,'4. Telecom lire'!N92,IF(P92='Menu tendina'!A$2,'4. Telecom lire'!M92,0)))) -> 1
A93: 4. Pubbliche Figurate | B93: 3. Telecom lire | C93: 483 | D93: 2538 | E93: 88 | F93: 5000 | G93: 31.12.97 | H93: Emporio Armani | I93: Man | K93: - | L93: 335 | M93: 1.3 | N93: 0.4 | P93: Nuova | S93: =IF(P93='Menu tendina'!A$5,0,IF(P93='Menu tendina'!A$4,'4. Telecom lire'!N93/2,IF(P93='Menu tendina'!A$3,'4. Telecom lire'!N93,IF(P93='Menu tendina'!A$2,'4. Telecom lire'!M93,0)))) -> 1.3
A94: 4. Pubbliche Figurate | B94: 3. Telecom lire | C94: 484 | D94: 2537 | E94: 89 | F94: 5000 | G94: 31.12.97 | H94: Emporio Armani | I94: Man | K94: - | L94: 335 | M94: 1.3 | N94: 0.4 | P94: Nuova | S94: =IF(P94='Menu tendina'!A$5,0,IF(P94='Menu tendina'!A$4,'4. Telecom lire'!N94/2,IF(P94='Menu tendina'!A$3,'4. Telecom lire'!N94,IF(P94='Menu tendina'!A$2,'4. Telecom lire'!M94,0)))) -> 1.3
A95: 4. Pubbliche Figurate | B95: 3. Telecom lire | C95: 485 | D95: 2540 | E95: 90 | F95: 5000 | G95: 31.12.97 | H95: Emporio Armani | I95: Man | K95: - | L95: 335 | M95: 1.3 | N95: 0.4 | P95: Nuova | S95: =IF(P95='Menu tendina'!A$5,0,IF(P95='Menu tendina'!A$4,'4. Telecom lire'!N95/2,IF(P95='Menu tendina'!A$3,'4. Telecom lire'!N95,IF(P95='Menu tendina'!A$2,'4. Telecom lire'!M95,0)))) -> 1.3
A96: 4. Pubbliche Figurate | B96: 3. Telecom lire | C96: 486 | D96: 2539 | E96: 91 | F96: 5000 | G96: 31.12.97 | H96: Emporio Armani | I96: Man | K96: - | L96: 335 | M96: 1.3 | N96: 0.4 | P96: Nuova | S96: =IF(P96='Menu tendina'!A$5,0,IF(P96='Menu tendina'!A$4,'4. Telecom lire'!N96/2,IF(P96='Menu tendina'!A$3,'4. Telecom lire'!N96,IF(P96='Menu tendina'!A$2,'4. Telecom lire'!M96,0)))) -> 1.3
A97: 4. Pubbliche Figurate | B97: 3. Telecom lire | C97: 487 | D97: 2541 | E97: 92 | F97: 10000 | G97: 31.12.97 | H97: Emporio Armani | I97: Man | K97: - | L97: 335 | M97: 1.3 | N97: 0.4 | P97: Nuova | S97: =IF(P97='Menu tendina'!A$5,0,IF(P97='Menu tendina'!A$4,'4. Telecom lire'!N97/2,IF(P97='Menu tendina'!A$3,'4. Telecom lire'!N97,IF(P97='Menu tendina'!A$2,'4. Telecom lire'!M97,0)))) -> 1.3
A98: 4. Pubbliche Figurate | B98: 3. Telecom lire | C98: 488 | D98: 2543 | E98: 93 | F98: 10000 | G98: 31.12.97 | H98: Emporio Armani | I98: Man | K98: - | L98: 335 | M98: 1.3 | N98: 0.4 | P98: Nuova | S98: =IF(P98='Menu tendina'!A$5,0,IF(P98='Menu tendina'!A$4,'4. Telecom lire'!N98/2,IF(P98='Menu tendina'!A$3,'4. Telecom lire'!N98,IF(P98='Menu tendina'!A$2,'4. Telecom lire'!M98,0)))) -> 1.3
A99: 4. Pubbliche Figurate | B99: 3. Telecom lire | C99: 489 | D99: 2542 | E99: 94 | F99: 10000 | G99: 31.12.97 | H99: Emporio Armani | I99: Man | K99: - | L99: 335 | M99: 1.3 | N99: 0.4 | P99: Nuova | S99: =IF(P99='Menu tendina'!A$5,0,IF(P99='Menu tendina'!A$4,'4. Telecom lire'!N99/2,IF(P99='Menu tendina'!A$3,'4. Telecom lire'!N99,IF(P99='Menu tendina'!A$2,'4. Telecom lire'!M99,0)))) -> 1.3
A100: 4. Pubbliche Figurate | B100: 3. Telecom lire | C100: 490 | D100: 2544 | E100: 95 | F100: 10000 | G100: 31.12.97 | H100: Emporio Armani | I100: Man | K100: - | L100: 335 | M100: 1.3 | N100: 0.4 | P100: Nuova | S100: =IF(P100='Menu tendina'!A$5,0,IF(P100='Menu tendina'!A$4,'4. Telecom lire'!N100/2,IF(P100='Menu tendina'!A$3,'4. Telecom lire'!N100,IF(P100='Menu tendina'!A$2,'4. Telecom lire'!M100,0)))) -> 1.3
A101: 4. Pubbliche Figurate | B101: 3. Telecom lire | C101: 491 | D101: 2547 | E101: 96 | F101: 5000 | G101: 31.12.97 | H101: Walt Disney - Pippo olimpionico | I101: Man | K101: - | L101: 40 | M101: 4 | N101: 2.5 | P101: Nuova | S101: =IF(P101='Menu tendina'!A$5,0,IF(P101='Menu tendina'!A$4,'4. Telecom lire'!N101/2,IF(P101='Menu tendina'!A$3,'4. Telecom lire'!N101,IF(P101='Menu tendina'!A$2,'4. Telecom lire'!M101,0)))) -> 4
... A186: 4. Pubbliche Figurate | B186: 3. Telecom lire | C186: 576 | D186: 2641 | E186: 181 | F186: 5000 | G186: 31.12.98 | H186: Giubileo | I186: Ces | K186: - | L186: 130 | M186: 1.3 | N186: 0.6 | P186: Nuova | S186: =IF(P186='Menu tendina'!A$5,0,IF(P186='Menu tendina'!A$4,'4. Telecom lire'!N186/2,IF(P186='Menu tendina'!A$3,'4. Telecom lire'!N186,IF(P186='Menu tendina'!A$2,'4. Telecom lire'!M186,0)))) -> 1.3
A187: 4. Pubbliche Figurate | B187: 3. Telecom lire | C187: 576A | D187: 2641A | E187: 181A | F187: 5000 | G187: 31.12.98 | H187: Giubileo | I187: Ces | J187: (N.E.)(N.M.) Scritta "FIRENZE" al posto di ROMA | K187: - | L187: - | M187: 100 | N187: 50 | P187: Nuova | Q187: n/a | S187: =IF(P187='Menu tendina'!A$5,0,IF(P187='Menu tendina'!A$4,'4. Telecom lire'!N187/2,IF(P187='Menu tendina'!A$3,'4. Telecom lire'!N187,IF(P187='Menu tendina'!A$2,'4. Telecom lire'!M187,0)))) -> 100
A188: 4. Pubbliche Figurate | B188: 3. Telecom lire | C188: 577 | D188: 2639 | E188: 182 | F188: 5000 | G188: 31.12.98 | H188: Mutuo casa - Caritro | I188: Tec | K188: - | L188: 69 | M188: 1.4 | N188: 0.8 | P188: Nuova | S188: =IF(P188='Menu tendina'!A$5,0,IF(P188='Menu tendina'!A$4,'4. Telecom lire'!N188/2,IF(P188='Menu tendina'!A$3,'4. Telecom lire'!N188,IF(P188='Menu tendina'!A$2,'4. Telecom lire'!M188,0)))) -> 1.4
A189: 4. Pubbliche Figurate | B189: 3. Telecom lire | C189: 578 | D189: 2640 | E189: 183 | F189: 10000 | G189: 31.12.98 | H189: Mutuo casa - Caritro | I189: Tec | K189: - | L189: 80 | M189: 1.4 | N189: 0.8 | P189: Nuova | S189: =IF(P189='Menu tendina'!A$5,0,IF(P189='Menu tendina'!A$4,'4. Telecom lire'!N189/2,IF(P189='Menu tendina'!A$3,'4. Telecom lire'!N189,IF(P189='Menu tendina'!A$2,'4. Telecom lire'!M189,0)))) -> 1.4
A190: 4. Pubbliche Figurate | B190: 3. Telecom lire | C190: 579 | D190: 2625 | E190: 184 | F190: 5000 | G190: 31.12.98 | H190: A Parigi e a Lione - Artesia | I190: Man | K190: - | L190: 160 | M190: 1.3 | N190: 0.6 | P190: Nuova | S190: =IF(P190='Menu tendina'!A$5,0,IF(P190='Menu tendina'!A$4,'4. Telecom lire'!N190/2,IF(P190='Menu tendina'!A$3,'4. Telecom lire'!N190,IF(P190='Menu tendina'!A$2,'4. Telecom lire'!M190,0)))) -> 1.3
A191: 4. Pubbliche Figurate | B191: 3. Telecom lire | C191: 580 | D191: 2626 | E191: 185 | F191: 10000 | G191: 31.12.98 | H191: A Parigi e a Lione - Artesia | I191: Man | K191: - | L191: 160 | M191: 1.3 | N191: 0.6 | P191: Nuova | S191: =IF(P191='Menu tendina'!A$5,0,IF(P191='Menu tendina'!A$4,'4. Telecom lire'!N191/2,IF(P191='Menu tendina'!A$3,'4. Telecom lire'!N191,IF(P191='Menu tendina'!A$2,'4. Telecom lire'!M191,0)))) -> 1.3
A192: 4. Pubbliche Figurate | B192: 3. Telecom lire | C192: 581 | D192: 2642 | E192: 186 | F192: 5000 | G192: 31.12.98 | H192: Aaattenti alla gola | I192: Man | K192: - | L192: 1790 | M192: 1 | N192: 0.2 | P192: Nuova | S192: =IF(P192='Menu tendina'!A$5,0,IF(P192='Menu tendina'!A$4,'4. Telecom lire'!N192/2,IF(P192='Menu tendina'!A$3,'4. Telecom lire'!N192,IF(P192='Menu tendina'!A$2,'4. Telecom lire'!M192,0)))) -> 1
A193: 4. Pubbliche Figurate | B193: 3. Telecom lire | C193: 582 | D193: 2630 | E193: 187 | F193: 5000 | G193: 31.12.98 | H193: Pietra Ligure - Bandiera Blu | I193: Tec | K193: - | L193: 99 | M193: 1.4 | N193: 0.6 | P193: Nuova | S193: =IF(P193='Menu tendina'!A$5,0,IF(P193='Menu tendina'!A$4,'4. Telecom lire'!N193/2,IF(P193='Menu tendina'!A$3,'4. Telecom lire'!N193,IF(P193='Menu tendina'!A$2,'4. Telecom lire'!M193,0)))) -> 1.4
A194: 4. Pubbliche Figurate | B194: 3. Telecom lire | C194: 583 | D194: 2644 | E194: 188 | F194: 5000 | G194: 31.12.98 | H194: Centralini InSip | I194: Man | K194: - | L194: 5000 | M194: 1 | N194: 0.2 | P194: Nuova | S194: =IF(P194='Menu tendina'!A$5,0,IF(P194='Menu tendina'!A$4,'4. Telecom lire'!N194/2,IF(P194='Menu tendina'!A$3,'4. Telecom lire'!N194,IF(P194='Menu tendina'!A$2,'4. Telecom lire'!M194,0)))) -> 1
A195: 4. Pubbliche Figurate | B195: 3. Telecom lire | C195: 584 | D195: 2645 | E195: 189 | F195: 10000 | G195: 31.12.98 | H195: Intercomunicanti e centralini InSip | I195: Tec | K195: - | L195: 3000 | M195: 1 | N195: 0.2 | P195: Nuova | S195: =IF(P195='Menu tendina'!A$5,0,IF(P195='Menu tendina'!A$4,'4. Telecom lire'!N195/2,IF(P195='Menu tendina'!A$3,'4. Telecom lire'!N195,IF(P195='Menu tendina'!A$2,'4. Telecom lire'!M195,0)))) -> 1
A196: 4. Pubbliche Figurate | B196: 3. Telecom lire | C196: 585 | D196: 2646 | E196: 190 | F196: 15000 | G196: 31.12.98 | H196: Fax InSip | I196: Ces | K196: - | L196: 1100 | M196: 1 | N196: 0.2 | P196: Nuova | S196: =IF(P196='Menu tendina'!A$5,0,IF(P196='Menu tendina'!A$4,'4. Telecom lire'!N196/2,IF(P196='Menu tendina'!A$3,'4. Telecom lire'!N196,IF(P196='Menu tendina'!A$2,'4. Telecom lire'!M196,0)))) -> 1
A197: 4. Pubbliche Figurate | B197: 3. Telecom lire | C197: 586 | D197: 2634 | E197: 191 | F197: 5000 | G197: 31.12.98 | H197: 1926-1996 ISTAT | I197: Man | K197: - | L197: 1100 | M197: 1 | N197: 0.2 | P197: Nuova | S197: =IF(P197='Menu tendina'!A$5,0,IF(P197='Menu tendina'!A$4,'4. Telecom lire'!N197/2,IF(P197='Menu tendina'!A$3,'4. Telecom lire'!N197,IF(P197='Menu tendina'!A$2,'4. Telecom lire'!M197,0)))) -> 1
A198: 4. Pubbliche Figurate | B198: 3. Telecom lire | C198: 587 | D198: 2638 | E198: 192 | F198: 5000 | G198: 31.12.98 | H198: Campionati italiani sci di fondo | I198: Man | K198: - | L198: 2000 | M198: 1 | N198: 0.2 | P198: Nuova | S198: =IF(P198='Menu tendina'!A$5,0,IF(P198='Menu tendina'!A$4,'4. Telecom lire'!N198/2,IF(P198='Menu tendina'!A$3,'4. Telecom lire'!N198,IF(P198='Menu tendina'!A$2,'4. Telecom lire'!M198,0)))) -> 1
A199: 4. Pubbliche Figurate | B199: 3. Telecom lire | C199: 588 | D199: 2647 | E199: 193 | F199: 5000 | G199: 30.06.99 | H199: Campionati mondiali di sci - Sestriere '97 | I199: Man | K199: - | L199: 2000 | M199: 1 | N199: 0.2 | P199: Nuova | S199: =IF(P199='Menu tendina'!A$5,0,IF(P199='Menu tendina'!A$4,'4. Telecom lire'!N199/2,IF(P199='Menu tendina'!A$3,'4. Telecom lire'!N199,IF(P199='Menu tendina'!A$2,'4. Telecom lire'!M199,0)))) -> 1
... A214: 4. Pubbliche Figurate | B214: 3. Telecom lire | C214: 603 | D214: 2662 | E214: 217 | F214: 5000 | G214: 30.06.99 | H214: Milanofil '97 | I214: Man | K214: - | L214: 65 | M214: 1.5 | N214: 0.8 | P214: Nuova | S214: =IF(P214='Menu tendina'!A$5,0,IF(P214='Menu tendina'!A$4,'4. Telecom lire'!N214/2,IF(P214='Menu tendina'!A$3,'4. Telecom lire'!N214,IF(P214='Menu tendina'!A$2,'4. Telecom lire'!M214,0)))) -> 1.5
A215: 4. Pubbliche Figurate | B215: 3. Telecom lire | C215: 604 | D215: 2661 | E215: 218 | F215: 5000 | G215: 30.06.99 | H215: Insieme si può | I215: Man | J215: Numerica | K215: - | L215: 5000 | M215: 1 | N215: 0.2 | P215: Nuova | S215: =IF(P215='Menu tendina'!A$5,0,IF(P215='Menu tendina'!A$4,'4. Telecom lire'!N215/2,IF(P215='Menu tendina'!A$3,'4. Telecom lire'!N215,IF(P215='Menu tendina'!A$2,'4. Telecom lire'!M215,0)))) -> 1
A216: 4. Pubbliche Figurate | B216: 3. Telecom lire | C216: 604A | D216: 2661A | E216: 218A | F216: 5000 | G216: 30.06.99 | H216: Insieme si può | I216: Man | J216: Betanumerica | K216: Variante | L216: - | M216: 10 | N216: 3 | P216: Nuova | S216: =IF(P216='Menu tendina'!A$5,0,IF(P216='Menu tendina'!A$4,'4. Telecom lire'!N216/2,IF(P216='Menu tendina'!A$3,'4. Telecom lire'!N216,IF(P216='Menu tendina'!A$2,'4. Telecom lire'!M216,0)))) -> 10
A217: 4. Pubbliche Figurate | B217: 3. Telecom lire | C217: 605 | D217: 2666 | E217: 225 | F217: 10000 | G217: 30.06.99 | H217: Parlate con più gusto - Panino | I217: Tec | K217: - | L217: 8000 | M217: 1 | N217: 0.2 | P217: Nuova | S217: =IF(P217='Menu tendina'!A$5,0,IF(P217='Menu tendina'!A$4,'4. Telecom lire'!N217/2,IF(P217='Menu tendina'!A$3,'4. Telecom lire'!N217,IF(P217='Menu tendina'!A$2,'4. Telecom lire'!M217,0)))) -> 1
A218: 4. Pubbliche Figurate | B218: 3. Telecom lire | C218: 605A | D218: 2666A | E218: - | F218: 10000 | G218: 30.06.99 | H218: Parlate con più gusto - Panino | I218: Tec | J218: Due punti dopo oltre | K218: Variante | L218: - | M218: 8 | N218: 0.7 | P218: Nuova | S218: =IF(P218='Menu tendina'!A$5,0,IF(P218='Menu tendina'!A$4,'4. Telecom lire'!N218/2,IF(P218='Menu tendina'!A$3,'4. Telecom lire'!N218,IF(P218='Menu tendina'!A$2,'4. Telecom lire'!M218,0)))) -> 8
A219: 4. Pubbliche Figurate | B219: 3. Telecom lire | C219: 606 | D219: 2665 | E219: 219 | F219: 5000 | G219: 30.06.99 | H219: Avete tanto da dire? | I219: Man | K219: - | L219: 5000 | M219: 1 | N219: 0.2 | P219: Nuova | S219: =IF(P219='Menu tendina'!A$5,0,IF(P219='Menu tendina'!A$4,'4. Telecom lire'!N219/2,IF(P219='Menu tendina'!A$3,'4. Telecom lire'!N219,IF(P219='Menu tendina'!A$2,'4. Telecom lire'!M219,0)))) -> 1
A220: 4. Pubbliche Figurate | B220: 3. Telecom lire | C220: 607 | D220: 2682 | E220: 220 | F220: 5000 | G220: 30.06.99 | H220: No - Dig '97 | I220: Tec | K220: - | L220: 1500 | M220: 1 | N220: 0.2 | P220: Nuova | S220: =IF(P220='Menu tendina'!A$5,0,IF(P220='Menu tendina'!A$4,'4. Telecom lire'!N220/2,IF(P220='Menu tendina'!A$3,'4. Telecom lire'!N220,IF(P220='Menu tendina'!A$2,'4. Telecom lire'!M220,0)))) -> 1
A221: 4. Pubbliche Figurate | B221: 3. Telecom lire | C221: 608 | D221: 2674 | E221: 198 | F221: 10000 | G221: 30.06.99 | H221: Non cercarla lontano - Mare | I221: Man | K221: - | L221: 5000 | M221: 1 | N221: 0.2 | P221: Nuova | S221: =IF(P221='Menu tendina'!A$5,0,IF(P221='Menu tendina'!A$4,'4. Telecom lire'!N221/2,IF(P221='Menu tendina'!A$3,'4. Telecom lire'!N221,IF(P221='Menu tendina'!A$2,'4. Telecom lire'!M221,0)))) -> 1
A222: 4. Pubbliche Figurate | B222: 3. Telecom lire | C222: 609 | D222: 2669 | E222: 221 | F222: 5000 | G222: 30.06.99 | H222: Bazar | I222: Ces | K222: - | L222: 80 | M222: 1.2 | N222: 0.8 | P222: Nuova | S222: =IF(P222='Menu tendina'!A$5,0,IF(P222='Menu tendina'!A$4,'4. Telecom lire'!N222/2,IF(P222='Menu tendina'!A$3,'4. Telecom lire'!N222,IF(P222='Menu tendina'!A$2,'4. Telecom lire'!M222,0)))) -> 1.2
A223: 4. Pubbliche Figurate | B223: 3. Telecom lire | C223: 610 | D223: 2672 | E223: 222 | F223: 5000 | G223: 30.06.99 | H223: Edizioni CxT | I223: Ces | K223: - | L223: 330 | M223: 1 | N223: 0.4 | P223: Nuova | S223: =IF(P223='Menu tendina'!A$5,0,IF(P223='Menu tendina'!A$4,'4. Telecom lire'!N223/2,IF(P223='Menu tendina'!A$3,'4. Telecom lire'!N223,IF(P223='Menu tendina'!A$2,'4. Telecom lire'!M223,0)))) -> 1
A224: 4. Pubbliche Figurate | B224: 3. Telecom lire | C224: 611 | D224: 2671 | E224: 223 | F224: 5000 | G224: 30.06.99 | H224: Exact collezioni | I224: Tec | K224: - | L224: 279 | M224: 1.3 | N224: 0.6 | P224: Nuova | S224: =IF(P224='Menu tendina'!A$5,0,IF(P224='Menu tendina'!A$4,'4. Telecom lire'!N224/2,IF(P224='Menu tendina'!A$3,'4. Telecom lire'!N224,IF(P224='Menu tendina'!A$2,'4. Telecom lire'!M224,0)))) -> 1.3
A225: 4. Pubbliche Figurate | B225: 3. Telecom lire | C225: 612 | D225: 2667 | E225: 224 | F225: 15000 | G225: 30.06.99 | H225: Marathon des sables | I225: Ces | K225: - | L225: 325 | M225: 1.3 | N225: 0.4 | P225: Nuova | S225: =IF(P225='Menu tendina'!A$5,0,IF(P225='Menu tendina'!A$4,'4. Telecom lire'!N225/2,IF(P225='Menu tendina'!A$3,'4. Telecom lire'!N225,IF(P225='Menu tendina'!A$2,'4. Telecom lire'!M225,0)))) -> 1.3
A226: 4. Pubbliche Figurate | B226: 3. Telecom lire | C226: 613 | D226: 2668 | E226: 233 | F226: 10000 | G226: 30.06.99 | H226: Futurshow 1997 | I226: Man | K226: - | L226: 75 | M226: 1.5 | N226: 0.8 | P226: Nuova | S226: =IF(P226='Menu tendina'!A$5,0,IF(P226='Menu tendina'!A$4,'4. Telecom lire'!N226/2,IF(P226='Menu tendina'!A$3,'4. Telecom lire'!N226,IF(P226='Menu tendina'!A$2,'4. Telecom lire'!M226,0)))) -> 1.5
A227: 4. Pubbliche Figurate | B227: 3. Telecom lire | C227: 614 | D227: 2664 | E227: 234 | F227: 10000 | G227: 30.06.99 | H227: Memotel "Numerica" | I227: Man | K227: - | L227: 5000 | M227: 1 | N227: 0.2 | P227: Nuova | S227: =IF(P227='Menu tendina'!A$5,0,IF(P227='Menu tendina'!A$4,'4. Telecom lire'!N227/2,IF(P227='Menu tendina'!A$3,'4. Telecom lire'!N227,IF(P227='Menu tendina'!A$2,'4. Telecom lire'!M227,0)))) -> 1
A228: 4. Pubbliche Figurate | B228: 3. Telecom lire | C228: 614A | D228: 2664A | E228: 234A | F228: 10000 | G228: 30.06.99 | H228: Memotel | I228: Man | J228: Alfanumerica | K228: Variante | L228: - | M228: 10 | N228: 2 | P228: Nuova | S228: =IF(P228='Menu tendina'!A$5,0,IF(P228='Menu tendina'!A$4,'4. Telecom lire'!N228/2,IF(P228='Menu tendina'!A$3,'4. Telecom lire'!N228,IF(P228='Menu tendina'!A$2,'4. Telecom lire'!M228,0)))) -> 10
